Workbook
Name L_ActivityStatus: Lists!$B$5:$B$11
Name L_Owners: Lists!$E$5:$E$34
Name L_Qual: Lists!$C$5:$C$10
Name L_Rating: Lists!$D$5:$D$8
Name L_Types: Lists!$F$5:$F$18
Name L_VendorStatus: Lists!$A$5:$A$13
Name P_Names: Projects!$B$5:$B$54
Name V_Names: Vendors!$B$5:$B$400

Sheet Read Me
A1: RFI Tracker
A2: Agentic Procurement | Internal - do not share vendor data outside Agentic | Owner: Jason Knedlhans
A4: Version | B4: 1.0
A5: Version date | B5: 46300
A6: Live file | B6: RFI-Tracker.xlsx in the Procurement SharePoint library (AI Procurement > artifacts > rfi-tracker). Always open it from SharePoint; do not keep local copies.
A7: Status | B7: In review
A9: PURPOSE
A10: What | B10: One file for every RFI activity. Each RFI activity is its own tab, tied to one project and one vendor type, and lists the invited vendors with contacts, RFI status, last contact, qualification status, key item responses and ratings, and the next action, owner and date.
A12: TABS
A13: Dashboard | B13: Live totals by vendor type and by project.
A14: RFI Register | B14: Index of all RFI activities. Type the RFI ID; the rest fills from that tab.
A15: RFI-001 | B15: Example RFI (BESS vendors, placeholder project). Repurpose it for the first real RFI or delete it and its Register row.
A16: RFI_TEMPLATE | B16: Blank RFI tab. Copy it for each new RFI activity; never type data into the template itself.
A17: Vendors | B17: Master vendor and contact list. RFI tabs pull contacts from here, so update contacts here only.
A18: Key Items | B18: Default 5-7 key items per vendor type (10 slots). Drives the key item headers on RFI tabs.
A19: Projects | B19: Project list for the Project dropdown. Rename the placeholders.
A20: Lists | B20: Dropdown values (statuses, ratings, owners).
A21: Change Log | B21: Record of structural changes and new RFI tabs.
A23: ADD A NEW RFI ACTIVITY
A24: 1. Copy the template | B24: Right-click the RFI_TEMPLATE tab > Move or Copy > tick Create a copy > OK. (Excel for the web: right-click > Duplicate.)
A25: 2. Rename the tab | B25: Use the next RFI ID, e.g. RFI-002. Keep it short, no spaces.
A26: 3. Fill the header | B26: C3 RFI ID (same as tab name), C4 Project, C5 Vendor Type, title, owner, dates, status. Key item headers fill automatically from the vendor type.
A27: 4. Add vendors | B27: Pick vendors in column A (dropdown from the Vendors tab). Add a missing vendor to the Vendors tab first.
A28: 5. Register it | B28: Type the RFI ID in the next empty row of the RFI Register, then add a Change Log line.
A30: KEY ITEMS
A31: Change a header | B31: For this RFI only: type over the header in row 13 of the RFI tab. For all RFIs of a vendor type: edit the Key Items tab.
A32: Add a key item | B32: Type a name into a spare slot (shown as 'spare - type a name'), either on the RFI tab or on the Key Items tab.
A33: Rating | B33: Meets / Review / Risk / Fails / Not Rated. Fails and Review / Risk roll up to the tab summary, Register and Dashboard.
A35: CELL COLORS
A36: Yellow | B36: Enter or edit data.
A37: Grey | B37: Formula. Do not overwrite (exception: key item headers in row 13).
A38: Red / amber | B38: Overdue actions, Fails ratings, or a Register row whose tab name does not match.
A40: VERSION CONTROL
A41: Live file | B41: One file, one name, one link. Everyone edits the SharePoint copy in place (co-authoring with AutoSave on). Do not download, edit offline and re-upload, and do not Save As a new name.
A42: Version history | B42: SharePoint keeps every saved version automatically. To see or restore: File > Info > Version History (desktop) or the file's ... menu > Version history (SharePoint).
A43: Version number | B43: Major (2.0): structural change - new or removed columns, tabs other than new RFI tabs, formula changes. Minor (1.1): list or key item default changes, new RFI tab. Update the Version cell above and add a Change Log line for both.
A44: Snapshots | B44: Before a major version, save a dated copy to artifacts/archive/rfi-tracker/ (e.g. 2026-10-05_rfi-tracker_v1.0.xlsx).
A45: Data entry | B45: Routine updates (statuses, dates, responses) need no Change Log line; version history records them.
A47: DATA NOTES / RISKS
A48: Vendor data | B48: Vendors tab seeded 2026-10-05 from the vendor landscape tracker. It is AI-seeded from public sources and unverified; no named contacts yet. Mark Data Verified? = Yes once confirmed with the vendor.
A49: Two vendor lists | B49: The vendor landscape tracker also holds vendors. Treat this file's Vendors tab as the contact record for RFIs, or agree another system of record.
A50: Confidentiality | B50: Internal. Vendor responses may include pricing or confidential data; do not share outside Agentic.
A51: Tab names | B51: Register formulas find RFI tabs by name. Renaming a tab breaks its Register row (shows 'Tab not found' in red) until the RFI ID in column A is updated.

Sheet Dashboard
A1: Dashboard
A2: Live totals from the RFI Register. Closed and cancelled RFIs are excluded from Active RFIs.
A4: Active RFIs | B4: Total RFIs | C4: Vendors invited | D4: RFIs sent | E4: Responses | F4: Actions overdue | G4: Key item fails
A5: =COUNTIFS('RFI Register'!$A$5:$A$104,"<>",'RFI Register'!$H$5:$H$104,"<>Closed*",'RFI Register'!$H$5:$H$104,"<>Cancelled") -> 1 | B5: =COUNTA('RFI Register'!$A$5:$A$104) -> 1 | C5: =SUM('RFI Register'!$I$5:$I$104) -> 10 | D5: =SUM('RFI Register'!$J$5:$J$104) -> 0 | E5: =SUM('RFI Register'!$K$5:$K$104) -> 0 | F5: =SUM('RFI Register'!$L$5:$L$104) -> 0 | G5: =SUM('RFI Register'!$M$5:$M$104) -> 0
A7: By vendor type
A8: Vendor Type | B8: RFIs | C8: Active | D8: Vendors Invited | E8: Responses | F8: Actions Overdue | G8: Key Item Fails
A9: Environmental Engineering | B9: =IF($A9="","",COUNTIF('RFI Register'!$C$5:$C$104,$A9)) -> 0 | C9: =IF($A9="","",COUNTIFS('RFI Register'!$C$5:$C$104,$A9,'RFI Register'!$H$5:$H$104,"<>Closed*",'RFI Register'!$H$5:$H$104,"<>Cancelled")) -> 0 | D9: =IF($A9="","",SUMIF('RFI Register'!$C$5:$C$104,$A9,'RFI Register'!$I$5:$I$104)) -> 0 | E9: =IF($A9="","",SUMIF('RFI Register'!$C$5:$C$104,$A9,'RFI Register'!$K$5:$K$104)) -> 0 | F9: =IF($A9="","",SUMIF('RFI Register'!$C$5:$C$104,$A9,'RFI Register'!$L$5:$L$104)) -> 0 | G9: =IF($A9="","",SUMIF('RFI Register'!$C$5:$C$104,$A9,'RFI Register'!$M$5:$M$104)) -> 0
A10: Civil Engineering | B10: =IF($A10="","",COUNTIF('RFI Register'!$C$5:$C$104,$A10)) -> 0 | C10: =IF($A10="","",COUNTIFS('RFI Register'!$C$5:$C$104,$A10,'RFI Register'!$H$5:$H$104,"<>Closed*",'RFI Register'!$H$5:$H$104,"<>Cancelled")) -> 0 | D10: =IF($A10="","",SUMIF('RFI Register'!$C$5:$C$104,$A10,'RFI Register'!$I$5:$I$104)) -> 0 | E10: =IF($A10="","",SUMIF('RFI Register'!$C$5:$C$104,$A10,'RFI Register'!$K$5:$K$104)) -> 0 | F10: =IF($A10="","",SUMIF('RFI Register'!$C$5:$C$104,$A10,'RFI Register'!$L$5:$L$104)) -> 0 | G10: =IF($A10="","",SUMIF('RFI Register'!$C$5:$C$104,$A10,'RFI Register'!$M$5:$M$104)) -> 0
A11: Structural Engineering | B11: =IF($A11="","",COUNTIF('RFI Register'!$C$5:$C$104,$A11)) -> 0 | C11: =IF($A11="","",COUNTIFS('RFI Register'!$C$5:$C$104,$A11,'RFI Register'!$H$5:$H$104,"<>Closed*",'RFI Register'!$H$5:$H$104,"<>Cancelled")) -> 0 | D11: =IF($A11="","",SUMIF('RFI Register'!$C$5:$C$104,$A11,'RFI Register'!$I$5:$I$104)) -> 0 | E11: =IF($A11="","",SUMIF('RFI Register'!$C$5:$C$104,$A11,'RFI Register'!$K$5:$K$104)) -> 0 | F11: =IF($A11="","",SUMIF('RFI Register'!$C$5:$C$104,$A11,'RFI Register'!$L$5:$L$104)) -> 0 | G11: =IF($A11="","",SUMIF('RFI Register'!$C$5:$C$104,$A11,'RFI Register'!$M$5:$M$104)) -> 0
A12: Electrical Engineering | B12: =IF($A12="","",COUNTIF('RFI Register'!$C$5:$C$104,$A12)) -> 0 | C12: =IF($A12="","",COUNTIFS('RFI Register'!$C$5:$C$104,$A12,'RFI Register'!$H$5:$H$104,"<>Closed*",'RFI Register'!$H$5:$H$104,"<>Cancelled")) -> 0 | D12: =IF($A12="","",SUMIF('RFI Register'!$C$5:$C$104,$A12,'RFI Register'!$I$5:$I$104)) -> 0 | E12: =IF($A12="","",SUMIF('RFI Register'!$C$5:$C$104,$A12,'RFI Register'!$K$5:$K$104)) -> 0 | F12: =IF($A12="","",SUMIF('RFI Register'!$C$5:$C$104,$A12,'RFI Register'!$L$5:$L$104)) -> 0 | G12: =IF($A12="","",SUMIF('RFI Register'!$C$5:$C$104,$A12,'RFI Register'!$M$5:$M$104)) -> 0
A13: Fire Protection Engineering | B13: =IF($A13="","",COUNTIF('RFI Register'!$C$5:$C$104,$A13)) -> 0 | C13: =IF($A13="","",COUNTIFS('RFI Register'!$C$5:$C$104,$A13,'RFI Register'!$H$5:$H$104,"<>Closed*",'RFI Register'!$H$5:$H$104,"<>Cancelled")) -> 0 | D13: =IF($A13="","",SUMIF('RFI Register'!$C$5:$C$104,$A13,'RFI Register'!$I$5:$I$104)) -> 0 | E13: =IF($A13="","",SUMIF('RFI Register'!$C$5:$C$104,$A13,'RFI Register'!$K$5:$K$104)) -> 0 | F13: =IF($A13="","",SUMIF('RFI Register'!$C$5:$C$104,$A13,'RFI Register'!$L$5:$L$104)) -> 0 | G13: =IF($A13="","",SUMIF('RFI Register'!$C$5:$C$104,$A13,'RFI Register'!$M$5:$M$104)) -> 0
A14: Owner's Engineer | B14: =IF($A14="","",COUNTIF('RFI Register'!$C$5:$C$104,$A14)) -> 0 | C14: =IF($A14="","",COUNTIFS('RFI Register'!$C$5:$C$104,$A14,'RFI Register'!$H$5:$H$104,"<>Closed*",'RFI Register'!$H$5:$H$104,"<>Cancelled")) -> 0 | D14: =IF($A14="","",SUMIF('RFI Register'!$C$5:$C$104,$A14,'RFI Register'!$I$5:$I$104)) -> 0 | E14: =IF($A14="","",SUMIF('RFI Register'!$C$5:$C$104,$A14,'RFI Register'!$K$5:$K$104)) -> 0 | F14: =IF($A14="","",SUMIF('RFI Register'!$C$5:$C$104,$A14,'RFI Register'!$L$5:$L$104)) -> 0 | G14: =IF($A14="","",SUMIF('RFI Register'!$C$5:$C$104,$A14,'RFI Register'!$M$5:$M$104)) -> 0
A15: Engineer of Record | B15: =IF($A15="","",COUNTIF('RFI Register'!$C$5:$C$104,$A15)) -> 0 | C15: =IF($A15="","",COUNTIFS('RFI Register'!$C$5:$C$104,$A15,'RFI Register'!$H$5:$H$104,"<>Closed*",'RFI Register'!$H$5:$H$104,"<>Cancelled")) -> 0 | D15: =IF($A15="","",SUMIF('RFI Register'!$C$5:$C$104,$A15,'RFI Register'!$I$5:$I$104)) -> 0 | E15: =IF($A15="","",SUMIF('RFI Register'!$C$5:$C$104,$A15,'RFI Register'!$K$5:$K$104)) -> 0 | F15: =IF($A15="","",SUMIF('RFI Register'!$C$5:$C$104,$A15,'RFI Register'!$L$5:$L$104)) -> 0 | G15: =IF($A15="","",SUMIF('RFI Register'!$C$5:$C$104,$A15,'RFI Register'!$M$5:$M$104)) -> 0
A16: Independent Engineer | B16: =IF($A16="","",COUNTIF('RFI Register'!$C$5:$C$104,$A16)) -> 0 | C16: =IF($A16="","",COUNTIFS('RFI Register'!$C$5:$C$104,$A16,'RFI Register'!$H$5:$H$104,"<>Closed*",'RFI Register'!$H$5:$H$104,"<>Cancelled")) -> 0 | D16: =IF($A16="","",SUMIF('RFI Register'!$C$5:$C$104,$A16,'RFI Register'!$I$5:$I$104)) -> 0 | E16: =IF($A16="","",SUMIF('RFI Register'!$C$5:$C$104,$A16,'RFI Register'!$K$5:$K$104)) -> 0 | F16: =IF($A16="","",SUMIF('RFI Register'!$C$5:$C$104,$A16,'RFI Register'!$L$5:$L$104)) -> 0 | G16: =IF($A16="","",SUMIF('RFI Register'!$C$5:$C$104,$A16,'RFI Register'!$M$5:$M$104)) -> 0
A17: BESS Equipment | B17: =IF($A17="","",COUNTIF('RFI Register'!$C$5:$C$104,$A17)) -> 1 | C17: =IF($A17="","",COUNTIFS('RFI Register'!$C$5:$C$104,$A17,'RFI Register'!$H$5:$H$104,"<>Closed*",'RFI Register'!$H$5:$H$104,"<>Cancelled")) -> 1 | D17: =IF($A17="","",SUMIF('RFI Register'!$C$5:$C$104,$A17,'RFI Register'!$I$5:$I$104)) -> 10 | E17: =IF($A17="","",SUMIF('RFI Register'!$C$5:$C$104,$A17,'RFI Register'!$K$5:$K$104)) -> 0 | F17: =IF($A17="","",SUMIF('RFI Register'!$C$5:$C$104,$A17,'RFI Register'!$L$5:$L$104)) -> 0 | G17: =IF($A17="","",SUMIF('RFI Register'!$C$5:$C$104,$A17,'RFI Register'!$M$5:$M$104)) -> 0
A18: MV Transformers | B18: =IF($A18="","",COUNTIF('RFI Register'!$C$5:$C$104,$A18)) -> 0 | C18: =IF($A18="","",COUNTIFS('RFI Register'!$C$5:$C$104,$A18,'RFI Register'!$H$5:$H$104,"<>Closed*",'RFI Register'!$H$5:$H$104,"<>Cancelled")) -> 0 | D18: =IF($A18="","",SUMIF('RFI Register'!$C$5:$C$104,$A18,'RFI Register'!$I$5:$I$104)) -> 0 | E18: =IF($A18="","",SUMIF('RFI Register'!$C$5:$C$104,$A18,'RFI Register'!$K$5:$K$104)) -> 0 | F18: =IF($A18="","",SUMIF('RFI Register'!$C$5:$C$104,$A18,'RFI Register'!$L$5:$L$104)) -> 0 | G18: =IF($A18="","",SUMIF('RFI Register'!$C$5:$C$104,$A18,'RFI Register'!$M$5:$M$104)) -> 0
A19: HV Breakers | B19: =IF($A19="","",COUNTIF('RFI Register'!$C$5:$C$104,$A19)) -> 0 | C19: =IF($A19="","",COUNTIFS('RFI Register'!$C$5:$C$104,$A19,'RFI Register'!$H$5:$H$104,"<>Closed*",'RFI Register'!$H$5:$H$104,"<>Cancelled")) -> 0 | D19: =IF($A19="","",SUMIF('RFI Register'!$C$5:$C$104,$A19,'RFI Register'!$I$5:$I$104)) -> 0 | E19: =IF($A19="","",SUMIF('RFI Register'!$C$5:$C$104,$A19,'RFI Register'!$K$5:$K$104)) -> 0 | F19: =IF($A19="","",SUMIF('RFI Register'!$C$5:$C$104,$A19,'RFI Register'!$L$5:$L$104)) -> 0 | G19: =IF($A19="","",SUMIF('RFI Register'!$C$5:$C$104,$A19,'RFI Register'!$M$5:$M$104)) -> 0
A20: MV Breakers / Switchgear | B20: =IF($A20="","",COUNTIF('RFI Register'!$C$5:$C$104,$A20)) -> 0 | C20: =IF($A20="","",COUNTIFS('RFI Register'!$C$5:$C$104,$A20,'RFI Register'!$H$5:$H$104,"<>Closed*",'RFI Register'!$H$5:$H$104,"<>Cancelled")) -> 0 | D20: =IF($A20="","",SUMIF('RFI Register'!$C$5:$C$104,$A20,'RFI Register'!$I$5:$I$104)) -> 0 | E20: =IF($A20="","",SUMIF('RFI Register'!$C$5:$C$104,$A20,'RFI Register'!$K$5:$K$104)) -> 0 | F20: =IF($A20="","",SUMIF('RFI Register'!$C$5:$C$104,$A20,'RFI Register'!$L$5:$L$104)) -> 0 | G20: =IF($A20="","",SUMIF('RFI Register'!$C$5:$C$104,$A20,'RFI Register'!$M$5:$M$104)) -> 0
... A22: Software | B22: =IF($A22="","",COUNTIF('RFI Register'!$C$5:$C$104,$A22)) -> 0 | C22: =IF($A22="","",COUNTIFS('RFI Register'!$C$5:$C$104,$A22,'RFI Register'!$H$5:$H$104,"<>Closed*",'RFI Register'!$H$5:$H$104,"<>Cancelled")) -> 0 | D22: =IF($A22="","",SUMIF('RFI Register'!$C$5:$C$104,$A22,'RFI Register'!$I$5:$I$104)) -> 0 | E22: =IF($A22="","",SUMIF('RFI Register'!$C$5:$C$104,$A22,'RFI Register'!$K$5:$K$104)) -> 0 | F22: =IF($A22="","",SUMIF('RFI Register'!$C$5:$C$104,$A22,'RFI Register'!$L$5:$L$104)) -> 0 | G22: =IF($A22="","",SUMIF('RFI Register'!$C$5:$C$104,$A22,'RFI Register'!$M$5:$M$104)) -> 0
A24: By project
A25: Project | B25: RFIs | C25: Active | D25: Vendors Invited | E25: Responses | F25: Actions Overdue | G25: Key Item Fails
A26: =IF(Projects!$B$5="","",Projects!$B$5) -> Seven Angels BESS | B26: =IF($A26="","",COUNTIF('RFI Register'!$B$5:$B$104,$A26)) -> 0 | C26: =IF($A26="","",COUNTIFS('RFI Register'!$B$5:$B$104,$A26,'RFI Register'!$H$5:$H$104,"<>Closed*",'RFI Register'!$H$5:$H$104,"<>Cancelled")) -> 0 | D26: =IF($A26="","",SUMIF('RFI Register'!$B$5:$B$104,$A26,'RFI Register'!$I$5:$I$104)) -> 0 | E26: =IF($A26="","",SUMIF('RFI Register'!$B$5:$B$104,$A26,'RFI Register'!$K$5:$K$104)) -> 0 | F26: =IF($A26="","",SUMIF('RFI Register'!$B$5:$B$104,$A26,'RFI Register'!$L$5:$L$104)) -> 0 | G26: =IF($A26="","",SUMIF('RFI Register'!$B$5:$B$104,$A26,'RFI Register'!$M$5:$M$104)) -> 0
A27: =IF(Projects!$B$6="","",Projects!$B$6) -> Project B (placeholder - rename) | B27: =IF($A27="","",COUNTIF('RFI Register'!$B$5:$B$104,$A27)) -> 0 | C27: =IF($A27="","",COUNTIFS('RFI Register'!$B$5:$B$104,$A27,'RFI Register'!$H$5:$H$104,"<>Closed*",'RFI Register'!$H$5:$H$104,"<>Cancelled")) -> 0 | D27: =IF($A27="","",SUMIF('RFI Register'!$B$5:$B$104,$A27,'RFI Register'!$I$5:$I$104)) -> 0 | E27: =IF($A27="","",SUMIF('RFI Register'!$B$5:$B$104,$A27,'RFI Register'!$K$5:$K$104)) -> 0 | F27: =IF($A27="","",SUMIF('RFI Register'!$B$5:$B$104,$A27,'RFI Register'!$L$5:$L$104)) -> 0 | G27: =IF($A27="","",SUMIF('RFI Register'!$B$5:$B$104,$A27,'RFI Register'!$M$5:$M$104)) -> 0
A28: =IF(Projects!$B$7="","",Projects!$B$7) -> Project C (placeholder - rename) | B28: =IF($A28="","",COUNTIF('RFI Register'!$B$5:$B$104,$A28)) -> 0 | C28: =IF($A28="","",COUNTIFS('RFI Register'!$B$5:$B$104,$A28,'RFI Register'!$H$5:$H$104,"<>Closed*",'RFI Register'!$H$5:$H$104,"<>Cancelled")) -> 0 | D28: =IF($A28="","",SUMIF('RFI Register'!$B$5:$B$104,$A28,'RFI Register'!$I$5:$I$104)) -> 0 | E28: =IF($A28="","",SUMIF('RFI Register'!$B$5:$B$104,$A28,'RFI Register'!$K$5:$K$104)) -> 0 | F28: =IF($A28="","",SUMIF('RFI Register'!$B$5:$B$104,$A28,'RFI Register'!$L$5:$L$104)) -> 0 | G28: =IF($A28="","",SUMIF('RFI Register'!$B$5:$B$104,$A28,'RFI Register'!$M$5:$M$104)) -> 0
A29: =IF(Projects!$B$8="","",Projects!$B$8) | B29: =IF($A29="","",COUNTIF('RFI Register'!$B$5:$B$104,$A29)) | C29: =IF($A29="","",COUNTIFS('RFI Register'!$B$5:$B$104,$A29,'RFI Register'!$H$5:$H$104,"<>Closed*",'RFI Register'!$H$5:$H$104,"<>Cancelled")) | D29: =IF($A29="","",SUMIF('RFI Register'!$B$5:$B$104,$A29,'RFI Register'!$I$5:$I$104)) | E29: =IF($A29="","",SUMIF('RFI Register'!$B$5:$B$104,$A29,'RFI Register'!$K$5:$K$104)) | F29: =IF($A29="","",SUMIF('RFI Register'!$B$5:$B$104,$A29,'RFI Register'!$L$5:$L$104)) | G29: =IF($A29="","",SUMIF('RFI Register'!$B$5:$B$104,$A29,'RFI Register'!$M$5:$M$104))
A30: =IF(Projects!$B$9="","",Projects!$B$9) | B30: =IF($A30="","",COUNTIF('RFI Register'!$B$5:$B$104,$A30)) | C30: =IF($A30="","",COUNTIFS('RFI Register'!$B$5:$B$104,$A30,'RFI Register'!$H$5:$H$104,"<>Closed*",'RFI Register'!$H$5:$H$104,"<>Cancelled")) | D30: =IF($A30="","",SUMIF('RFI Register'!$B$5:$B$104,$A30,'RFI Register'!$I$5:$I$104)) | E30: =IF($A30="","",SUMIF('RFI Register'!$B$5:$B$104,$A30,'RFI Register'!$K$5:$K$104)) | F30: =IF($A30="","",SUMIF('RFI Register'!$B$5:$B$104,$A30,'RFI Register'!$L$5:$L$104)) | G30: =IF($A30="","",SUMIF('RFI Register'!$B$5:$B$104,$A30,'RFI Register'!$M$5:$M$104))
A31: =IF(Projects!$B$10="","",Projects!$B$10) | B31: =IF($A31="","",COUNTIF('RFI Register'!$B$5:$B$104,$A31)) | C31: =IF($A31="","",COUNTIFS('RFI Register'!$B$5:$B$104,$A31,'RFI Register'!$H$5:$H$104,"<>Closed*",'RFI Register'!$H$5:$H$104,"<>Cancelled")) | D31: =IF($A31="","",SUMIF('RFI Register'!$B$5:$B$104,$A31,'RFI Register'!$I$5:$I$104)) | E31: =IF($A31="","",SUMIF('RFI Register'!$B$5:$B$104,$A31,'RFI Register'!$K$5:$K$104)) | F31: =IF($A31="","",SUMIF('RFI Register'!$B$5:$B$104,$A31,'RFI Register'!$L$5:$L$104)) | G31: =IF($A31="","",SUMIF('RFI Register'!$B$5:$B$104,$A31,'RFI Register'!$M$5:$M$104))
A32: =IF(Projects!$B$11="","",Projects!$B$11) | B32: =IF($A32="","",COUNTIF('RFI Register'!$B$5:$B$104,$A32)) | C32: =IF($A32="","",COUNTIFS('RFI Register'!$B$5:$B$104,$A32,'RFI Register'!$H$5:$H$104,"<>Closed*",'RFI Register'!$H$5:$H$104,"<>Cancelled")) | D32: =IF($A32="","",SUMIF('RFI Register'!$B$5:$B$104,$A32,'RFI Register'!$I$5:$I$104)) | E32: =IF($A32="","",SUMIF('RFI Register'!$B$5:$B$104,$A32,'RFI Register'!$K$5:$K$104)) | F32: =IF($A32="","",SUMIF('RFI Register'!$B$5:$B$104,$A32,'RFI Register'!$L$5:$L$104)) | G32: =IF($A32="","",SUMIF('RFI Register'!$B$5:$B$104,$A32,'RFI Register'!$M$5:$M$104))
A33: =IF(Projects!$B$12="","",Projects!$B$12) | B33: =IF($A33="","",COUNTIF('RFI Register'!$B$5:$B$104,$A33)) | C33: =IF($A33="","",COUNTIFS('RFI Register'!$B$5:$B$104,$A33,'RFI Register'!$H$5:$H$104,"<>Closed*",'RFI Register'!$H$5:$H$104,"<>Cancelled")) | D33: =IF($A33="","",SUMIF('RFI Register'!$B$5:$B$104,$A33,'RFI Register'!$I$5:$I$104)) | E33: =IF($A33="","",SUMIF('RFI Register'!$B$5:$B$104,$A33,'RFI Register'!$K$5:$K$104)) | F33: =IF($A33="","",SUMIF('RFI Register'!$B$5:$B$104,$A33,'RFI Register'!$L$5:$L$104)) | G33: =IF($A33="","",SUMIF('RFI Register'!$B$5:$B$104,$A33,'RFI Register'!$M$5:$M$104))
A34: =IF(Projects!$B$13="","",Projects!$B$13) | B34: =IF($A34="","",COUNTIF('RFI Register'!$B$5:$B$104,$A34)) | C34: =IF($A34="","",COUNTIFS('RFI Register'!$B$5:$B$104,$A34,'RFI Register'!$H$5:$H$104,"<>Closed*",'RFI Register'!$H$5:$H$104,"<>Cancelled")) | D34: =IF($A34="","",SUMIF('RFI Register'!$B$5:$B$104,$A34,'RFI Register'!$I$5:$I$104)) | E34: =IF($A34="","",SUMIF('RFI Register'!$B$5:$B$104,$A34,'RFI Register'!$K$5:$K$104)) | F34: =IF($A34="","",SUMIF('RFI Register'!$B$5:$B$104,$A34,'RFI Register'!$L$5:$L$104)) | G34: =IF($A34="","",SUMIF('RFI Register'!$B$5:$B$104,$A34,'RFI Register'!$M$5:$M$104))
A35: =IF(Projects!$B$14="","",Projects!$B$14) | B35: =IF($A35="","",COUNTIF('RFI Register'!$B$5:$B$104,$A35)) | C35: =IF($A35="","",COUNTIFS('RFI Register'!$B$5:$B$104,$A35,'RFI Register'!$H$5:$H$104,"<>Closed*",'RFI Register'!$H$5:$H$104,"<>Cancelled")) | D35: =IF($A35="","",SUMIF('RFI Register'!$B$5:$B$104,$A35,'RFI Register'!$I$5:$I$104)) | E35: =IF($A35="","",SUMIF('RFI Register'!$B$5:$B$104,$A35,'RFI Register'!$K$5:$K$104)) | F35: =IF($A35="","",SUMIF('RFI Register'!$B$5:$B$104,$A35,'RFI Register'!$L$5:$L$104)) | G35: =IF($A35="","",SUMIF('RFI Register'!$B$5:$B$104,$A35,'RFI Register'!$M$5:$M$104))
A36: =IF(Projects!$B$15="","",Projects!$B$15) | B36: =IF($A36="","",COUNTIF('RFI Register'!$B$5:$B$104,$A36)) | C36: =IF($A36="","",COUNTIFS('RFI Register'!$B$5:$B$104,$A36,'RFI Register'!$H$5:$H$104,"<>Closed*",'RFI Register'!$H$5:$H$104,"<>Cancelled")) | D36: =IF($A36="","",SUMIF('RFI Register'!$B$5:$B$104,$A36,'RFI Register'!$I$5:$I$104)) | E36: =IF($A36="","",SUMIF('RFI Register'!$B$5:$B$104,$A36,'RFI Register'!$K$5:$K$104)) | F36: =IF($A36="","",SUMIF('RFI Register'!$B$5:$B$104,$A36,'RFI Register'!$L$5:$L$104)) | G36: =IF($A36="","",SUMIF('RFI Register'!$B$5:$B$104,$A36,'RFI Register'!$M$5:$M$104))
A37: =IF(Projects!$B$16="","",Projects!$B$16) | B37: =IF($A37="","",COUNTIF('RFI Register'!$B$5:$B$104,$A37)) | C37: =IF($A37="","",COUNTIFS('RFI Register'!$B$5:$B$104,$A37,'RFI Register'!$H$5:$H$104,"<>Closed*",'RFI Register'!$H$5:$H$104,"<>Cancelled")) | D37: =IF($A37="","",SUMIF('RFI Register'!$B$5:$B$104,$A37,'RFI Register'!$I$5:$I$104)) | E37: =IF($A37="","",SUMIF('RFI Register'!$B$5:$B$104,$A37,'RFI Register'!$K$5:$K$104)) | F37: =IF($A37="","",SUMIF('RFI Register'!$B$5:$B$104,$A37,'RFI Register'!$L$5:$L$104)) | G37: =IF($A37="","",SUMIF('RFI Register'!$B$5:$B$104,$A37,'RFI Register'!$M$5:$M$104))
A38: =IF(Projects!$B$17="","",Projects!$B$17) | B38: =IF($A38="","",COUNTIF('RFI Register'!$B$5:$B$104,$A38)) | C38: =IF($A38="","",COUNTIFS('RFI Register'!$B$5:$B$104,$A38,'RFI Register'!$H$5:$H$104,"<>Closed*",'RFI Register'!$H$5:$H$104,"<>Cancelled")) | D38: =IF($A38="","",SUMIF('RFI Register'!$B$5:$B$104,$A38,'RFI Register'!$I$5:$I$104)) | E38: =IF($A38="","",SUMIF('RFI Register'!$B$5:$B$104,$A38,'RFI Register'!$K$5:$K$104)) | F38: =IF($A38="","",SUMIF('RFI Register'!$B$5:$B$104,$A38,'RFI Register'!$L$5:$L$104)) | G38: =IF($A38="","",SUMIF('RFI Register'!$B$5:$B$104,$A38,'RFI Register'!$M$5:$M$104))
A39: =IF(Projects!$B$18="","",Projects!$B$18) | B39: =IF($A39="","",COUNTIF('RFI Register'!$B$5:$B$104,$A39)) | C39: =IF($A39="","",COUNTIFS('RFI Register'!$B$5:$B$104,$A39,'RFI Register'!$H$5:$H$104,"<>Closed*",'RFI Register'!$H$5:$H$104,"<>Cancelled")) | D39: =IF($A39="","",SUMIF('RFI Register'!$B$5:$B$104,$A39,'RFI Register'!$I$5:$I$104)) | E39: =IF($A39="","",SUMIF('RFI Register'!$B$5:$B$104,$A39,'RFI Register'!$K$5:$K$104)) | F39: =IF($A39="","",SUMIF('RFI Register'!$B$5:$B$104,$A39,'RFI Register'!$L$5:$L$104)) | G39: =IF($A39="","",SUMIF('RFI Register'!$B$5:$B$104,$A39,'RFI Register'!$M$5:$M$104))
A40: =IF(Projects!$B$19="","",Projects!$B$19) | B40: =IF($A40="","",COUNTIF('RFI Register'!$B$5:$B$104,$A40)) | C40: =IF($A40="","",COUNTIFS('RFI Register'!$B$5:$B$104,$A40,'RFI Register'!$H$5:$H$104,"<>Closed*",'RFI Register'!$H$5:$H$104,"<>Cancelled")) | D40: =IF($A40="","",SUMIF('RFI Register'!$B$5:$B$104,$A40,'RFI Register'!$I$5:$I$104)) | E40: =IF($A40="","",SUMIF('RFI Register'!$B$5:$B$104,$A40,'RFI Register'!$K$5:$K$104)) | F40: =IF($A40="","",SUMIF('RFI Register'!$B$5:$B$104,$A40,'RFI Register'!$L$5:$L$104)) | G40: =IF($A40="","",SUMIF('RFI Register'!$B$5:$B$104,$A40,'RFI Register'!$M$5:$M$104))

Sheet RFI Register
A1: RFI Register
A2: One row per RFI activity. Type the RFI ID (= tab name) in column A; the grey columns fill in from that tab. Add the outcome and notes in yellow.
A4: RFI ID (tab name) | B4: Project | C4: Vendor Type | D4: RFI Title / Scope | E4: RFI Owner | F4: Issue Date | G4: Response Due | H4: Activity Status | I4: Vendors Invited | J4: RFIs Sent | K4: Responses | L4: Actions Overdue | M4: Key Items Fails | N4: Days to Due | O4: Outcome / Next RFx Step | P4: Notes
A5: RFI-001 | B5: =IF($A5="","",IFERROR(INDIRECT("'"&$A5&"'!C4")&"","Tab not found")) -> Project A (placeholder - rename) | C5: =IF($A5="","",IFERROR(INDIRECT("'"&$A5&"'!C5")&"","Tab not found")) -> BESS Equipment | D5: =IF($A5="","",IFERROR(INDIRECT("'"&$A5&"'!C6")&"","Tab not found")) -> EXAMPLE - BESS equipment RFI (repurpose or delete) | E5: =IF($A5="","",IFERROR(INDIRECT("'"&$A5&"'!C7")&"","Tab not found")) -> Jason Knedlhans | F5: =IF($A5="","",IFERROR(IF(INDIRECT("'"&$A5&"'!C8")="","",INDIRECT("'"&$A5&"'!C8")),"Tab not found")) | G5: =IF($A5="","",IFERROR(IF(INDIRECT("'"&$A5&"'!C9")="","",INDIRECT("'"&$A5&"'!C9")),"Tab not found")) | H5: =IF($A5="","",IFERROR(INDIRECT("'"&$A5&"'!C10")&"","Tab not found")) -> Planning | I5: =IF($A5="","",IFERROR(IF(INDIRECT("'"&$A5&"'!I3")="","",INDIRECT("'"&$A5&"'!I3")+0),"Tab not found")) -> 10 | J5: =IF($A5="","",IFERROR(IF(INDIRECT("'"&$A5&"'!I4")="","",INDIRECT("'"&$A5&"'!I4")+0),"Tab not found")) -> 0 | K5: =IF($A5="","",IFERROR(IF(INDIRECT("'"&$A5&"'!I5")="","",INDIRECT("'"&$A5&"'!I5")+0),"Tab not found")) -> 0 | L5: =IF($A5="","",IFERROR(IF(INDIRECT("'"&$A5&"'!I7")="","",INDIRECT("'"&$A5&"'!I7")+0),"Tab not found")) -> 0 | M5: =IF($A5="","",IFERROR(IF(INDIRECT("'"&$A5&"'!I9")="","",INDIRECT("'"&$A5&"'!I9")+0),"Tab not found")) -> 0 | N5: =IF($A5="","",IFERROR(IF(INDIRECT("'"&$A5&"'!I10")="","",INDIRECT("'"&$A5&"'!I10")+0),"Tab not found")) | P5: Example tab - repurpose for the first real RFI or delete this row and the tab.
B6: =IF($A6="","",IFERROR(INDIRECT("'"&$A6&"'!C4")&"","Tab not found")) | C6: =IF($A6="","",IFERROR(INDIRECT("'"&$A6&"'!C5")&"","Tab not found")) | D6: =IF($A6="","",IFERROR(INDIRECT("'"&$A6&"'!C6")&"","Tab not found")) | E6: =IF($A6="","",IFERROR(INDIRECT("'"&$A6&"'!C7")&"","Tab not found")) | F6: =IF($A6="","",IFERROR(IF(INDIRECT("'"&$A6&"'!C8")="","",INDIRECT("'"&$A6&"'!C8")),"Tab not found")) | G6: =IF($A6="","",IFERROR(IF(INDIRECT("'"&$A6&"'!C9")="","",INDIRECT("'"&$A6&"'!C9")),"Tab not found")) | H6: =IF($A6="","",IFERROR(INDIRECT("'"&$A6&"'!C10")&"","Tab not found")) | I6: =IF($A6="","",IFERROR(IF(INDIRECT("'"&$A6&"'!I3")="","",INDIRECT("'"&$A6&"'!I3")+0),"Tab not found")) | J6: =IF($A6="","",IFERROR(IF(INDIRECT("'"&$A6&"'!I4")="","",INDIRECT("'"&$A6&"'!I4")+0),"Tab not found")) | K6: =IF($A6="","",IFERROR(IF(INDIRECT("'"&$A6&"'!I5")="","",INDIRECT("'"&$A6&"'!I5")+0),"Tab not found")) | L6: =IF($A6="","",IFERROR(IF(INDIRECT("'"&$A6&"'!I7")="","",INDIRECT("'"&$A6&"'!I7")+0),"Tab not found")) | M6: =IF($A6="","",IFERROR(IF(INDIRECT("'"&$A6&"'!I9")="","",INDIRECT("'"&$A6&"'!I9")+0),"Tab not found")) | N6: =IF($A6="","",IFERROR(IF(INDIRECT("'"&$A6&"'!I10")="","",INDIRECT("'"&$A6&"'!I10")+0),"Tab not found"))
B7: =IF($A7="","",IFERROR(INDIRECT("'"&$A7&"'!C4")&"","Tab not found")) | C7: =IF($A7="","",IFERROR(INDIRECT("'"&$A7&"'!C5")&"","Tab not found")) | D7: =IF($A7="","",IFERROR(INDIRECT("'"&$A7&"'!C6")&"","Tab not found")) | E7: =IF($A7="","",IFERROR(INDIRECT("'"&$A7&"'!C7")&"","Tab not found")) | F7: =IF($A7="","",IFERROR(IF(INDIRECT("'"&$A7&"'!C8")="","",INDIRECT("'"&$A7&"'!C8")),"Tab not found")) | G7: =IF($A7="","",IFERROR(IF(INDIRECT("'"&$A7&"'!C9")="","",INDIRECT("'"&$A7&"'!C9")),"Tab not found")) | H7: =IF($A7="","",IFERROR(INDIRECT("'"&$A7&"'!C10")&"","Tab not found")) | I7: =IF($A7="","",IFERROR(IF(INDIRECT("'"&$A7&"'!I3")="","",INDIRECT("'"&$A7&"'!I3")+0),"Tab not found")) | J7: =IF($A7="","",IFERROR(IF(INDIRECT("'"&$A7&"'!I4")="","",INDIRECT("'"&$A7&"'!I4")+0),"Tab not found")) | K7: =IF($A7="","",IFERROR(IF(INDIRECT("'"&$A7&"'!I5")="","",INDIRECT("'"&$A7&"'!I5")+0),"Tab not found")) | L7: =IF($A7="","",IFERROR(IF(INDIRECT("'"&$A7&"'!I7")="","",INDIRECT("'"&$A7&"'!I7")+0),"Tab not found")) | M7: =IF($A7="","",IFERROR(IF(INDIRECT("'"&$A7&"'!I9")="","",INDIRECT("'"&$A7&"'!I9")+0),"Tab not found")) | N7: =IF($A7="","",IFERROR(IF(INDIRECT("'"&$A7&"'!I10")="","",INDIRECT("'"&$A7&"'!I10")+0),"Tab not found"))
B8: =IF($A8="","",IFERROR(INDIRECT("'"&$A8&"'!C4")&"","Tab not found")) | C8: =IF($A8="","",IFERROR(INDIRECT("'"&$A8&"'!C5")&"","Tab not found")) | D8: =IF($A8="","",IFERROR(INDIRECT("'"&$A8&"'!C6")&"","Tab not found")) | E8: =IF($A8="","",IFERROR(INDIRECT("'"&$A8&"'!C7")&"","Tab not found")) | F8: =IF($A8="","",IFERROR(IF(INDIRECT("'"&$A8&"'!C8")="","",INDIRECT("'"&$A8&"'!C8")),"Tab not found")) | G8: =IF($A8="","",IFERROR(IF(INDIRECT("'"&$A8&"'!C9")="","",INDIRECT("'"&$A8&"'!C9")),"Tab not found")) | H8: =IF($A8="","",IFERROR(INDIRECT("'"&$A8&"'!C10")&"","Tab not found")) | I8: =IF($A8="","",IFERROR(IF(INDIRECT("'"&$A8&"'!I3")="","",INDIRECT("'"&$A8&"'!I3")+0),"Tab not found")) | J8: =IF($A8="","",IFERROR(IF(INDIRECT("'"&$A8&"'!I4")="","",INDIRECT("'"&$A8&"'!I4")+0),"Tab not found")) | K8: =IF($A8="","",IFERROR(IF(INDIRECT("'"&$A8&"'!I5")="","",INDIRECT("'"&$A8&"'!I5")+0),"Tab not found")) | L8: =IF($A8="","",IFERROR(IF(INDIRECT("'"&$A8&"'!I7")="","",INDIRECT("'"&$A8&"'!I7")+0),"Tab not found")) | M8: =IF($A8="","",IFERROR(IF(INDIRECT("'"&$A8&"'!I9")="","",INDIRECT("'"&$A8&"'!I9")+0),"Tab not found")) | N8: =IF($A8="","",IFERROR(IF(INDIRECT("'"&$A8&"'!I10")="","",INDIRECT("'"&$A8&"'!I10")+0),"Tab not found"))
B9: =IF($A9="","",IFERROR(INDIRECT("'"&$A9&"'!C4")&"","Tab not found")) | C9: =IF($A9="","",IFERROR(INDIRECT("'"&$A9&"'!C5")&"","Tab not found")) | D9: =IF($A9="","",IFERROR(INDIRECT("'"&$A9&"'!C6")&"","Tab not found")) | E9: =IF($A9="","",IFERROR(INDIRECT("'"&$A9&"'!C7")&"","Tab not found")) | F9: =IF($A9="","",IFERROR(IF(INDIRECT("'"&$A9&"'!C8")="","",INDIRECT("'"&$A9&"'!C8")),"Tab not found")) | G9: =IF($A9="","",IFERROR(IF(INDIRECT("'"&$A9&"'!C9")="","",INDIRECT("'"&$A9&"'!C9")),"Tab not found")) | H9: =IF($A9="","",IFERROR(INDIRECT("'"&$A9&"'!C10")&"","Tab not found")) | I9: =IF($A9="","",IFERROR(IF(INDIRECT("'"&$A9&"'!I3")="","",INDIRECT("'"&$A9&"'!I3")+0),"Tab not found")) | J9: =IF($A9="","",IFERROR(IF(INDIRECT("'"&$A9&"'!I4")="","",INDIRECT("'"&$A9&"'!I4")+0),"Tab not found")) | K9: =IF($A9="","",IFERROR(IF(INDIRECT("'"&$A9&"'!I5")="","",INDIRECT("'"&$A9&"'!I5")+0),"Tab not found")) | L9: =IF($A9="","",IFERROR(IF(INDIRECT("'"&$A9&"'!I7")="","",INDIRECT("'"&$A9&"'!I7")+0),"Tab not found")) | M9: =IF($A9="","",IFERROR(IF(INDIRECT("'"&$A9&"'!I9")="","",INDIRECT("'"&$A9&"'!I9")+0),"Tab not found")) | N9: =IF($A9="","",IFERROR(IF(INDIRECT("'"&$A9&"'!I10")="","",INDIRECT("'"&$A9&"'!I10")+0),"Tab not found"))
B10: =IF($A10="","",IFERROR(INDIRECT("'"&$A10&"'!C4")&"","Tab not found")) | C10: =IF($A10="","",IFERROR(INDIRECT("'"&$A10&"'!C5")&"","Tab not found")) | D10: =IF($A10="","",IFERROR(INDIRECT("'"&$A10&"'!C6")&"","Tab not found")) | E10: =IF($A10="","",IFERROR(INDIRECT("'"&$A10&"'!C7")&"","Tab not found")) | F10: =IF($A10="","",IFERROR(IF(INDIRECT("'"&$A10&"'!C8")="","",INDIRECT("'"&$A10&"'!C8")),"Tab not found")) | G10: =IF($A10="","",IFERROR(IF(INDIRECT("'"&$A10&"'!C9")="","",INDIRECT("'"&$A10&"'!C9")),"Tab not found")) | H10: =IF($A10="","",IFERROR(INDIRECT("'"&$A10&"'!C10")&"","Tab not found")) | I10: =IF($A10="","",IFERROR(IF(INDIRECT("'"&$A10&"'!I3")="","",INDIRECT("'"&$A10&"'!I3")+0),"Tab not found")) | J10: =IF($A10="","",IFERROR(IF(INDIRECT("'"&$A10&"'!I4")="","",INDIRECT("'"&$A10&"'!I4")+0),"Tab not found")) | K10: =IF($A10="","",IFERROR(IF(INDIRECT("'"&$A10&"'!I5")="","",INDIRECT("'"&$A10&"'!I5")+0),"Tab not found")) | L10: =IF($A10="","",IFERROR(IF(INDIRECT("'"&$A10&"'!I7")="","",INDIRECT("'"&$A10&"'!I7")+0),"Tab not found")) | M10: =IF($A10="","",IFERROR(IF(INDIRECT("'"&$A10&"'!I9")="","",INDIRECT("'"&$A10&"'!I9")+0),"Tab not found")) | N10: =IF($A10="","",IFERROR(IF(INDIRECT("'"&$A10&"'!I10")="","",INDIRECT("'"&$A10&"'!I10")+0),"Tab not found"))
B11: =IF($A11="","",IFERROR(INDIRECT("'"&$A11&"'!C4")&"","Tab not found")) | C11: =IF($A11="","",IFERROR(INDIRECT("'"&$A11&"'!C5")&"","Tab not found")) | D11: =IF($A11="","",IFERROR(INDIRECT("'"&$A11&"'!C6")&"","Tab not found")) | E11: =IF($A11="","",IFERROR(INDIRECT("'"&$A11&"'!C7")&"","Tab not found")) | F11: =IF($A11="","",IFERROR(IF(INDIRECT("'"&$A11&"'!C8")="","",INDIRECT("'"&$A11&"'!C8")),"Tab not found")) | G11: =IF($A11="","",IFERROR(IF(INDIRECT("'"&$A11&"'!C9")="","",INDIRECT("'"&$A11&"'!C9")),"Tab not found")) | H11: =IF($A11="","",IFERROR(INDIRECT("'"&$A11&"'!C10")&"","Tab not found")) | I11: =IF($A11="","",IFERROR(IF(INDIRECT("'"&$A11&"'!I3")="","",INDIRECT("'"&$A11&"'!I3")+0),"Tab not found")) | J11: =IF($A11="","",IFERROR(IF(INDIRECT("'"&$A11&"'!I4")="","",INDIRECT("'"&$A11&"'!I4")+0),"Tab not found")) | K11: =IF($A11="","",IFERROR(IF(INDIRECT("'"&$A11&"'!I5")="","",INDIRECT("'"&$A11&"'!I5")+0),"Tab not found")) | L11: =IF($A11="","",IFERROR(IF(INDIRECT("'"&$A11&"'!I7")="","",INDIRECT("'"&$A11&"'!I7")+0),"Tab not found")) | M11: =IF($A11="","",IFERROR(IF(INDIRECT("'"&$A11&"'!I9")="","",INDIRECT("'"&$A11&"'!I9")+0),"Tab not found")) | N11: =IF($A11="","",IFERROR(IF(INDIRECT("'"&$A11&"'!I10")="","",INDIRECT("'"&$A11&"'!I10")+0),"Tab not found"))
B12: =IF($A12="","",IFERROR(INDIRECT("'"&$A12&"'!C4")&"","Tab not found")) | C12: =IF($A12="","",IFERROR(INDIRECT("'"&$A12&"'!C5")&"","Tab not found")) | D12: =IF($A12="","",IFERROR(INDIRECT("'"&$A12&"'!C6")&"","Tab not found")) | E12: =IF($A12="","",IFERROR(INDIRECT("'"&$A12&"'!C7")&"","Tab not found")) | F12: =IF($A12="","",IFERROR(IF(INDIRECT("'"&$A12&"'!C8")="","",INDIRECT("'"&$A12&"'!C8")),"Tab not found")) | G12: =IF($A12="","",IFERROR(IF(INDIRECT("'"&$A12&"'!C9")="","",INDIRECT("'"&$A12&"'!C9")),"Tab not found")) | H12: =IF($A12="","",IFERROR(INDIRECT("'"&$A12&"'!C10")&"","Tab not found")) | I12: =IF($A12="","",IFERROR(IF(INDIRECT("'"&$A12&"'!I3")="","",INDIRECT("'"&$A12&"'!I3")+0),"Tab not found")) | J12: =IF($A12="","",IFERROR(IF(INDIRECT("'"&$A12&"'!I4")="","",INDIRECT("'"&$A12&"'!I4")+0),"Tab not found")) | K12: =IF($A12="","",IFERROR(IF(INDIRECT("'"&$A12&"'!I5")="","",INDIRECT("'"&$A12&"'!I5")+0),"Tab not found")) | L12: =IF($A12="","",IFERROR(IF(INDIRECT("'"&$A12&"'!I7")="","",INDIRECT("'"&$A12&"'!I7")+0),"Tab not found")) | M12: =IF($A12="","",IFERROR(IF(INDIRECT("'"&$A12&"'!I9")="","",INDIRECT("'"&$A12&"'!I9")+0),"Tab not found")) | N12: =IF($A12="","",IFERROR(IF(INDIRECT("'"&$A12&"'!I10")="","",INDIRECT("'"&$A12&"'!I10")+0),"Tab not found"))
B13: =IF($A13="","",IFERROR(INDIRECT("'"&$A13&"'!C4")&"","Tab not found")) | C13: =IF($A13="","",IFERROR(INDIRECT("'"&$A13&"'!C5")&"","Tab not found")) | D13: =IF($A13="","",IFERROR(INDIRECT("'"&$A13&"'!C6")&"","Tab not found")) | E13: =IF($A13="","",IFERROR(INDIRECT("'"&$A13&"'!C7")&"","Tab not found")) | F13: =IF($A13="","",IFERROR(IF(INDIRECT("'"&$A13&"'!C8")="","",INDIRECT("'"&$A13&"'!C8")),"Tab not found")) | G13: =IF($A13="","",IFERROR(IF(INDIRECT("'"&$A13&"'!C9")="","",INDIRECT("'"&$A13&"'!C9")),"Tab not found")) | H13: =IF($A13="","",IFERROR(INDIRECT("'"&$A13&"'!C10")&"","Tab not found")) | I13: =IF($A13="","",IFERROR(IF(INDIRECT("'"&$A13&"'!I3")="","",INDIRECT("'"&$A13&"'!I3")+0),"Tab not found")) | J13: =IF($A13="","",IFERROR(IF(INDIRECT("'"&$A13&"'!I4")="","",INDIRECT("'"&$A13&"'!I4")+0),"Tab not found")) | K13: =IF($A13="","",IFERROR(IF(INDIRECT("'"&$A13&"'!I5")="","",INDIRECT("'"&$A13&"'!I5")+0),"Tab not found")) | L13: =IF($A13="","",IFERROR(IF(INDIRECT("'"&$A13&"'!I7")="","",INDIRECT("'"&$A13&"'!I7")+0),"Tab not found")) | M13: =IF($A13="","",IFERROR(IF(INDIRECT("'"&$A13&"'!I9")="","",INDIRECT("'"&$A13&"'!I9")+0),"Tab not found")) | N13: =IF($A13="","",IFERROR(IF(INDIRECT("'"&$A13&"'!I10")="","",INDIRECT("'"&$A13&"'!I10")+0),"Tab not found"))
B14: =IF($A14="","",IFERROR(INDIRECT("'"&$A14&"'!C4")&"","Tab not found")) | C14: =IF($A14="","",IFERROR(INDIRECT("'"&$A14&"'!C5")&"","Tab not found")) | D14: =IF($A14="","",IFERROR(INDIRECT("'"&$A14&"'!C6")&"","Tab not found")) | E14: =IF($A14="","",IFERROR(INDIRECT("'"&$A14&"'!C7")&"","Tab not found")) | F14: =IF($A14="","",IFERROR(IF(INDIRECT("'"&$A14&"'!C8")="","",INDIRECT("'"&$A14&"'!C8")),"Tab not found")) | G14: =IF($A14="","",IFERROR(IF(INDIRECT("'"&$A14&"'!C9")="","",INDIRECT("'"&$A14&"'!C9")),"Tab not found")) | H14: =IF($A14="","",IFERROR(INDIRECT("'"&$A14&"'!C10")&"","Tab not found")) | I14: =IF($A14="","",IFERROR(IF(INDIRECT("'"&$A14&"'!I3")="","",INDIRECT("'"&$A14&"'!I3")+0),"Tab not found")) | J14: =IF($A14="","",IFERROR(IF(INDIRECT("'"&$A14&"'!I4")="","",INDIRECT("'"&$A14&"'!I4")+0),"Tab not found")) | K14: =IF($A14="","",IFERROR(IF(INDIRECT("'"&$A14&"'!I5")="","",INDIRECT("'"&$A14&"'!I5")+0),"Tab not found")) | L14: =IF($A14="","",IFERROR(IF(INDIRECT("'"&$A14&"'!I7")="","",INDIRECT("'"&$A14&"'!I7")+0),"Tab not found")) | M14: =IF($A14="","",IFERROR(IF(INDIRECT("'"&$A14&"'!I9")="","",INDIRECT("'"&$A14&"'!I9")+0),"Tab not found")) | N14: =IF($A14="","",IFERROR(IF(INDIRECT("'"&$A14&"'!I10")="","",INDIRECT("'"&$A14&"'!I10")+0),"Tab not found"))
B15: =IF($A15="","",IFERROR(INDIRECT("'"&$A15&"'!C4")&"","Tab not found")) | C15: =IF($A15="","",IFERROR(INDIRECT("'"&$A15&"'!C5")&"","Tab not found")) | D15: =IF($A15="","",IFERROR(INDIRECT("'"&$A15&"'!C6")&"","Tab not found")) | E15: =IF($A15="","",IFERROR(INDIRECT("'"&$A15&"'!C7")&"","Tab not found")) | F15: =IF($A15="","",IFERROR(IF(INDIRECT("'"&$A15&"'!C8")="","",INDIRECT("'"&$A15&"'!C8")),"Tab not found")) | G15: =IF($A15="","",IFERROR(IF(INDIRECT("'"&$A15&"'!C9")="","",INDIRECT("'"&$A15&"'!C9")),"Tab not found")) | H15: =IF($A15="","",IFERROR(INDIRECT("'"&$A15&"'!C10")&"","Tab not found")) | I15: =IF($A15="","",IFERROR(IF(INDIRECT("'"&$A15&"'!I3")="","",INDIRECT("'"&$A15&"'!I3")+0),"Tab not found")) | J15: =IF($A15="","",IFERROR(IF(INDIRECT("'"&$A15&"'!I4")="","",INDIRECT("'"&$A15&"'!I4")+0),"Tab not found")) | K15: =IF($A15="","",IFERROR(IF(INDIRECT("'"&$A15&"'!I5")="","",INDIRECT("'"&$A15&"'!I5")+0),"Tab not found")) | L15: =IF($A15="","",IFERROR(IF(INDIRECT("'"&$A15&"'!I7")="","",INDIRECT("'"&$A15&"'!I7")+0),"Tab not found")) | M15: =IF($A15="","",IFERROR(IF(INDIRECT("'"&$A15&"'!I9")="","",INDIRECT("'"&$A15&"'!I9")+0),"Tab not found")) | N15: =IF($A15="","",IFERROR(IF(INDIRECT("'"&$A15&"'!I10")="","",INDIRECT("'"&$A15&"'!I10")+0),"Tab not found"))
B16: =IF($A16="","",IFERROR(INDIRECT("'"&$A16&"'!C4")&"","Tab not found")) | C16: =IF($A16="","",IFERROR(INDIRECT("'"&$A16&"'!C5")&"","Tab not found")) | D16: =IF($A16="","",IFERROR(INDIRECT("'"&$A16&"'!C6")&"","Tab not found")) | E16: =IF($A16="","",IFERROR(INDIRECT("'"&$A16&"'!C7")&"","Tab not found")) | F16: =IF($A16="","",IFERROR(IF(INDIRECT("'"&$A16&"'!C8")="","",INDIRECT("'"&$A16&"'!C8")),"Tab not found")) | G16: =IF($A16="","",IFERROR(IF(INDIRECT("'"&$A16&"'!C9")="","",INDIRECT("'"&$A16&"'!C9")),"Tab not found")) | H16: =IF($A16="","",IFERROR(INDIRECT("'"&$A16&"'!C10")&"","Tab not found")) | I16: =IF($A16="","",IFERROR(IF(INDIRECT("'"&$A16&"'!I3")="","",INDIRECT("'"&$A16&"'!I3")+0),"Tab not found")) | J16: =IF($A16="","",IFERROR(IF(INDIRECT("'"&$A16&"'!I4")="","",INDIRECT("'"&$A16&"'!I4")+0),"Tab not found")) | K16: =IF($A16="","",IFERROR(IF(INDIRECT("'"&$A16&"'!I5")="","",INDIRECT("'"&$A16&"'!I5")+0),"Tab not found")) | L16: =IF($A16="","",IFERROR(IF(INDIRECT("'"&$A16&"'!I7")="","",INDIRECT("'"&$A16&"'!I7")+0),"Tab not found")) | M16: =IF($A16="","",IFERROR(IF(INDIRECT("'"&$A16&"'!I9")="","",INDIRECT("'"&$A16&"'!I9")+0),"Tab not found")) | N16: =IF($A16="","",IFERROR(IF(INDIRECT("'"&$A16&"'!I10")="","",INDIRECT("'"&$A16&"'!I10")+0),"Tab not found"))
B17: =IF($A17="","",IFERROR(INDIRECT("'"&$A17&"'!C4")&"","Tab not found")) | C17: =IF($A17="","",IFERROR(INDIRECT("'"&$A17&"'!C5")&"","Tab not found")) | D17: =IF($A17="","",IFERROR(INDIRECT("'"&$A17&"'!C6")&"","Tab not found")) | E17: =IF($A17="","",IFERROR(INDIRECT("'"&$A17&"'!C7")&"","Tab not found")) | F17: =IF($A17="","",IFERROR(IF(INDIRECT("'"&$A17&"'!C8")="","",INDIRECT("'"&$A17&"'!C8")),"Tab not found")) | G17: =IF($A17="","",IFERROR(IF(INDIRECT("'"&$A17&"'!C9")="","",INDIRECT("'"&$A17&"'!C9")),"Tab not found")) | H17: =IF($A17="","",IFERROR(INDIRECT("'"&$A17&"'!C10")&"","Tab not found")) | I17: =IF($A17="","",IFERROR(IF(INDIRECT("'"&$A17&"'!I3")="","",INDIRECT("'"&$A17&"'!I3")+0),"Tab not found")) | J17: =IF($A17="","",IFERROR(IF(INDIRECT("'"&$A17&"'!I4")="","",INDIRECT("'"&$A17&"'!I4")+0),"Tab not found")) | K17: =IF($A17="","",IFERROR(IF(INDIRECT("'"&$A17&"'!I5")="","",INDIRECT("'"&$A17&"'!I5")+0),"Tab not found")) | L17: =IF($A17="","",IFERROR(IF(INDIRECT("'"&$A17&"'!I7")="","",INDIRECT("'"&$A17&"'!I7")+0),"Tab not found")) | M17: =IF($A17="","",IFERROR(IF(INDIRECT("'"&$A17&"'!I9")="","",INDIRECT("'"&$A17&"'!I9")+0),"Tab not found")) | N17: =IF($A17="","",IFERROR(IF(INDIRECT("'"&$A17&"'!I10")="","",INDIRECT("'"&$A17&"'!I10")+0),"Tab not found"))
... B104: =IF($A104="","",IFERROR(INDIRECT("'"&$A104&"'!C4")&"","Tab not found")) | C104: =IF($A104="","",IFERROR(INDIRECT("'"&$A104&"'!C5")&"","Tab not found")) | D104: =IF($A104="","",IFERROR(INDIRECT("'"&$A104&"'!C6")&"","Tab not found")) | E104: =IF($A104="","",IFERROR(INDIRECT("'"&$A104&"'!C7")&"","Tab not found")) | F104: =IF($A104="","",IFERROR(IF(INDIRECT("'"&$A104&"'!C8")="","",INDIRECT("'"&$A104&"'!C8")),"Tab not found")) | G104: =IF($A104="","",IFERROR(IF(INDIRECT("'"&$A104&"'!C9")="","",INDIRECT("'"&$A104&"'!C9")),"Tab not found")) | H104: =IF($A104="","",IFERROR(INDIRECT("'"&$A104&"'!C10")&"","Tab not found")) | I104: =IF($A104="","",IFERROR(IF(INDIRECT("'"&$A104&"'!I3")="","",INDIRECT("'"&$A104&"'!I3")+0),"Tab not found")) | J104: =IF($A104="","",IFERROR(IF(INDIRECT("'"&$A104&"'!I4")="","",INDIRECT("'"&$A104&"'!I4")+0),"Tab not found")) | K104: =IF($A104="","",IFERROR(IF(INDIRECT("'"&$A104&"'!I5")="","",INDIRECT("'"&$A104&"'!I5")+0),"Tab not found")) | L104: =IF($A104="","",IFERROR(IF(INDIRECT("'"&$A104&"'!I7")="","",INDIRECT("'"&$A104&"'!I7")+0),"Tab not found")) | M104: =IF($A104="","",IFERROR(IF(INDIRECT("'"&$A104&"'!I9")="","",INDIRECT("'"&$A104&"'!I9")+0),"Tab not found")) | N104: =IF($A104="","",IFERROR(IF(INDIRECT("'"&$A104&"'!I10")="","",INDIRECT("'"&$A104&"'!I10")+0),"Tab not found"))

Sheet RFI-001
A1: =IF(C3="","RFI Activity (new - fill in the yellow cells)",C3&" | "&C6) -> RFI-001 | EXAMPLE - BESS equipment RFI (repurpose or delete)
A2: Yellow = enter data. Grey = formula, do not overwrite (except key item headers in row 13, which you may type over). Rename this tab to match the RFI ID, then add the ID to the RFI Register.
B3: RFI ID | C3: RFI-001 | H3: Vendors invited | I3: =COUNTA($A$15:$A$64) -> 10
B4: Project | C4: Project A (placeholder - rename) | H4: RFIs sent | I4: =COUNTIFS($A$15:$A$64,"<>",$F$15:$F$64,"<>Not Sent",$F$15:$F$64,"<>") -> 0
B5: Vendor Type | C5: BESS Equipment | H5: Responses received | I5: =COUNTIF($F$15:$F$64,"Response Received")+COUNTIF($F$15:$F$64,"Under Review")+COUNTIF($F$15:$F$64,"Complete") -> 0
B6: RFI Title / Scope | C6: EXAMPLE - BESS equipment RFI (repurpose or delete) | H6: Declined / no response | I6: =COUNTIF($F$15:$F$64,"Declined")+COUNTIF($F$15:$F$64,"No Response") -> 0
B7: RFI Owner | C7: Jason Knedlhans | H7: Actions overdue | I7: =COUNTIF($AH$15:$AH$64,"OVERDUE") -> 0
B8: Issue Date | H8: Key items: Review / Risk | I8: =COUNTIF($L$15:$L$64,"Review / Risk")+COUNTIF($N$15:$N$64,"Review / Risk")+COUNTIF($P$15:$P$64,"Review / Risk")+COUNTIF($R$15:$R$64,"Review / Risk")+COUNTIF($T$15:$T$64,"Review / Risk")+COUNTIF($V$15:$V$64,"Review / Risk")+COUNTIF($X$15:$X$64,"Review / Risk")+COUNTIF($Z$15:$Z$64,"Review / Risk")+COUNTIF($AB$15:$AB$64,"Review / Risk")+COUNTIF($AD$15:$AD$64,"Review / Risk") -> 9
B9: Response Due | H9: Key items: Fails | I9: =COUNTIF($L$15:$L$64,"Fails")+COUNTIF($N$15:$N$64,"Fails")+COUNTIF($P$15:$P$64,"Fails")+COUNTIF($R$15:$R$64,"Fails")+COUNTIF($T$15:$T$64,"Fails")+COUNTIF($V$15:$V$64,"Fails")+COUNTIF($X$15:$X$64,"Fails")+COUNTIF($Z$15:$Z$64,"Fails")+COUNTIF($AB$15:$AB$64,"Fails")+COUNTIF($AD$15:$AD$64,"Fails") -> 0
B10: Activity Status | C10: Planning | H10: Days to response due | I10: =IF(C9="","",C9-TODAY())
A12: VENDOR & CONTACT (contacts pull from Vendors tab) | F12: RFI | K12: ="KEY ITEMS - "&IF($C$5="","pick a Vendor Type in C5",UPPER($C$5)) -> KEY ITEMS - BESS EQUIPMENT | AE12: NEXT ACTION
A13: Vendor | B13: Vendor ID | C13: Contact Name | D13: Contact Email | E13: Contact Phone | F13: RFI Status | G13: Date Sent | H13: Last Contact | I13: Response Date | J13: Qualification Status | K13: =IF($C$5="","Key item 1",IFERROR(IF(INDEX('Key Items'!$B$5:$O$14,1,MATCH($C$5,'Key Items'!$B$4:$O$4,0))="","Key item 1 (spare - type a name)",INDEX('Key Items'!$B$5:$O$14,1,MATCH($C$5,'Key Items'!$B$4:$O$4,0))),"Key item 1")) -> Lead time (weeks ARO) | M13: =IF($C$5="","Key item 2",IFERROR(IF(INDEX('Key Items'!$B$5:$O$14,2,MATCH($C$5,'Key Items'!$B$4:$O$4,0))="","Key item 2 (spare - type a name)",INDEX('Key Items'!$B$5:$O$14,2,MATCH($C$5,'Key Items'!$B$4:$O$4,0))),"Key item 2")) -> FEOC compliance | O13: =IF($C$5="","Key item 3",IFERROR(IF(INDEX('Key Items'!$B$5:$O$14,3,MATCH($C$5,'Key Items'!$B$4:$O$4,0))="","Key item 3 (spare - type a name)",INDEX('Key Items'!$B$5:$O$14,3,MATCH($C$5,'Key Items'!$B$4:$O$4,0))),"Key item 3")) -> Cell chemistry & cell / module origin | Q13: =IF($C$5="","Key item 4",IFERROR(IF(INDEX('Key Items'!$B$5:$O$14,4,MATCH($C$5,'Key Items'!$B$4:$O$4,0))="","Key item 4 (spare - type a name)",INDEX('Key Items'!$B$5:$O$14,4,MATCH($C$5,'Key Items'!$B$4:$O$4,0))),"Key item 4")) -> Certifications (UL 9540, UL 9540A, NFPA 855) | S13: =IF($C$5="","Key item 5",IFERROR(IF(INDEX('Key Items'!$B$5:$O$14,5,MATCH($C$5,'Key Items'!$B$4:$O$4,0))="","Key item 5 (spare - type a name)",INDEX('Key Items'!$B$5:$O$14,5,MATCH($C$5,'Key Items'!$B$4:$O$4,0))),"Key item 5")) -> Warranty & performance guarantee | U13: =IF($C$5="","Key item 6",IFERROR(IF(INDEX('Key Items'!$B$5:$O$14,6,MATCH($C$5,'Key Items'!$B$4:$O$4,0))="","Key item 6 (spare - type a name)",INDEX('Key Items'!$B$5:$O$14,6,MATCH($C$5,'Key Items'!$B$4:$O$4,0))),"Key item 6")) -> Domestic content (ITC adder) | W13: =IF($C$5="","Key item 7",IFERROR(IF(INDEX('Key Items'!$B$5:$O$14,7,MATCH($C$5,'Key Items'!$B$4:$O$4,0))="","Key item 7 (spare - type a name)",INDEX('Key Items'!$B$5:$O$14,7,MATCH($C$5,'Key Items'!$B$4:$O$4,0))),"Key item 7")) -> Bankability / financial strength | Y13: =IF($C$5="","Key item 8",IFERROR(IF(INDEX('Key Items'!$B$5:$O$14,8,MATCH($C$5,'Key Items'!$B$4:$O$4,0))="","Key item 8 (spare - type a name)",INDEX('Key Items'!$B$5:$O$14,8,MATCH($C$5,'Key Items'!$B$4:$O$4,0))),"Key item 8")) -> Key item 8 (spare - type a name) | AA13: =IF($C$5="","Key item 9",IFERROR(IF(INDEX('Key Items'!$B$5:$O$14,9,MATCH($C$5,'Key Items'!$B$4:$O$4,0))="","Key item 9 (spare - type a name)",INDEX('Key Items'!$B$5:$O$14,9,MATCH($C$5,'Key Items'!$B$4:$O$4,0))),"Key item 9")) -> Key item 9 (spare - type a name) | AC13: =IF($C$5="","Key item 10",IFERROR(IF(INDEX('Key Items'!$B$5:$O$14,10,MATCH($C$5,'Key Items'!$B$4:$O$4,0))="","Key item 10 (spare - type a name)",INDEX('Key Items'!$B$5:$O$14,10,MATCH($C$5,'Key Items'!$B$4:$O$4,0))),"Key item 10")) -> Key item 10 (spare - type a name) | AE13: Next Action | AF13: Next Action Owner | AG13: Next Action Date | AH13: Action Flag | AI13: Notes
K14: Response / notes | L14: Rating | M14: Response / notes | N14: Rating | O14: Response / notes | P14: Rating | Q14: Response / notes | R14: Rating | S14: Response / notes | T14: Rating | U14: Response / notes | V14: Rating | W14: Response / notes | X14: Rating | Y14: Response / notes | Z14: Rating | AA14: Response / notes | AB14: Rating | AC14: Response / notes | AD14: Rating
A15: Tesla (Tesla Energy) | B15: =IF($A15="","",IFERROR(INDEX(Vendors!$A$5:$A$400,MATCH($A15,Vendors!$B$5:$B$400,0)),"Not in Vendors tab")) -> BESS-001 | C15: =IF($A15="","",IFERROR(INDEX(Vendors!$H$5:$H$400,MATCH($A15,Vendors!$B$5:$B$400,0))&"","")) | D15: =IF($A15="","",IFERROR(INDEX(Vendors!$J$5:$J$400,MATCH($A15,Vendors!$B$5:$B$400,0))&"","")) | E15: =IF($A15="","",IFERROR(IF(INDEX(Vendors!$K$5:$K$400,MATCH($A15,Vendors!$B$5:$B$400,0))&""="",INDEX(Vendors!$F$5:$F$400,MATCH($A15,Vendors!$B$5:$B$400,0))&"",INDEX(Vendors!$K$5:$K$400,MATCH($A15,Vendors!$B$5:$B$400,0))&""),"")) | F15: Not Sent | J15: Discovery | M15: Flagged FEOC Review in vendor landscape - confirm ownership / origin in RFI | N15: Review / Risk | AE15: Identify RFI contact | AF15: Jason Knedlhans | AH15: =IF(OR($A15="",AG15=""),"",IF(OR(F15="Complete",F15="Declined",F15="No Response"),"",IF(AG15<TODAY(),"OVERDUE",IF(AG15-TODAY()<=7,"Due 7d",""))))
A16: Fluence Energy | B16: =IF($A16="","",IFERROR(INDEX(Vendors!$A$5:$A$400,MATCH($A16,Vendors!$B$5:$B$400,0)),"Not in Vendors tab")) -> BESS-002 | C16: =IF($A16="","",IFERROR(INDEX(Vendors!$H$5:$H$400,MATCH($A16,Vendors!$B$5:$B$400,0))&"","")) | D16: =IF($A16="","",IFERROR(INDEX(Vendors!$J$5:$J$400,MATCH($A16,Vendors!$B$5:$B$400,0))&"","")) | E16: =IF($A16="","",IFERROR(IF(INDEX(Vendors!$K$5:$K$400,MATCH($A16,Vendors!$B$5:$B$400,0))&""="",INDEX(Vendors!$F$5:$F$400,MATCH($A16,Vendors!$B$5:$B$400,0))&"",INDEX(Vendors!$K$5:$K$400,MATCH($A16,Vendors!$B$5:$B$400,0))&""),"")) | F16: Not Sent | J16: Discovery | M16: Flagged FEOC Review in vendor landscape - confirm ownership / origin in RFI | N16: Review / Risk | AE16: Identify RFI contact | AF16: Jason Knedlhans | AH16: =IF(OR($A16="",AG16=""),"",IF(OR(F16="Complete",F16="Declined",F16="No Response"),"",IF(AG16<TODAY(),"OVERDUE",IF(AG16-TODAY()<=7,"Due 7d",""))))
A17: Sungrow | B17: =IF($A17="","",IFERROR(INDEX(Vendors!$A$5:$A$400,MATCH($A17,Vendors!$B$5:$B$400,0)),"Not in Vendors tab")) -> BESS-003 | C17: =IF($A17="","",IFERROR(INDEX(Vendors!$H$5:$H$400,MATCH($A17,Vendors!$B$5:$B$400,0))&"","")) | D17: =IF($A17="","",IFERROR(INDEX(Vendors!$J$5:$J$400,MATCH($A17,Vendors!$B$5:$B$400,0))&"","")) | E17: =IF($A17="","",IFERROR(IF(INDEX(Vendors!$K$5:$K$400,MATCH($A17,Vendors!$B$5:$B$400,0))&""="",INDEX(Vendors!$F$5:$F$400,MATCH($A17,Vendors!$B$5:$B$400,0))&"",INDEX(Vendors!$K$5:$K$400,MATCH($A17,Vendors!$B$5:$B$400,0))&""),"")) -> +1 833 747 6937 | F17: Not Sent | J17: Discovery | M17: Flagged FEOC Review in vendor landscape - confirm ownership / origin in RFI | N17: Review / Risk | AE17: Identify RFI contact | AF17: Jason Knedlhans | AH17: =IF(OR($A17="",AG17=""),"",IF(OR(F17="Complete",F17="Declined",F17="No Response"),"",IF(AG17<TODAY(),"OVERDUE",IF(AG17-TODAY()<=7,"Due 7d",""))))
A18: LG Energy Solution Vertech | B18: =IF($A18="","",IFERROR(INDEX(Vendors!$A$5:$A$400,MATCH($A18,Vendors!$B$5:$B$400,0)),"Not in Vendors tab")) -> BESS-004 | C18: =IF($A18="","",IFERROR(INDEX(Vendors!$H$5:$H$400,MATCH($A18,Vendors!$B$5:$B$400,0))&"","")) | D18: =IF($A18="","",IFERROR(INDEX(Vendors!$J$5:$J$400,MATCH($A18,Vendors!$B$5:$B$400,0))&"","")) | E18: =IF($A18="","",IFERROR(IF(INDEX(Vendors!$K$5:$K$400,MATCH($A18,Vendors!$B$5:$B$400,0))&""="",INDEX(Vendors!$F$5:$F$400,MATCH($A18,Vendors!$B$5:$B$400,0))&"",INDEX(Vendors!$K$5:$K$400,MATCH($A18,Vendors!$B$5:$B$400,0))&""),"")) | F18: Not Sent | J18: Discovery | M18: Flagged FEOC Review in vendor landscape - confirm ownership / origin in RFI | N18: Review / Risk | AE18: Identify RFI contact | AF18: Jason Knedlhans | AH18: =IF(OR($A18="",AG18=""),"",IF(OR(F18="Complete",F18="Declined",F18="No Response"),"",IF(AG18<TODAY(),"OVERDUE",IF(AG18-TODAY()<=7,"Due 7d",""))))
A19: Samsung SDI | B19: =IF($A19="","",IFERROR(INDEX(Vendors!$A$5:$A$400,MATCH($A19,Vendors!$B$5:$B$400,0)),"Not in Vendors tab")) -> BESS-005 | C19: =IF($A19="","",IFERROR(INDEX(Vendors!$H$5:$H$400,MATCH($A19,Vendors!$B$5:$B$400,0))&"","")) | D19: =IF($A19="","",IFERROR(INDEX(Vendors!$J$5:$J$400,MATCH($A19,Vendors!$B$5:$B$400,0))&"","")) | E19: =IF($A19="","",IFERROR(IF(INDEX(Vendors!$K$5:$K$400,MATCH($A19,Vendors!$B$5:$B$400,0))&""="",INDEX(Vendors!$F$5:$F$400,MATCH($A19,Vendors!$B$5:$B$400,0))&"",INDEX(Vendors!$K$5:$K$400,MATCH($A19,Vendors!$B$5:$B$400,0))&""),"")) | F19: Not Sent | J19: Discovery | AE19: Identify RFI contact | AF19: Jason Knedlhans | AH19: =IF(OR($A19="",AG19=""),"",IF(OR(F19="Complete",F19="Declined",F19="No Response"),"",IF(AG19<TODAY(),"OVERDUE",IF(AG19-TODAY()<=7,"Due 7d",""))))
A20: Wärtsilä Energy Storage | B20: =IF($A20="","",IFERROR(INDEX(Vendors!$A$5:$A$400,MATCH($A20,Vendors!$B$5:$B$400,0)),"Not in Vendors tab")) -> BESS-006 | C20: =IF($A20="","",IFERROR(INDEX(Vendors!$H$5:$H$400,MATCH($A20,Vendors!$B$5:$B$400,0))&"","")) | D20: =IF($A20="","",IFERROR(INDEX(Vendors!$J$5:$J$400,MATCH($A20,Vendors!$B$5:$B$400,0))&"","")) | E20: =IF($A20="","",IFERROR(IF(INDEX(Vendors!$K$5:$K$400,MATCH($A20,Vendors!$B$5:$B$400,0))&""="",INDEX(Vendors!$F$5:$F$400,MATCH($A20,Vendors!$B$5:$B$400,0))&"",INDEX(Vendors!$K$5:$K$400,MATCH($A20,Vendors!$B$5:$B$400,0))&""),"")) -> +1 281 233 6200 | F20: Not Sent | J20: Discovery | M20: Flagged FEOC Review in vendor landscape - confirm ownership / origin in RFI | N20: Review / Risk | AE20: Identify RFI contact | AF20: Jason Knedlhans | AH20: =IF(OR($A20="",AG20=""),"",IF(OR(F20="Complete",F20="Declined",F20="No Response"),"",IF(AG20<TODAY(),"OVERDUE",IF(AG20-TODAY()<=7,"Due 7d",""))))
A21: FlexGen Power Systems | B21: =IF($A21="","",IFERROR(INDEX(Vendors!$A$5:$A$400,MATCH($A21,Vendors!$B$5:$B$400,0)),"Not in Vendors tab")) -> BESS-007 | C21: =IF($A21="","",IFERROR(INDEX(Vendors!$H$5:$H$400,MATCH($A21,Vendors!$B$5:$B$400,0))&"","")) | D21: =IF($A21="","",IFERROR(INDEX(Vendors!$J$5:$J$400,MATCH($A21,Vendors!$B$5:$B$400,0))&"","")) | E21: =IF($A21="","",IFERROR(IF(INDEX(Vendors!$K$5:$K$400,MATCH($A21,Vendors!$B$5:$B$400,0))&""="",INDEX(Vendors!$F$5:$F$400,MATCH($A21,Vendors!$B$5:$B$400,0))&"",INDEX(Vendors!$K$5:$K$400,MATCH($A21,Vendors!$B$5:$B$400,0))&""),"")) -> 855-327-5674 | F21: Not Sent | J21: Discovery | M21: Flagged FEOC Review in vendor landscape - confirm ownership / origin in RFI | N21: Review / Risk | AE21: Identify RFI contact | AF21: Jason Knedlhans | AH21: =IF(OR($A21="",AG21=""),"",IF(OR(F21="Complete",F21="Declined",F21="No Response"),"",IF(AG21<TODAY(),"OVERDUE",IF(AG21-TODAY()<=7,"Due 7d",""))))
A22: Hithium | B22: =IF($A22="","",IFERROR(INDEX(Vendors!$A$5:$A$400,MATCH($A22,Vendors!$B$5:$B$400,0)),"Not in Vendors tab")) -> BESS-008 | C22: =IF($A22="","",IFERROR(INDEX(Vendors!$H$5:$H$400,MATCH($A22,Vendors!$B$5:$B$400,0))&"","")) | D22: =IF($A22="","",IFERROR(INDEX(Vendors!$J$5:$J$400,MATCH($A22,Vendors!$B$5:$B$400,0))&"","")) | E22: =IF($A22="","",IFERROR(IF(INDEX(Vendors!$K$5:$K$400,MATCH($A22,Vendors!$B$5:$B$400,0))&""="",INDEX(Vendors!$F$5:$F$400,MATCH($A22,Vendors!$B$5:$B$400,0))&"",INDEX(Vendors!$K$5:$K$400,MATCH($A22,Vendors!$B$5:$B$400,0))&""),"")) | F22: Not Sent | J22: Discovery | M22: Flagged FEOC Review in vendor landscape - confirm ownership / origin in RFI | N22: Review / Risk | AE22: Identify RFI contact | AF22: Jason Knedlhans | AH22: =IF(OR($A22="",AG22=""),"",IF(OR(F22="Complete",F22="Declined",F22="No Response"),"",IF(AG22<TODAY(),"OVERDUE",IF(AG22-TODAY()<=7,"Due 7d",""))))
A23: Canadian Solar e-STORAGE | B23: =IF($A23="","",IFERROR(INDEX(Vendors!$A$5:$A$400,MATCH($A23,Vendors!$B$5:$B$400,0)),"Not in Vendors tab")) -> BESS-009 | C23: =IF($A23="","",IFERROR(INDEX(Vendors!$H$5:$H$400,MATCH($A23,Vendors!$B$5:$B$400,0))&"","")) | D23: =IF($A23="","",IFERROR(INDEX(Vendors!$J$5:$J$400,MATCH($A23,Vendors!$B$5:$B$400,0))&"","")) | E23: =IF($A23="","",IFERROR(IF(INDEX(Vendors!$K$5:$K$400,MATCH($A23,Vendors!$B$5:$B$400,0))&""="",INDEX(Vendors!$F$5:$F$400,MATCH($A23,Vendors!$B$5:$B$400,0))&"",INDEX(Vendors!$K$5:$K$400,MATCH($A23,Vendors!$B$5:$B$400,0))&""),"")) | F23: Not Sent | J23: Discovery | M23: Flagged FEOC Review in vendor landscape - confirm ownership / origin in RFI | N23: Review / Risk | AE23: Identify RFI contact | AF23: Jason Knedlhans | AH23: =IF(OR($A23="",AG23=""),"",IF(OR(F23="Complete",F23="Declined",F23="No Response"),"",IF(AG23<TODAY(),"OVERDUE",IF(AG23-TODAY()<=7,"Due 7d",""))))
A24: Prevalon Energy (now Nextpower) | B24: =IF($A24="","",IFERROR(INDEX(Vendors!$A$5:$A$400,MATCH($A24,Vendors!$B$5:$B$400,0)),"Not in Vendors tab")) -> BESS-010 | C24: =IF($A24="","",IFERROR(INDEX(Vendors!$H$5:$H$400,MATCH($A24,Vendors!$B$5:$B$400,0))&"","")) | D24: =IF($A24="","",IFERROR(INDEX(Vendors!$J$5:$J$400,MATCH($A24,Vendors!$B$5:$B$400,0))&"","")) | E24: =IF($A24="","",IFERROR(IF(INDEX(Vendors!$K$5:$K$400,MATCH($A24,Vendors!$B$5:$B$400,0))&""="",INDEX(Vendors!$F$5:$F$400,MATCH($A24,Vendors!$B$5:$B$400,0))&"",INDEX(Vendors!$K$5:$K$400,MATCH($A24,Vendors!$B$5:$B$400,0))&""),"")) | F24: Not Sent | J24: Discovery | M24: Flagged FEOC Review in vendor landscape - confirm ownership / origin in RFI | N24: Review / Risk | AE24: Identify RFI contact | AF24: Jason Knedlhans | AH24: =IF(OR($A24="",AG24=""),"",IF(OR(F24="Complete",F24="Declined",F24="No Response"),"",IF(AG24<TODAY(),"OVERDUE",IF(AG24-TODAY()<=7,"Due 7d",""))))
B25: =IF($A25="","",IFERROR(INDEX(Vendors!$A$5:$A$400,MATCH($A25,Vendors!$B$5:$B$400,0)),"Not in Vendors tab")) | C25: =IF($A25="","",IFERROR(INDEX(Vendors!$H$5:$H$400,MATCH($A25,Vendors!$B$5:$B$400,0))&"","")) | D25: =IF($A25="","",IFERROR(INDEX(Vendors!$J$5:$J$400,MATCH($A25,Vendors!$B$5:$B$400,0))&"","")) | E25: =IF($A25="","",IFERROR(IF(INDEX(Vendors!$K$5:$K$400,MATCH($A25,Vendors!$B$5:$B$400,0))&""="",INDEX(Vendors!$F$5:$F$400,MATCH($A25,Vendors!$B$5:$B$400,0))&"",INDEX(Vendors!$K$5:$K$400,MATCH($A25,Vendors!$B$5:$B$400,0))&""),"")) | AH25: =IF(OR($A25="",AG25=""),"",IF(OR(F25="Complete",F25="Declined",F25="No Response"),"",IF(AG25<TODAY(),"OVERDUE",IF(AG25-TODAY()<=7,"Due 7d",""))))
B26: =IF($A26="","",IFERROR(INDEX(Vendors!$A$5:$A$400,MATCH($A26,Vendors!$B$5:$B$400,0)),"Not in Vendors tab")) | C26: =IF($A26="","",IFERROR(INDEX(Vendors!$H$5:$H$400,MATCH($A26,Vendors!$B$5:$B$400,0))&"","")) | D26: =IF($A26="","",IFERROR(INDEX(Vendors!$J$5:$J$400,MATCH($A26,Vendors!$B$5:$B$400,0))&"","")) | E26: =IF($A26="","",IFERROR(IF(INDEX(Vendors!$K$5:$K$400,MATCH($A26,Vendors!$B$5:$B$400,0))&""="",INDEX(Vendors!$F$5:$F$400,MATCH($A26,Vendors!$B$5:$B$400,0))&"",INDEX(Vendors!$K$5:$K$400,MATCH($A26,Vendors!$B$5:$B$400,0))&""),"")) | AH26: =IF(OR($A26="",AG26=""),"",IF(OR(F26="Complete",F26="Declined",F26="No Response"),"",IF(AG26<TODAY(),"OVERDUE",IF(AG26-TODAY()<=7,"Due 7d",""))))
B27: =IF($A27="","",IFERROR(INDEX(Vendors!$A$5:$A$400,MATCH($A27,Vendors!$B$5:$B$400,0)),"Not in Vendors tab")) | C27: =IF($A27="","",IFERROR(INDEX(Vendors!$H$5:$H$400,MATCH($A27,Vendors!$B$5:$B$400,0))&"","")) | D27: =IF($A27="","",IFERROR(INDEX(Vendors!$J$5:$J$400,MATCH($A27,Vendors!$B$5:$B$400,0))&"","")) | E27: =IF($A27="","",IFERROR(IF(INDEX(Vendors!$K$5:$K$400,MATCH($A27,Vendors!$B$5:$B$400,0))&""="",INDEX(Vendors!$F$5:$F$400,MATCH($A27,Vendors!$B$5:$B$400,0))&"",INDEX(Vendors!$K$5:$K$400,MATCH($A27,Vendors!$B$5:$B$400,0))&""),"")) | AH27: =IF(OR($A27="",AG27=""),"",IF(OR(F27="Complete",F27="Declined",F27="No Response"),"",IF(AG27<TODAY(),"OVERDUE",IF(AG27-TODAY()<=7,"Due 7d",""))))
B28: =IF($A28="","",IFERROR(INDEX(Vendors!$A$5:$A$400,MATCH($A28,Vendors!$B$5:$B$400,0)),"Not in Vendors tab")) | C28: =IF($A28="","",IFERROR(INDEX(Vendors!$H$5:$H$400,MATCH($A28,Vendors!$B$5:$B$400,0))&"","")) | D28: =IF($A28="","",IFERROR(INDEX(Vendors!$J$5:$J$400,MATCH($A28,Vendors!$B$5:$B$400,0))&"","")) | E28: =IF($A28="","",IFERROR(IF(INDEX(Vendors!$K$5:$K$400,MATCH($A28,Vendors!$B$5:$B$400,0))&""="",INDEX(Vendors!$F$5:$F$400,MATCH($A28,Vendors!$B$5:$B$400,0))&"",INDEX(Vendors!$K$5:$K$400,MATCH($A28,Vendors!$B$5:$B$400,0))&""),"")) | AH28: =IF(OR($A28="",AG28=""),"",IF(OR(F28="Complete",F28="Declined",F28="No Response"),"",IF(AG28<TODAY(),"OVERDUE",IF(AG28-TODAY()<=7,"Due 7d",""))))
B29: =IF($A29="","",IFERROR(INDEX(Vendors!$A$5:$A$400,MATCH($A29,Vendors!$B$5:$B$400,0)),"Not in Vendors tab")) | C29: =IF($A29="","",IFERROR(INDEX(Vendors!$H$5:$H$400,MATCH($A29,Vendors!$B$5:$B$400,0))&"","")) | D29: =IF($A29="","",IFERROR(INDEX(Vendors!$J$5:$J$400,MATCH($A29,Vendors!$B$5:$B$400,0))&"","")) | E29: =IF($A29="","",IFERROR(IF(INDEX(Vendors!$K$5:$K$400,MATCH($A29,Vendors!$B$5:$B$400,0))&""="",INDEX(Vendors!$F$5:$F$400,MATCH($A29,Vendors!$B$5:$B$400,0))&"",INDEX(Vendors!$K$5:$K$400,MATCH($A29,Vendors!$B$5:$B$400,0))&""),"")) | AH29: =IF(OR($A29="",AG29=""),"",IF(OR(F29="Complete",F29="Declined",F29="No Response"),"",IF(AG29<TODAY(),"OVERDUE",IF(AG29-TODAY()<=7,"Due 7d",""))))
B30: =IF($A30="","",IFERROR(INDEX(Vendors!$A$5:$A$400,MATCH($A30,Vendors!$B$5:$B$400,0)),"Not in Vendors tab")) | C30: =IF($A30="","",IFERROR(INDEX(Vendors!$H$5:$H$400,MATCH($A30,Vendors!$B$5:$B$400,0))&"","")) | D30: =IF($A30="","",IFERROR(INDEX(Vendors!$J$5:$J$400,MATCH($A30,Vendors!$B$5:$B$400,0))&"","")) | E30: =IF($A30="","",IFERROR(IF(INDEX(Vendors!$K$5:$K$400,MATCH($A30,Vendors!$B$5:$B$400,0))&""="",INDEX(Vendors!$F$5:$F$400,MATCH($A30,Vendors!$B$5:$B$400,0))&"",INDEX(Vendors!$K$5:$K$400,MATCH($A30,Vendors!$B$5:$B$400,0))&""),"")) | AH30: =IF(OR($A30="",AG30=""),"",IF(OR(F30="Complete",F30="Declined",F30="No Response"),"",IF(AG30<TODAY(),"OVERDUE",IF(AG30-TODAY()<=7,"Due 7d",""))))
B31: =IF($A31="","",IFERROR(INDEX(Vendors!$A$5:$A$400,MATCH($A31,Vendors!$B$5:$B$400,0)),"Not in Vendors tab")) | C31: =IF($A31="","",IFERROR(INDEX(Vendors!$H$5:$H$400,MATCH($A31,Vendors!$B$5:$B$400,0))&"","")) | D31: =IF($A31="","",IFERROR(INDEX(Vendors!$J$5:$J$400,MATCH($A31,Vendors!$B$5:$B$400,0))&"","")) | E31: =IF($A31="","",IFERROR(IF(INDEX(Vendors!$K$5:$K$400,MATCH($A31,Vendors!$B$5:$B$400,0))&""="",INDEX(Vendors!$F$5:$F$400,MATCH($A31,Vendors!$B$5:$B$400,0))&"",INDEX(Vendors!$K$5:$K$400,MATCH($A31,Vendors!$B$5:$B$400,0))&""),"")) | AH31: =IF(OR($A31="",AG31=""),"",IF(OR(F31="Complete",F31="Declined",F31="No Response"),"",IF(AG31<TODAY(),"OVERDUE",IF(AG31-TODAY()<=7,"Due 7d",""))))
B32: =IF($A32="","",IFERROR(INDEX(Vendors!$A$5:$A$400,MATCH($A32,Vendors!$B$5:$B$400,0)),"Not in Vendors tab")) | C32: =IF($A32="","",IFERROR(INDEX(Vendors!$H$5:$H$400,MATCH($A32,Vendors!$B$5:$B$400,0))&"","")) | D32: =IF($A32="","",IFERROR(INDEX(Vendors!$J$5:$J$400,MATCH($A32,Vendors!$B$5:$B$400,0))&"","")) | E32: =IF($A32="","",IFERROR(IF(INDEX(Vendors!$K$5:$K$400,MATCH($A32,Vendors!$B$5:$B$400,0))&""="",INDEX(Vendors!$F$5:$F$400,MATCH($A32,Vendors!$B$5:$B$400,0))&"",INDEX(Vendors!$K$5:$K$400,MATCH($A32,Vendors!$B$5:$B$400,0))&""),"")) | AH32: =IF(OR($A32="",AG32=""),"",IF(OR(F32="Complete",F32="Declined",F32="No Response"),"",IF(AG32<TODAY(),"OVERDUE",IF(AG32-TODAY()<=7,"Due 7d",""))))
B33: =IF($A33="","",IFERROR(INDEX(Vendors!$A$5:$A$400,MATCH($A33,Vendors!$B$5:$B$400,0)),"Not in Vendors tab")) | C33: =IF($A33="","",IFERROR(INDEX(Vendors!$H$5:$H$400,MATCH($A33,Vendors!$B$5:$B$400,0))&"","")) | D33: =IF($A33="","",IFERROR(INDEX(Vendors!$J$5:$J$400,MATCH($A33,Vendors!$B$5:$B$400,0))&"","")) | E33: =IF($A33="","",IFERROR(IF(INDEX(Vendors!$K$5:$K$400,MATCH($A33,Vendors!$B$5:$B$400,0))&""="",INDEX(Vendors!$F$5:$F$400,MATCH($A33,Vendors!$B$5:$B$400,0))&"",INDEX(Vendors!$K$5:$K$400,MATCH($A33,Vendors!$B$5:$B$400,0))&""),"")) | AH33: =IF(OR($A33="",AG33=""),"",IF(OR(F33="Complete",F33="Declined",F33="No Response"),"",IF(AG33<TODAY(),"OVERDUE",IF(AG33-TODAY()<=7,"Due 7d",""))))
B34: =IF($A34="","",IFERROR(INDEX(Vendors!$A$5:$A$400,MATCH($A34,Vendors!$B$5:$B$400,0)),"Not in Vendors tab")) | C34: =IF($A34="","",IFERROR(INDEX(Vendors!$H$5:$H$400,MATCH($A34,Vendors!$B$5:$B$400,0))&"","")) | D34: =IF($A34="","",IFERROR(INDEX(Vendors!$J$5:$J$400,MATCH($A34,Vendors!$B$5:$B$400,0))&"","")) | E34: =IF($A34="","",IFERROR(IF(INDEX(Vendors!$K$5:$K$400,MATCH($A34,Vendors!$B$5:$B$400,0))&""="",INDEX(Vendors!$F$5:$F$400,MATCH($A34,Vendors!$B$5:$B$400,0))&"",INDEX(Vendors!$K$5:$K$400,MATCH($A34,Vendors!$B$5:$B$400,0))&""),"")) | AH34: =IF(OR($A34="",AG34=""),"",IF(OR(F34="Complete",F34="Declined",F34="No Response"),"",IF(AG34<TODAY(),"OVERDUE",IF(AG34-TODAY()<=7,"Due 7d",""))))
B35: =IF($A35="","",IFERROR(INDEX(Vendors!$A$5:$A$400,MATCH($A35,Vendors!$B$5:$B$400,0)),"Not in Vendors tab")) | C35: =IF($A35="","",IFERROR(INDEX(Vendors!$H$5:$H$400,MATCH($A35,Vendors!$B$5:$B$400,0))&"","")) | D35: =IF($A35="","",IFERROR(INDEX(Vendors!$J$5:$J$400,MATCH($A35,Vendors!$B$5:$B$400,0))&"","")) | E35: =IF($A35="","",IFERROR(IF(INDEX(Vendors!$K$5:$K$400,MATCH($A35,Vendors!$B$5:$B$400,0))&""="",INDEX(Vendors!$F$5:$F$400,MATCH($A35,Vendors!$B$5:$B$400,0))&"",INDEX(Vendors!$K$5:$K$400,MATCH($A35,Vendors!$B$5:$B$400,0))&""),"")) | AH35: =IF(OR($A35="",AG35=""),"",IF(OR(F35="Complete",F35="Declined",F35="No Response"),"",IF(AG35<TODAY(),"OVERDUE",IF(AG35-TODAY()<=7,"Due 7d",""))))
B36: =IF($A36="","",IFERROR(INDEX(Vendors!$A$5:$A$400,MATCH($A36,Vendors!$B$5:$B$400,0)),"Not in Vendors tab")) | C36: =IF($A36="","",IFERROR(INDEX(Vendors!$H$5:$H$400,MATCH($A36,Vendors!$B$5:$B$400,0))&"","")) | D36: =IF($A36="","",IFERROR(INDEX(Vendors!$J$5:$J$400,MATCH($A36,Vendors!$B$5:$B$400,0))&"","")) | E36: =IF($A36="","",IFERROR(IF(INDEX(Vendors!$K$5:$K$400,MATCH($A36,Vendors!$B$5:$B$400,0))&""="",INDEX(Vendors!$F$5:$F$400,MATCH($A36,Vendors!$B$5:$B$400,0))&"",INDEX(Vendors!$K$5:$K$400,MATCH($A36,Vendors!$B$5:$B$400,0))&""),"")) | AH36: =IF(OR($A36="",AG36=""),"",IF(OR(F36="Complete",F36="Declined",F36="No Response"),"",IF(AG36<TODAY(),"OVERDUE",IF(AG36-TODAY()<=7,"Due 7d",""))))
... B64: =IF($A64="","",IFERROR(INDEX(Vendors!$A$5:$A$400,MATCH($A64,Vendors!$B$5:$B$400,0)),"Not in Vendors tab")) | C64: =IF($A64="","",IFERROR(INDEX(Vendors!$H$5:$H$400,MATCH($A64,Vendors!$B$5:$B$400,0))&"","")) | D64: =IF($A64="","",IFERROR(INDEX(Vendors!$J$5:$J$400,MATCH($A64,Vendors!$B$5:$B$400,0))&"","")) | E64: =IF($A64="","",IFERROR(IF(INDEX(Vendors!$K$5:$K$400,MATCH($A64,Vendors!$B$5:$B$400,0))&""="",INDEX(Vendors!$F$5:$F$400,MATCH($A64,Vendors!$B$5:$B$400,0))&"",INDEX(Vendors!$K$5:$K$400,MATCH($A64,Vendors!$B$5:$B$400,0))&""),"")) | AH64: =IF(OR($A64="",AG64=""),"",IF(OR(F64="Complete",F64="Declined",F64="No Response"),"",IF(AG64<TODAY(),"OVERDUE",IF(AG64-TODAY()<=7,"Due 7d",""))))

Sheet RFI_TEMPLATE
A1: =IF(C3="","RFI Activity (new - fill in the yellow cells)",C3&" | "&C6) -> RFI Activity (new - fill in the yellow cells)
A2: Yellow = enter data. Grey = formula, do not overwrite (except key item headers in row 13, which you may type over). Rename this tab to match the RFI ID, then add the ID to the RFI Register.
B3: RFI ID | H3: Vendors invited | I3: =COUNTA($A$15:$A$64) -> 0
B4: Project | H4: RFIs sent | I4: =COUNTIFS($A$15:$A$64,"<>",$F$15:$F$64,"<>Not Sent",$F$15:$F$64,"<>") -> 0
B5: Vendor Type | H5: Responses received | I5: =COUNTIF($F$15:$F$64,"Response Received")+COUNTIF($F$15:$F$64,"Under Review")+COUNTIF($F$15:$F$64,"Complete") -> 0
B6: RFI Title / Scope | H6: Declined / no response | I6: =COUNTIF($F$15:$F$64,"Declined")+COUNTIF($F$15:$F$64,"No Response") -> 0
B7: RFI Owner | H7: Actions overdue | I7: =COUNTIF($AH$15:$AH$64,"OVERDUE") -> 0
B8: Issue Date | H8: Key items: Review / Risk | I8: =COUNTIF($L$15:$L$64,"Review / Risk")+COUNTIF($N$15:$N$64,"Review / Risk")+COUNTIF($P$15:$P$64,"Review / Risk")+COUNTIF($R$15:$R$64,"Review / Risk")+COUNTIF($T$15:$T$64,"Review / Risk")+COUNTIF($V$15:$V$64,"Review / Risk")+COUNTIF($X$15:$X$64,"Review / Risk")+COUNTIF($Z$15:$Z$64,"Review / Risk")+COUNTIF($AB$15:$AB$64,"Review / Risk")+COUNTIF($AD$15:$AD$64,"Review / Risk") -> 0
B9: Response Due | H9: Key items: Fails | I9: =COUNTIF($L$15:$L$64,"Fails")+COUNTIF($N$15:$N$64,"Fails")+COUNTIF($P$15:$P$64,"Fails")+COUNTIF($R$15:$R$64,"Fails")+COUNTIF($T$15:$T$64,"Fails")+COUNTIF($V$15:$V$64,"Fails")+COUNTIF($X$15:$X$64,"Fails")+COUNTIF($Z$15:$Z$64,"Fails")+COUNTIF($AB$15:$AB$64,"Fails")+COUNTIF($AD$15:$AD$64,"Fails") -> 0
B10: Activity Status | H10: Days to response due | I10: =IF(C9="","",C9-TODAY())
A12: VENDOR & CONTACT (contacts pull from Vendors tab) | F12: RFI | K12: ="KEY ITEMS - "&IF($C$5="","pick a Vendor Type in C5",UPPER($C$5)) -> KEY ITEMS - pick a Vendor Type in C5 | AE12: NEXT ACTION
A13: Vendor | B13: Vendor ID | C13: Contact Name | D13: Contact Email | E13: Contact Phone | F13: RFI Status | G13: Date Sent | H13: Last Contact | I13: Response Date | J13: Qualification Status | K13: =IF($C$5="","Key item 1",IFERROR(IF(INDEX('Key Items'!$B$5:$O$14,1,MATCH($C$5,'Key Items'!$B$4:$O$4,0))="","Key item 1 (spare - type a name)",INDEX('Key Items'!$B$5:$O$14,1,MATCH($C$5,'Key Items'!$B$4:$O$4,0))),"Key item 1")) -> Key item 1 | M13: =IF($C$5="","Key item 2",IFERROR(IF(INDEX('Key Items'!$B$5:$O$14,2,MATCH($C$5,'Key Items'!$B$4:$O$4,0))="","Key item 2 (spare - type a name)",INDEX('Key Items'!$B$5:$O$14,2,MATCH($C$5,'Key Items'!$B$4:$O$4,0))),"Key item 2")) -> Key item 2 | O13: =IF($C$5="","Key item 3",IFERROR(IF(INDEX('Key Items'!$B$5:$O$14,3,MATCH($C$5,'Key Items'!$B$4:$O$4,0))="","Key item 3 (spare - type a name)",INDEX('Key Items'!$B$5:$O$14,3,MATCH($C$5,'Key Items'!$B$4:$O$4,0))),"Key item 3")) -> Key item 3 | Q13: =IF($C$5="","Key item 4",IFERROR(IF(INDEX('Key Items'!$B$5:$O$14,4,MATCH($C$5,'Key Items'!$B$4:$O$4,0))="","Key item 4 (spare - type a name)",INDEX('Key Items'!$B$5:$O$14,4,MATCH($C$5,'Key Items'!$B$4:$O$4,0))),"Key item 4")) -> Key item 4 | S13: =IF($C$5="","Key item 5",IFERROR(IF(INDEX('Key Items'!$B$5:$O$14,5,MATCH($C$5,'Key Items'!$B$4:$O$4,0))="","Key item 5 (spare - type a name)",INDEX('Key Items'!$B$5:$O$14,5,MATCH($C$5,'Key Items'!$B$4:$O$4,0))),"Key item 5")) -> Key item 5 | U13: =IF($C$5="","Key item 6",IFERROR(IF(INDEX('Key Items'!$B$5:$O$14,6,MATCH($C$5,'Key Items'!$B$4:$O$4,0))="","Key item 6 (spare - type a name)",INDEX('Key Items'!$B$5:$O$14,6,MATCH($C$5,'Key Items'!$B$4:$O$4,0))),"Key item 6")) -> Key item 6 | W13: =IF($C$5="","Key item 7",IFERROR(IF(INDEX('Key Items'!$B$5:$O$14,7,MATCH($C$5,'Key Items'!$B$4:$O$4,0))="","Key item 7 (spare - type a name)",INDEX('Key Items'!$B$5:$O$14,7,MATCH($C$5,'Key Items'!$B$4:$O$4,0))),"Key item 7")) -> Key item 7 | Y13: =IF($C$5="","Key item 8",IFERROR(IF(INDEX('Key Items'!$B$5:$O$14,8,MATCH($C$5,'Key Items'!$B$4:$O$4,0))="","Key item 8 (spare - type a name)",INDEX('Key Items'!$B$5:$O$14,8,MATCH($C$5,'Key Items'!$B$4:$O$4,0))),"Key item 8")) -> Key item 8 | AA13: =IF($C$5="","Key item 9",IFERROR(IF(INDEX('Key Items'!$B$5:$O$14,9,MATCH($C$5,'Key Items'!$B$4:$O$4,0))="","Key item 9 (spare - type a name)",INDEX('Key Items'!$B$5:$O$14,9,MATCH($C$5,'Key Items'!$B$4:$O$4,0))),"Key item 9")) -> Key item 9 | AC13: =IF($C$5="","Key item 10",IFERROR(IF(INDEX('Key Items'!$B$5:$O$14,10,MATCH($C$5,'Key Items'!$B$4:$O$4,0))="","Key item 10 (spare - type a name)",INDEX('Key Items'!$B$5:$O$14,10,MATCH($C$5,'Key Items'!$B$4:$O$4,0))),"Key item 10")) -> Key item 10 | AE13: Next Action | AF13: Next Action Owner | AG13: Next Action Date | AH13: Action Flag | AI13: Notes
K14: Response / notes | L14: Rating | M14: Response / notes | N14: Rating | O14: Response / notes | P14: Rating | Q14: Response / notes | R14: Rating | S14: Response / notes | T14: Rating | U14: Response / notes | V14: Rating | W14: Response / notes | X14: Rating | Y14: Response / notes | Z14: Rating | AA14: Response / notes | AB14: Rating | AC14: Response / notes | AD14: Rating
B15: =IF($A15="","",IFERROR(INDEX(Vendors!$A$5:$A$400,MATCH($A15,Vendors!$B$5:$B$400,0)),"Not in Vendors tab")) | C15: =IF($A15="","",IFERROR(INDEX(Vendors!$H$5:$H$400,MATCH($A15,Vendors!$B$5:$B$400,0))&"","")) | D15: =IF($A15="","",IFERROR(INDEX(Vendors!$J$5:$J$400,MATCH($A15,Vendors!$B$5:$B$400,0))&"","")) | E15: =IF($A15="","",IFERROR(IF(INDEX(Vendors!$K$5:$K$400,MATCH($A15,Vendors!$B$5:$B$400,0))&""="",INDEX(Vendors!$F$5:$F$400,MATCH($A15,Vendors!$B$5:$B$400,0))&"",INDEX(Vendors!$K$5:$K$400,MATCH($A15,Vendors!$B$5:$B$400,0))&""),"")) | AH15: =IF(OR($A15="",AG15=""),"",IF(OR(F15="Complete",F15="Declined",F15="No Response"),"",IF(AG15<TODAY(),"OVERDUE",IF(AG15-TODAY()<=7,"Due 7d",""))))
B16: =IF($A16="","",IFERROR(INDEX(Vendors!$A$5:$A$400,MATCH($A16,Vendors!$B$5:$B$400,0)),"Not in Vendors tab")) | C16: =IF($A16="","",IFERROR(INDEX(Vendors!$H$5:$H$400,MATCH($A16,Vendors!$B$5:$B$400,0))&"","")) | D16: =IF($A16="","",IFERROR(INDEX(Vendors!$J$5:$J$400,MATCH($A16,Vendors!$B$5:$B$400,0))&"","")) | E16: =IF($A16="","",IFERROR(IF(INDEX(Vendors!$K$5:$K$400,MATCH($A16,Vendors!$B$5:$B$400,0))&""="",INDEX(Vendors!$F$5:$F$400,MATCH($A16,Vendors!$B$5:$B$400,0))&"",INDEX(Vendors!$K$5:$K$400,MATCH($A16,Vendors!$B$5:$B$400,0))&""),"")) | AH16: =IF(OR($A16="",AG16=""),"",IF(OR(F16="Complete",F16="Declined",F16="No Response"),"",IF(AG16<TODAY(),"OVERDUE",IF(AG16-TODAY()<=7,"Due 7d",""))))
B17: =IF($A17="","",IFERROR(INDEX(Vendors!$A$5:$A$400,MATCH($A17,Vendors!$B$5:$B$400,0)),"Not in Vendors tab")) | C17: =IF($A17="","",IFERROR(INDEX(Vendors!$H$5:$H$400,MATCH($A17,Vendors!$B$5:$B$400,0))&"","")) | D17: =IF($A17="","",IFERROR(INDEX(Vendors!$J$5:$J$400,MATCH($A17,Vendors!$B$5:$B$400,0))&"","")) | E17: =IF($A17="","",IFERROR(IF(INDEX(Vendors!$K$5:$K$400,MATCH($A17,Vendors!$B$5:$B$400,0))&""="",INDEX(Vendors!$F$5:$F$400,MATCH($A17,Vendors!$B$5:$B$400,0))&"",INDEX(Vendors!$K$5:$K$400,MATCH($A17,Vendors!$B$5:$B$400,0))&""),"")) | AH17: =IF(OR($A17="",AG17=""),"",IF(OR(F17="Complete",F17="Declined",F17="No Response"),"",IF(AG17<TODAY(),"OVERDUE",IF(AG17-TODAY()<=7,"Due 7d",""))))
B18: =IF($A18="","",IFERROR(INDEX(Vendors!$A$5:$A$400,MATCH($A18,Vendors!$B$5:$B$400,0)),"Not in Vendors tab")) | C18: =IF($A18="","",IFERROR(INDEX(Vendors!$H$5:$H$400,MATCH($A18,Vendors!$B$5:$B$400,0))&"","")) | D18: =IF($A18="","",IFERROR(INDEX(Vendors!$J$5:$J$400,MATCH($A18,Vendors!$B$5:$B$400,0))&"","")) | E18: =IF($A18="","",IFERROR(IF(INDEX(Vendors!$K$5:$K$400,MATCH($A18,Vendors!$B$5:$B$400,0))&""="",INDEX(Vendors!$F$5:$F$400,MATCH($A18,Vendors!$B$5:$B$400,0))&"",INDEX(Vendors!$K$5:$K$400,MATCH($A18,Vendors!$B$5:$B$400,0))&""),"")) | AH18: =IF(OR($A18="",AG18=""),"",IF(OR(F18="Complete",F18="Declined",F18="No Response"),"",IF(AG18<TODAY(),"OVERDUE",IF(AG18-TODAY()<=7,"Due 7d",""))))
B19: =IF($A19="","",IFERROR(INDEX(Vendors!$A$5:$A$400,MATCH($A19,Vendors!$B$5:$B$400,0)),"Not in Vendors tab")) | C19: =IF($A19="","",IFERROR(INDEX(Vendors!$H$5:$H$400,MATCH($A19,Vendors!$B$5:$B$400,0))&"","")) | D19: =IF($A19="","",IFERROR(INDEX(Vendors!$J$5:$J$400,MATCH($A19,Vendors!$B$5:$B$400,0))&"","")) | E19: =IF($A19="","",IFERROR(IF(INDEX(Vendors!$K$5:$K$400,MATCH($A19,Vendors!$B$5:$B$400,0))&""="",INDEX(Vendors!$F$5:$F$400,MATCH($A19,Vendors!$B$5:$B$400,0))&"",INDEX(Vendors!$K$5:$K$400,MATCH($A19,Vendors!$B$5:$B$400,0))&""),"")) | AH19: =IF(OR($A19="",AG19=""),"",IF(OR(F19="Complete",F19="Declined",F19="No Response"),"",IF(AG19<TODAY(),"OVERDUE",IF(AG19-TODAY()<=7,"Due 7d",""))))
B20: =IF($A20="","",IFERROR(INDEX(Vendors!$A$5:$A$400,MATCH($A20,Vendors!$B$5:$B$400,0)),"Not in Vendors tab")) | C20: =IF($A20="","",IFERROR(INDEX(Vendors!$H$5:$H$400,MATCH($A20,Vendors!$B$5:$B$400,0))&"","")) | D20: =IF($A20="","",IFERROR(INDEX(Vendors!$J$5:$J$400,MATCH($A20,Vendors!$B$5:$B$400,0))&"","")) | E20: =IF($A20="","",IFERROR(IF(INDEX(Vendors!$K$5:$K$400,MATCH($A20,Vendors!$B$5:$B$400,0))&""="",INDEX(Vendors!$F$5:$F$400,MATCH($A20,Vendors!$B$5:$B$400,0))&"",INDEX(Vendors!$K$5:$K$400,MATCH($A20,Vendors!$B$5:$B$400,0))&""),"")) | AH20: =IF(OR($A20="",AG20=""),"",IF(OR(F20="Complete",F20="Declined",F20="No Response"),"",IF(AG20<TODAY(),"OVERDUE",IF(AG20-TODAY()<=7,"Due 7d",""))))
B21: =IF($A21="","",IFERROR(INDEX(Vendors!$A$5:$A$400,MATCH($A21,Vendors!$B$5:$B$400,0)),"Not in Vendors tab")) | C21: =IF($A21="","",IFERROR(INDEX(Vendors!$H$5:$H$400,MATCH($A21,Vendors!$B$5:$B$400,0))&"","")) | D21: =IF($A21="","",IFERROR(INDEX(Vendors!$J$5:$J$400,MATCH($A21,Vendors!$B$5:$B$400,0))&"","")) | E21: =IF($A21="","",IFERROR(IF(INDEX(Vendors!$K$5:$K$400,MATCH($A21,Vendors!$B$5:$B$400,0))&""="",INDEX(Vendors!$F$5:$F$400,MATCH($A21,Vendors!$B$5:$B$400,0))&"",INDEX(Vendors!$K$5:$K$400,MATCH($A21,Vendors!$B$5:$B$400,0))&""),"")) | AH21: =IF(OR($A21="",AG21=""),"",IF(OR(F21="Complete",F21="Declined",F21="No Response"),"",IF(AG21<TODAY(),"OVERDUE",IF(AG21-TODAY()<=7,"Due 7d",""))))
B22: =IF($A22="","",IFERROR(INDEX(Vendors!$A$5:$A$400,MATCH($A22,Vendors!$B$5:$B$400,0)),"Not in Vendors tab")) | C22: =IF($A22="","",IFERROR(INDEX(Vendors!$H$5:$H$400,MATCH($A22,Vendors!$B$5:$B$400,0))&"","")) | D22: =IF($A22="","",IFERROR(INDEX(Vendors!$J$5:$J$400,MATCH($A22,Vendors!$B$5:$B$400,0))&"","")) | E22: =IF($A22="","",IFERROR(IF(INDEX(Vendors!$K$5:$K$400,MATCH($A22,Vendors!$B$5:$B$400,0))&""="",INDEX(Vendors!$F$5:$F$400,MATCH($A22,Vendors!$B$5:$B$400,0))&"",INDEX(Vendors!$K$5:$K$400,MATCH($A22,Vendors!$B$5:$B$400,0))&""),"")) | AH22: =IF(OR($A22="",AG22=""),"",IF(OR(F22="Complete",F22="Declined",F22="No Response"),"",IF(AG22<TODAY(),"OVERDUE",IF(AG22-TODAY()<=7,"Due 7d",""))))
B23: =IF($A23="","",IFERROR(INDEX(Vendors!$A$5:$A$400,MATCH($A23,Vendors!$B$5:$B$400,0)),"Not in Vendors tab")) | C23: =IF($A23="","",IFERROR(INDEX(Vendors!$H$5:$H$400,MATCH($A23,Vendors!$B$5:$B$400,0))&"","")) | D23: =IF($A23="","",IFERROR(INDEX(Vendors!$J$5:$J$400,MATCH($A23,Vendors!$B$5:$B$400,0))&"","")) | E23: =IF($A23="","",IFERROR(IF(INDEX(Vendors!$K$5:$K$400,MATCH($A23,Vendors!$B$5:$B$400,0))&""="",INDEX(Vendors!$F$5:$F$400,MATCH($A23,Vendors!$B$5:$B$400,0))&"",INDEX(Vendors!$K$5:$K$400,MATCH($A23,Vendors!$B$5:$B$400,0))&""),"")) | AH23: =IF(OR($A23="",AG23=""),"",IF(OR(F23="Complete",F23="Declined",F23="No Response"),"",IF(AG23<TODAY(),"OVERDUE",IF(AG23-TODAY()<=7,"Due 7d",""))))
B24: =IF($A24="","",IFERROR(INDEX(Vendors!$A$5:$A$400,MATCH($A24,Vendors!$B$5:$B$400,0)),"Not in Vendors tab")) | C24: =IF($A24="","",IFERROR(INDEX(Vendors!$H$5:$H$400,MATCH($A24,Vendors!$B$5:$B$400,0))&"","")) | D24: =IF($A24="","",IFERROR(INDEX(Vendors!$J$5:$J$400,MATCH($A24,Vendors!$B$5:$B$400,0))&"","")) | E24: =IF($A24="","",IFERROR(IF(INDEX(Vendors!$K$5:$K$400,MATCH($A24,Vendors!$B$5:$B$400,0))&""="",INDEX(Vendors!$F$5:$F$400,MATCH($A24,Vendors!$B$5:$B$400,0))&"",INDEX(Vendors!$K$5:$K$400,MATCH($A24,Vendors!$B$5:$B$400,0))&""),"")) | AH24: =IF(OR($A24="",AG24=""),"",IF(OR(F24="Complete",F24="Declined",F24="No Response"),"",IF(AG24<TODAY(),"OVERDUE",IF(AG24-TODAY()<=7,"Due 7d",""))))
B25: =IF($A25="","",IFERROR(INDEX(Vendors!$A$5:$A$400,MATCH($A25,Vendors!$B$5:$B$400,0)),"Not in Vendors tab")) | C25: =IF($A25="","",IFERROR(INDEX(Vendors!$H$5:$H$400,MATCH($A25,Vendors!$B$5:$B$400,0))&"","")) | D25: =IF($A25="","",IFERROR(INDEX(Vendors!$J$5:$J$400,MATCH($A25,Vendors!$B$5:$B$400,0))&"","")) | E25: =IF($A25="","",IFERROR(IF(INDEX(Vendors!$K$5:$K$400,MATCH($A25,Vendors!$B$5:$B$400,0))&""="",INDEX(Vendors!$F$5:$F$400,MATCH($A25,Vendors!$B$5:$B$400,0))&"",INDEX(Vendors!$K$5:$K$400,MATCH($A25,Vendors!$B$5:$B$400,0))&""),"")) | AH25: =IF(OR($A25="",AG25=""),"",IF(OR(F25="Complete",F25="Declined",F25="No Response"),"",IF(AG25<TODAY(),"OVERDUE",IF(AG25-TODAY()<=7,"Due 7d",""))))
B26: =IF($A26="","",IFERROR(INDEX(Vendors!$A$5:$A$400,MATCH($A26,Vendors!$B$5:$B$400,0)),"Not in Vendors tab")) | C26: =IF($A26="","",IFERROR(INDEX(Vendors!$H$5:$H$400,MATCH($A26,Vendors!$B$5:$B$400,0))&"","")) | D26: =IF($A26="","",IFERROR(INDEX(Vendors!$J$5:$J$400,MATCH($A26,Vendors!$B$5:$B$400,0))&"","")) | E26: =IF($A26="","",IFERROR(IF(INDEX(Vendors!$K$5:$K$400,MATCH($A26,Vendors!$B$5:$B$400,0))&""="",INDEX(Vendors!$F$5:$F$400,MATCH($A26,Vendors!$B$5:$B$400,0))&"",INDEX(Vendors!$K$5:$K$400,MATCH($A26,Vendors!$B$5:$B$400,0))&""),"")) | AH26: =IF(OR($A26="",AG26=""),"",IF(OR(F26="Complete",F26="Declined",F26="No Response"),"",IF(AG26<TODAY(),"OVERDUE",IF(AG26-TODAY()<=7,"Due 7d",""))))
... B64: =IF($A64="","",IFERROR(INDEX(Vendors!$A$5:$A$400,MATCH($A64,Vendors!$B$5:$B$400,0)),"Not in Vendors tab")) | C64: =IF($A64="","",IFERROR(INDEX(Vendors!$H$5:$H$400,MATCH($A64,Vendors!$B$5:$B$400,0))&"","")) | D64: =IF($A64="","",IFERROR(INDEX(Vendors!$J$5:$J$400,MATCH($A64,Vendors!$B$5:$B$400,0))&"","")) | E64: =IF($A64="","",IFERROR(IF(INDEX(Vendors!$K$5:$K$400,MATCH($A64,Vendors!$B$5:$B$400,0))&""="",INDEX(Vendors!$F$5:$F$400,MATCH($A64,Vendors!$B$5:$B$400,0))&"",INDEX(Vendors!$K$5:$K$400,MATCH($A64,Vendors!$B$5:$B$400,0))&""),"")) | AH64: =IF(OR($A64="",AG64=""),"",IF(OR(F64="Complete",F64="Declined",F64="No Response"),"",IF(AG64<TODAY(),"OVERDUE",IF(AG64-TODAY()<=7,"Due 7d",""))))

Sheet Vendors
A1: Vendors
A2: Master vendor and contact list. RFI tabs look up contacts here, so update contacts in this tab only. Seeded 2026-10-05 from vendor landscape tracker (AI-seeded, unverified).
A4: Vendor ID | B4: Vendor Name | C4: Vendor Type | D4: Services / Product Line | E4: Website | F4: Main Phone | G4: Contact Page | H4: Primary Contact | I4: Contact Title | J4: Contact Email | K4: Direct Phone | L4: Qualification Status | M4: Data Verified? | N4: Notes
A5: ENV-001 | B5: ERM (Environmental Resources Management) | C5: Environmental Engineering | D5: Environmental, health, safety, risk and social consulting; permitting/impact assessment and sustainability services for energy projects | E5: https://www.erm.com/ | G5: https://www.erm.com/contact-us/ | L5: Discovery | M5: No - AI seeded
A6: ENV-002 | B6: Tetra Tech, Inc. | C6: Environmental Engineering | D6: Environmental consulting and engineering (water, environment, energy); permitting, site assessment, natural/cultural resources | E6: https://www.tetratech.com/ | F6: +1 (626) 351-4664 | G6: https://www.tetratech.com/contact/ | L6: Discovery | M6: No - AI seeded
A7: ENV-003 | B7: Stantec Inc. | C7: Environmental Engineering | D7: Environmental consulting and engineering; environmental permitting and studies for energy/infrastructure projects | E7: https://www.stantec.com/en | L7: Discovery | M7: No - AI seeded
A8: ENV-004 | B8: WSP Global Inc. (WSP USA) | C8: Environmental Engineering | D8: Environmental, engineering and permitting consulting; power & energy platform (incl. POWER Engineers and TRC) | E8: https://www.wsp.com/en-us | G8: https://www.wsp.com/en-us/contact-us | L8: Discovery | M8: No - AI seeded
A9: ENV-005 | B9: Terracon Consultants, Inc. | C9: Environmental Engineering | D9: Environmental site assessment (Phase I/II ESA), geotechnical, materials testing and facilities consulting | E9: https://www.terracon.com/ | F9: (800) 593-7777 | G9: https://www.terracon.com/contact/ | L9: Discovery | M9: No - AI seeded
A10: ENV-006 | B10: SWCA Environmental Consultants | C10: Environmental Engineering | D10: Environmental planning/permitting, natural & cultural resources, renewable energy environmental services | E10: https://www.swca.com/ | F10: 602-274-3831 | G10: https://www.swca.com/contact/ | L10: Discovery | M10: No - AI seeded
A11: ENV-007 | B11: Westwood Professional Services | C11: Environmental Engineering | D11: Renewable/BESS development support incl. environmental permitting, survey, and design of standalone and hybrid battery storage | E11: https://westwoodps.com/ | F11: 214-473-4640 (HQ); 1-888-937-5150 (toll-free) | G11: https://westwoodps.com/contact-us | L11: Discovery | M11: No - AI seeded
A12: ENV-008 | B12: HDR, Inc. | C12: Environmental Engineering | D12: Engineering, environmental and architecture consulting incl. environmental planning for infrastructure/energy | E12: https://www.hdrinc.com/ | F12: (402) 399-1000 | G12: https://www.hdrinc.com/contact-us | L12: Discovery | M12: No - AI seeded
A13: CIV-001 | B13: Kimley-Horn and Associates, Inc. | C13: Civil Engineering | D13: Site civil, grading/drainage, roads and planning/design; energy and infrastructure site development | E13: https://www.kimley-horn.com/ | G13: https://www.kimley-horn.com/contact/ | L13: Discovery | M13: No - AI seeded
A14: CIV-002 | B14: Westwood Professional Services | C14: Civil Engineering | D14: Civil/site design, survey, and permitting for utility-scale solar, wind and BESS; power delivery | E14: https://westwoodps.com/ | F14: 214-473-4640 (HQ); 1-888-937-5150 (toll-free) | G14: https://westwoodps.com/contact-us | L14: Discovery | M14: No - AI seeded
A15: CIV-003 | B15: Halff Associates, Inc. | C15: Civil Engineering | D15: Infrastructure consulting: site civil, drainage/water resources, survey, transportation | E15: https://www.halff.com/ | G15: https://www.halff.com/contact/ | L15: Discovery | M15: No - AI seeded
A16: CIV-004 | B16: Pape-Dawson Engineers | C16: Civil Engineering | D16: Civil engineering, survey, permitting; substation/switchyard civil design (170+ substations) and wind/solar civil | E16: https://www.pape-dawson.com/ | F16: 210-375-9000 | G16: https://www.pape-dawson.com/contact | L16: Discovery | M16: No - AI seeded
A17: CIV-005 | B17: Bowman Consulting Group Ltd. | C17: Civil Engineering | D17: Infrastructure design, civil engineering, survey, environmental; energy design incl. battery storage | E17: https://bowman.com/ | F17: (703) 464-1000 | G17: https://bowman.com/contact | L17: Discovery | M17: No - AI seeded
A18: CIV-006 | B18: Terracon Consultants, Inc. | C18: Civil Engineering | D18: Geotechnical engineering, materials testing and construction QA for site/foundation design | E18: https://www.terracon.com/ | F18: (800) 593-7777 | G18: https://www.terracon.com/contact/ | L18: Discovery | M18: No - AI seeded
A19: CIV-007 | B19: Burns & McDonnell | C19: Civil Engineering | D19: Engineering/EPC incl. site civil for power generation, substations and transmission | E19: https://www.burnsmcd.com/ | G19: https://info.burnsmcd.com/contact-us | L19: Discovery | M19: No - AI seeded
A20: STR-001 | B20: Walter P Moore | C20: Structural Engineering | D20: Structural and civil engineering, foundations, forensic engineering | E20: https://www.walterpmoore.com/ | F20: 800-364-7300 (general); 713-630-7300 (Houston HQ) | G20: https://www.walterpmoore.com/contact | L20: Discovery | M20: No - AI seeded
A21: STR-002 | B21: Sargent & Lundy | C21: Structural Engineering | D21: Power engineering incl. structural design for generation, BESS, substations and transmission structures | E21: https://www.sargentlundy.com/ | F21: (312) 269-2000 | G21: https://www.sargentlundy.com/contact-us | L21: Discovery | M21: No - AI seeded
A22: STR-003 | B22: Burns & McDonnell | C22: Structural Engineering | D22: Structural/civil design for substations, equipment foundations and power plants (engineering/EPC) | E22: https://www.burnsmcd.com/ | G22: https://info.burnsmcd.com/contact-us | L22: Discovery | M22: No - AI seeded
A23: STR-004 | B23: Black & Veatch | C23: Structural Engineering | D23: Engineering/EPC for power generation, power delivery and substations incl. structural design | E23: https://www.bv.com/ | F23: +1 913-458-2000 | G23: https://www.bv.com/contact-us | L23: Discovery | M23: No - AI seeded
A24: STR-005 | B24: POWER Engineers (a WSP company) | C24: Structural Engineering | D24: Power delivery engineering incl. substation and transmission structural/civil design; renewables & storage | E24: https://www.powereng.com/ | L24: Discovery | M24: No - AI seeded
A25: STR-006 | B25: Electrical Consultants, Inc. (ECI) | C25: Structural Engineering | D25: Power delivery only: civil, structural, electrical, survey for substations, transmission (to 765 kV), renewables and battery storage | E25: https://eciusa.com/ | L25: Discovery | M25: No - AI seeded
A26: ELE-001 | B26: POWER Engineers (a WSP company) | C26: Electrical Engineering | D26: Substation, transmission and interconnection engineering; renewables & storage power delivery | E26: https://www.powereng.com/ | L26: Discovery | M26: No - AI seeded
A27: ELE-002 | B27: Burns & McDonnell | C27: Electrical Engineering | D27: Substation/transmission design and EPC, interconnection and power generation electrical engineering | E27: https://www.burnsmcd.com/ | G27: https://info.burnsmcd.com/contact-us | L27: Discovery | M27: No - AI seeded
A28: ELE-003 | B28: Sargent & Lundy | C28: Electrical Engineering | D28: Grid/substation/transmission engineering, renewables and BESS electrical design, owner's engineer/due diligence | E28: https://www.sargentlundy.com/ | F28: (312) 269-2000 | G28: https://www.sargentlundy.com/contact-us | L28: Discovery | M28: No - AI seeded
A29: ELE-004 | B29: Black & Veatch | C29: Electrical Engineering | D29: Power delivery (substation/transmission) engineering and EPC; generation and storage | E29: https://www.bv.com/ | F29: +1 913-458-2000 | G29: https://www.bv.com/contact-us | L29: Discovery | M29: No - AI seeded
A30: ELE-005 | B30: Electric Power Engineers, LLC (EPE) | C30: Electrical Engineering | D30: Grid analysis/interconnection studies, utility engineering, regulatory/compliance; renewables & storage | E30: https://epeconsulting.com/ | F30: 512-382-6700 | G30: https://epeconsulting.com/contact | L30: Discovery | M30: No - AI seeded
A31: ELE-006 | B31: TRC Companies, Inc. (a member of WSP) | C31: Electrical Engineering | D31: Power & utilities engineering incl. substation, transmission and interconnection; environmental | E31: https://www.trccompanies.com/ | F31: +1 (860) 298-9692 | G31: https://www.trccompanies.com/contact-us/ | L31: Discovery | M31: No - AI seeded
A32: ELE-007 | B32: Leidos (Power Delivery / Energy) | C32: Electrical Engineering | D32: Substation design (4-765 kV), T&D lines, SCADA, system planning, NERC compliance for Texas utilities | E32: https://www.leidos.com/ | G32: https://www.leidos.com/contact-us | L32: Discovery | M32: No - AI seeded
A33: ELE-008 | B33: Electrical Consultants, Inc. (ECI) | C33: Electrical Engineering | D33: Power delivery engineering: substations, transmission to 765 kV, protection & control, renewables/BESS | E33: https://eciusa.com/ | L33: Discovery | M33: No - AI seeded
A34: FIRE-001 | B34: Jensen Hughes | C34: Fire Protection Engineering | D34: Lithium-ion/BESS risk consulting: hazard mitigation, NFPA 855/UL 9540A expertise, explosion protection (CFD, deflagration venting), large-scale fire testing | E34: https://www.jensenhughes.com/ | G34: https://www.jensenhughes.com/contact-us | L34: Discovery | M34: No - AI seeded
A35: FIRE-002 | B35: ESRG (Energy Safety Response Group) | C35: Fire Protection Engineering | D35: Energy-storage-only safety: testing, permitting/project review, emergency response plans & first-responder training, incident response | E35: https://www.energyresponsegroup.com/ | F35: 1-833-SAFE-ESS | G35: https://www.energyresponsegroup.com/contact | L35: Discovery | M35: No - AI seeded
A36: FIRE-003 | B36: Fire & Risk Alliance | C36: Fire Protection Engineering | D36: BESS code consulting (NFPA 855/IFC), HMA, UL 9540A assessment, deflagration (NFPA 68/69) and heat-flux modeling, FMEA, ERP and responder training | E36: https://fireriskalliance.com/ | F36: (301) 658-3060 | G36: https://fireriskalliance.com/contact-us/ | L36: Discovery | M36: No - AI seeded
A37: FIRE-004 | B37: Telgian Engineering & Consulting | C37: Fire Protection Engineering | D37: Fire protection engineering and code consulting; has published ESS fire-hazard guidance (BESS-specific services not detailed on site) | E37: https://www.telgian.com/ | F37: 480.753.5444 | G37: https://www.telgian.com/contact/ | L37: Discovery | M37: No - AI seeded
A38: FIRE-005 | B38: DNV | C38: Fire Protection Engineering | D38: Battery safety, risk analysis (QRA) and permitting support; energy storage technical due diligence and engineering review | E38: https://www.dnv.com/ | G38: https://www.dnv.us/contact/ | L38: Discovery | M38: No - AI seeded
A39: FIRE-006 | B39: UL Solutions Inc. | C39: Fire Protection Engineering | D39: UL 9540A testing, NFPA 855 documentation readiness review, fire/explosion hazard assessment, AHJ-focused technical support | E39: https://www.ul.com/ | F39: +1.877.854.3577 (customer service) | G39: https://www.ul.com/contact-us | L39: Discovery | M39: No - AI seeded
A40: FIRE-007 | B40: Exponent, Inc. | C40: Fire Protection Engineering | D40: BESS safety & risk consulting: fire protection engineering, emergency response planning, root-cause failure analysis, testing | E40: https://www.exponent.com/ | F40: (650) 326-9400 | L40: Discovery | M40: No - AI seeded
A41: OE-001 | B41: DNV | C41: Owner's Engineer | D41: Owner's engineering for energy storage: feasibility, dispatch modeling, RFP/tender support, design and procurement review, grid connection, warranty definition, FAT/SAT, construction PM, HSE | E41: https://www.dnv.com | F41: +1 281 396 1000 (DNV North America HQ, Houston) | G41: https://www.dnv.us/contact/ | L41: Discovery | M41: No - AI seeded
A42: OE-002 | B42: Enertis Applus+ | C42: Owner's Engineer | D42: Renewables and BESS technical advisory: design evaluation, site assessment, engineering, QA/QC, testing and optimization for developers, owners and financiers | E42: https://enertisapplus.com | F42: +1 415 671 4000 (US offices, San Francisco / Raleigh) | G42: https://enertisapplus.com/contact/ | L42: Discovery | M42: No - AI seeded
A43: OE-003 | B43: Black & Veatch | C43: Owner's Engineer | D43: BESS owner's engineer: EPC design review, construction monitoring, commissioning supervision, early operations oversight; firm reports 74 GWh supported as OE | E43: https://www.bv.com | F43: +1 913-458-2000 | G43: https://www.bv.com/contact-us | L43: Discovery | M43: No - AI seeded
A44: OE-004 | B44: Sargent & Lundy | C44: Owner's Engineer | D44: Owner's engineer for utility-scale solar + BESS: EPC RFP/specs, bid evaluation, contract negotiation support, review of LV/MV, collection, substation and transmission designs | E44: https://www.sargentlundy.com | F44: 312-269-2000 | G44: https://www.sargentlundy.com/contact-us | L44: Discovery | M44: No - AI seeded
A45: OE-005 | B45: Clean Energy Associates (Intertek CEA) | C45: Owner's Engineer | D45: Owner's engineer and technical due diligence; storage system QA, factory/production monitoring, supply-chain traceability for BESS and PV | E45: https://www.cea3.com | L45: Discovery | M45: No - AI seeded
A46: OE-006 | B46: Kimley-Horn | C46: Owner's Engineer | D46: BESS consulting incl. owner's engineering, feasibility, siting/permitting, interconnection studies, and civil/structural/electrical design | E46: https://www.kimley-horn.com | G46: https://www.kimley-horn.com/contact/submit-a-service-inquiry/ | L46: Discovery | M46: No - AI seeded
A47: OE-007 | B47: Natural Power | C47: Owner's Engineer | D47: Renewables-only consultant: owner's advisory, technology evaluation, field inspections and technical due diligence for standalone/co-located storage | E47: https://www.naturalpower.com | F47: +1 (518) 308 0200 (Saratoga Springs, NY office) | G47: https://www.naturalpower.com/us/contact | L47: Discovery | M47: No - AI seeded
A48: EOR-001 | B48: Burns & McDonnell | C48: Engineer of Record | D48: In-house design engineering and EPC for BESS, substations and transmission; delivered Texas BESS EPC (e.g., RWE Texas Waves II, LGES/SER West Texas) | E48: https://www.burnsmcd.com | F48: (816) 333-9400 | G48: https://info.burnsmcd.com/contact-us | L48: Discovery | M48: No - AI seeded
A49: EOR-002 | B49: Sargent & Lundy | C49: Engineer of Record | D49: Power engineering firm: electrical design for collection, substation and transmission; renewables and storage engineering | E49: https://www.sargentlundy.com | F49: 312-269-2000 | G49: https://www.sargentlundy.com/contact-us | L49: Discovery | M49: No - AI seeded
A50: EOR-003 | B50: POWER Engineers (Member of WSP) | C50: Engineer of Record | D50: Power delivery engineering: substation, transmission, renewables and storage design | E50: https://www.powereng.com | L50: Discovery | M50: No - AI seeded
A51: EOR-004 | B51: Westwood Professional Services | C51: Engineer of Record | D51: Design, permitting and optimization of standalone/hybrid BESS; substation and transmission line engineering; surveying | E51: https://www.westwoodps.com | F51: 1-888-937-5150 | G51: https://westwoodps.com/contact-us | L51: Discovery | M51: No - AI seeded
A52: EOR-005 | B52: Black & Veatch | C52: Engineer of Record | D52: Engineering and EPC for BESS and HV substations; firm reports 8.9 GWh delivered as BESS EPC | E52: https://www.bv.com | F52: +1 913-458-2000 | G52: https://www.bv.com/contact-us | L52: Discovery | M52: No - AI seeded
A53: EOR-006 | B53: Kimley-Horn | C53: Engineer of Record | D53: Detailed civil, structural and electrical BESS design incl. plant, HV substation and transmission/interconnection design | E53: https://www.kimley-horn.com | G53: https://www.kimley-horn.com/contact/submit-a-service-inquiry/ | L53: Discovery | M53: No - AI seeded
A54: EOR-007 | B54: Bowman Consulting Group | C54: Engineer of Record | D54: Energy design and engineering incl. BESS, electric power and transmission; civil/survey | E54: https://bowman.com | G54: https://bowman.com/contact/ | L54: Discovery | M54: No - AI seeded
A55: IE-001 | B55: DNV | C55: Independent Engineer | D55: Independent engineering and technical due diligence for BESS: vendor/design/safety review, performance validation, guarantee verification, bankability for investors/financiers | E55: https://www.dnv.com | F55: +1 281 396 1000 (DNV North America HQ, Houston) | G55: https://www.dnv.us/contact/ | L55: Discovery | M55: No - AI seeded
A56: IE-002 | B56: Enertis Applus+ | C56: Independent Engineer | D56: Lender's IE for BESS: project-finance technical due diligence, design/grid/warranty review, MC/SC/FC milestone certification (e.g., 550 MW / 1,433 MWh Texas portfolio for Excelsior/Lydian) | E56: https://enertisapplus.com | F56: +1 415 671 4000 (US offices) | G56: https://enertisapplus.com/contact/ | L56: Discovery | M56: No - AI seeded
A57: IE-003 | B57: Leidos | C57: Independent Engineer | D57: Independent engineering for project development, acquisition, financing and investment diligence across energy storage and other technologies | E57: https://www.leidos.com | F57: (571) 526-6000 | G57: https://www.leidos.com/contact | L57: Discovery | M57: No - AI seeded
A58: IE-004 | B58: Sargent & Lundy | C58: Independent Engineer | D58: BESS independent engineering due diligence for investors/tax equity: use-case modeling, module warranty terms, fire protection design | E58: https://www.sargentlundy.com | F58: 312-269-2000 | G58: https://www.sargentlundy.com/contact-us | L58: Discovery | M58: No - AI seeded
A59: IE-005 | B59: Natural Power | C59: Independent Engineer | D59: Independent engineering and technical due diligence for lenders/investors on wind, solar and storage; new Head of IE North America (Dec 2025) | E59: https://www.naturalpower.com | F59: +1 (518) 308 0200 (Saratoga Springs, NY office) | G59: https://www.naturalpower.com/us/contact | L59: Discovery | M59: No - AI seeded
A60: IE-006 | B60: UL Solutions | C60: Independent Engineer | D60: Energy Storage Advisory: IE and technical advisory for project financing, tax equity, sales and acquisitions (contracts, financial models, designs); BESS testing/certification | E60: https://www.ul.com | F60: (847) 272-8800 | L60: Discovery | M60: No - AI seeded
A61: BESS-001 | B61: Tesla (Tesla Energy) | C61: BESS Equipment | D61: Megapack 2 / Megapack 2 XL / Megapack 3 (~5 MWh) / Megablock (4x Megapack 3 + transformer + switchgear, ~20 MWh) | E61: https://www.tesla.com/megapack | G61: https://www.tesla.com/megapack | L61: Discovery | M61: No - AI seeded | N61: Landscape: FEOC Review
A62: BESS-002 | B62: Fluence Energy | C62: BESS Equipment | D62: Grid-scale BESS (Gridstack/Smartstack platforms), US domestic-content offering | E62: https://fluenceenergy.com | L62: Discovery | M62: No - AI seeded | N62: Landscape: FEOC Review
A63: BESS-003 | B63: Sungrow | C63: BESS Equipment | D63: PowerTitan 3.0 AC block (6.9 MWh per 20-ft container); PowerStack (C&I) | E63: https://www.sungrowpower.com/us/en | F63: +1 833 747 6937 | G63: https://www.sungrowpower.com/us/en/about-us/contact-us | L63: Discovery | M63: No - AI seeded | N63: Landscape: FEOC Review
A64: BESS-004 | B64: LG Energy Solution Vertech | C64: BESS Equipment | D64: Containerized LFP grid-scale BESS + AEROS controls/analytics; integration and lifecycle services | L64: Discovery | M64: No - AI seeded | N64: Landscape: FEOC Review
A65: BESS-005 | B65: Samsung SDI | C65: BESS Equipment | D65: Samsung Battery Box (SBB) 2.0 — prismatic LFP DC block (cell/DC supplier; requires PCS/EMS integrator) | E65: https://www.samsungsdi.com | L65: Discovery | M65: No - AI seeded
A66: BESS-006 | B66: Wärtsilä Energy Storage | C66: BESS Equipment | D66: Quantum3 AC-block BESS (introduced Sep 2024); GEMS software | E66: https://www.wartsila.com/usa | F66: +1 281 233 6200 | G66: https://www.wartsila.com/usa/about/contact-us | L66: Discovery | M66: No - AI seeded | N66: Landscape: FEOC Review
A67: BESS-007 | B67: FlexGen Power Systems | C67: BESS Equipment | D67: BESS integration with HybridOS EMS; legacy Powin fleet support (Powin assets/IP acquired) | E67: https://www.flexgen.com | F67: 855-327-5674 | G67: https://www.flexgen.com/contact-us | L67: Discovery | M67: No - AI seeded | N67: Landscape: FEOC Review
A68: BESS-008 | B68: Hithium | C68: BESS Equipment | D68: LFP BESS modules/systems (∞Power 6.25 MWh platform) | E68: https://hithium.com | L68: Discovery | M68: No - AI seeded | N68: Landscape: FEOC Review
A69: BESS-009 | B69: Canadian Solar e-STORAGE | C69: BESS Equipment | D69: Utility-scale BESS (SolBank platform) and EPC/LTSA services | E69: https://www.csisolar.com/e-storage/ | L69: Discovery | M69: No - AI seeded | N69: Landscape: FEOC Review
A70: BESS-010 | B70: Prevalon Energy (now Nextpower) | C70: BESS Equipment | D70: HD5 AC / HD5 DC BESS platforms, insightOS, service/LTSA | E70: https://prevalonenergy.com | G70: https://prevalonenergy.com/contact-us/ | L70: Discovery | M70: No - AI seeded | N70: Landscape: FEOC Review
A71: MVT-001 | B71: Hitachi Energy | C71: MV Transformers | D71: Pad-mount and distribution transformers (single-phase pad-mount from Reynosa); large distribution transformers (South Boston, VA) | E71: https://www.hitachienergy.com/us/en | L71: Discovery | M71: No - AI seeded
A72: MVT-002 | B72: Eaton | C72: MV Transformers | D72: Three-phase pad-mount transformers; single-phase/pole/pad-mount | E72: https://www.eaton.com/us/en-us.html | L72: Discovery | M72: No - AI seeded
A73: MVT-003 | B73: Prolec GE (GE Vernova) | C73: MV Transformers | D73: Three-phase pad-mount (Shreveport) and medium power / substation transformers (Goldsboro) | E73: https://www.prolec.energy | L73: Discovery | M73: No - AI seeded
A74: MVT-004 | B74: WEG | C74: MV Transformers | D74: Distribution and power transformers (WEG Transformers USA); confirm three-phase 34.5 kV pad-mount offering | E74: https://www.weg.net/institutional/US/en/ | L74: Discovery | M74: No - AI seeded
A75: MVT-005 | B75: Virginia Transformer Corp | C75: MV Transformers | D75: E2X pad-mount; liquid substation/GSU (500 kVA–1,400 MVA); BESS listed as served industry | E75: https://www.vatransformer.com | F75: (540) 345-9892 | G75: https://www.vatransformer.com | L75: Discovery | M75: No - AI seeded
A76: MVT-006 | B76: ERMCO | C76: MV Transformers | D76: Three-phase and single-phase pad-mount distribution transformers (incl. ECO-PAD) | E76: https://www.ermco-eci.com | G76: https://www.ermco-eci.com/ | L76: Discovery | M76: No - AI seeded
A77: MVT-007 | B77: Howard Industries | C77: MV Transformers | D77: Distribution transformers incl. large three-phase pad-mount 750–10,000 kVA (utilities, data centers, BESS) | E77: https://www.howard.com | F77: (601) 425-3151 | L77: Discovery | M77: No - AI seeded
A78: MVT-008 | B78: Maddox Transformer | C78: MV Transformers | D78: New and remanufactured three-phase pad-mount and substation transformers; in-stock inventory | E78: https://www.maddox.com | F78: 1-800-270-2011 | G78: https://www.maddox.com/contact | L78: Discovery | M78: No - AI seeded
A79: MVT-009 | B79: JST Power Equipment | C79: MV Transformers | D79: Liquid-filled pad-mount 1- and 3-phase (25–6,000 kVA, up to 35 kV); MV switchgear and packaged substations | E79: https://www.jstpower.com | G79: https://jstpower.com/contact/ | L79: Discovery | M79: No - AI seeded
A80: MVT-010 | B80: Sunbelt Solomon | C80: MV Transformers | D80: New and refurbished pad-mount and substation transformers; rentals and field services | E80: https://www.sunbeltsolomon.com | F80: 888-691-4712 | G80: https://www.sunbeltsolomon.com/ | L80: Discovery | M80: No - AI seeded
A81: HVB-001 | B81: Hitachi Energy | C81: HV Breakers | D81: Dead tank circuit breakers up to 420 kV (incl. 362 kV); EconiQ SF6-free; PASS hybrid switchgear | E81: https://www.hitachienergy.com/us/en | L81: Discovery | M81: No - AI seeded
A82: HVB-002 | B82: Siemens Energy | C82: HV Breakers | D82: Dead tank breakers 72.5–550 kV (US SPS 362 kV); Blue SF6-free portfolio | E82: https://siemens-energy.com/us/en/home.html | G82: https://siemens-energy.com/us/en/home/products-services/product/dead-tank.html | L82: Discovery | M82: No - AI seeded
A83: HVB-003 | B83: GE Vernova | C83: HV Breakers | D83: Dead tank breakers up to 550 kV (DT1-362 for 362 kV); g3 SF6-free models (72.5/145 kV) | E83: https://www.gevernova.com/grid-solutions/equipment/circuit-breakers/dead-tank-circuit-breakers | L83: Discovery | M83: No - AI seeded
A84: HVB-004 | B84: Mitsubishi Electric Power Products (MEPPI) | C84: HV Breakers | D84: Dead tank gas circuit breakers 72.5–800 kV (362 kV up to 63 kA) | E84: https://www.meppi.com | G84: https://www.meppi.com/contact-us | L84: Discovery | M84: No - AI seeded
A85: HVB-005 | B85: Hyosung HICO | C85: HV Breakers | D85: Gas circuit breakers 72.5–800 kV | E85: https://www.hyosungheavyindustries.com/en/business/power-products/P010104 | L85: Discovery | M85: No - AI seeded
A86: HVB-006 | B86: HD Hyundai Electric (watchlist) | C86: HV Breakers | D86: SF6-free switchgear/breakers; 362 kV dead tank breaker planned for 2028 launch | L86: Discovery | M86: No - AI seeded
A87: MVB-001 | B87: Eaton | C87: MV Breakers / Switchgear | D87: VacClad-HD 38 kV metal-clad switchgear with VCPW-HD vacuum breakers (1,200–3,000 A, up to 40 kA) | E87: https://www.eaton.com/us/en-us.html | L87: Discovery | M87: No - AI seeded
A88: MVB-002 | B88: Schneider Electric | C88: MV Breakers / Switchgear | D88: MV switchgear: air-insulated, gas-insulated and shielded solid insulation | E88: https://www.se.com/us/en/ | L88: Discovery | M88: No - AI seeded
A89: MVB-003 | B89: ABB | C89: MV Breakers / Switchgear | D89: MV breakers/switchgear and grid components (Electrification); confirm 38 kV outdoor breaker line | E89: https://electrification.us.abb.com | L89: Discovery | M89: No - AI seeded
A90: MVB-004 | B90: Siemens (Smart Infrastructure) | C90: MV Breakers / Switchgear | D90: SDV7 / SDV7-AR outdoor distribution vacuum breakers (15.5–38 kV, up to 40 kA, 200 kV BIL) | E90: https://www.siemens.com/us/en.html | F90: +1 (800) 347-6659 | L90: Discovery | M90: No - AI seeded
A91: MVB-005 | B91: Powell Industries | C91: MV Breakers / Switchgear | D91: ANSI metal-clad (PowlVac, Power/Vac) and metal-enclosed switchgear; E-houses / PCR packaged solutions | E91: https://www.powellind.com | G91: https://www.powellind.com/contact | L91: Discovery | M91: No - AI seeded
A92: MVB-006 | B92: S&C Electric Company | C92: MV Breakers / Switchgear | D92: MV switching and protection (pad-mounted / metal-enclosed switchgear, distribution switching); confirm 34.5 kV collector-system products | E92: https://www.sandc.com | L92: Discovery | M92: No - AI seeded
A93: MVB-007 | B93: G&W Electric | C93: MV Breakers / Switchgear | D93: Switchgear, reclosers, overhead switches, current-limiting protection, cable accessories; confirm 38 kV ratings | E93: https://www.gwelectric.com | L93: Discovery | M93: No - AI seeded
A94: EPC-001 | B94: Mortenson | C94: EPC Contractor | D94: Full EPC for utility-scale BESS incl. project substation and gen-tie (e.g., Revolution 150 MW / 300 MWh, Crane TX, ERCOT) | E94: https://www.mortenson.com | F94: 763.522.2100 | G94: https://www.mortenson.com/contact | L94: Discovery | M94: No - AI seeded
A95: EPC-002 | B95: McCarthy Building Companies | C95: EPC Contractor | D95: Renewable Energy & Storage group: utility-scale BESS and solar EPC | E95: https://www.mccarthy.com | F95: 314-968-3300 | G95: https://www.mccarthy.com/contact-us | L95: Discovery | M95: No - AI seeded
A96: EPC-003 | B96: Blattner (Quanta Services) | C96: EPC Contractor | D96: Utility-scale wind, solar and energy storage construction/EPC incl. HV substation and collection | E96: https://www.blattnercompany.com | F96: 320-356-7351 | G96: https://www.blattnercompany.com/contact | L96: Discovery | M96: No - AI seeded
A97: EPC-004 | B97: Burns & McDonnell | C97: EPC Contractor | D97: Self-perform EPC for BESS, substations and transmission; Texas BESS EPC references | E97: https://www.burnsmcd.com | F97: (816) 333-9400 | G97: https://info.burnsmcd.com/contact-us | L97: Discovery | M97: No - AI seeded
A98: EPC-005 | B98: Primoris Services (Primoris Renewable Energy) | C98: EPC Contractor | D98: Utility-scale solar and BESS EPC; T&D/substation via Primoris T&D and Power Line Services | E98: https://www.prim.com | F98: (214) 740-5600 | G98: https://www.prim.com/contact | L98: Discovery | M98: No - AI seeded
A99: EPC-006 | B99: Rosendin | C99: EPC Contractor | D99: Electrical contractor/EPC for utility-scale wind, solar, BESS and HV substation | E99: https://www.rosendin.com | F99: (408) 286-2800 | G99: https://www.rosendin.com/contact/ | L99: Discovery | M99: No - AI seeded
A100: EPC-007 | B100: SOLV Energy | C100: EPC Contractor | D100: Utility-scale solar and BESS EPC, substation/HV, and O&M | E100: https://solvenergy.com | F100: 858.251.4888 | G100: https://solvenergy.com/contact/ | L100: Discovery | M100: No - AI seeded
A101: EPC-008 | B101: MasTec Renewables (incl. former IEA, Wanzek, White Construction) | C101: EPC Contractor | D101: Utility-scale solar, wind and battery storage EPC; parent also provides transmission and substation (Power Delivery segment) | E101: https://www.mastec.com | L101: Discovery | M101: No - AI seeded
...

Sheet Key Items
A1: Key Items
A2: Default key items per vendor type (slots 1-10). RFI tabs use these as column headers. Edit a cell to change the default; type in a blank slot to add a key item.
A4: Slot | B4: Environmental Engineering | C4: Civil Engineering | D4: Structural Engineering | E4: Electrical Engineering | F4: Fire Protection Engineering | G4: Owner's Engineer | H4: Engineer of Record | I4: Independent Engineer | J4: BESS Equipment | K4: MV Transformers | L4: HV Breakers | M4: MV Breakers / Switchgear | N4: EPC Contractor | O4: Software
A5: 1 | B5: Permitting experience (TCEQ, USACE, TPWD) | C5: Relevant BESS / substation site experience | D5: BESS enclosure / substation structure experience | E5: 345 kV / ERCOT interconnection experience | F5: NFPA 855 / UL 9540A experience | G5: BESS OE portfolio (MW / MWh) | H5: 345 kV substation & collector design experience | I5: Lender acceptance / bankability record | J5: Lead time (weeks ARO) | K5: Lead time (weeks ARO) | L5: Lead time (weeks ARO) | M5: Lead time (weeks ARO) | N5: BESS & substation EPC experience (MW / MWh) | O5: ERCOT QSE / market integration
A6: 2 | B6: Relevant BESS / ERCOT project experience | C6: Texas PE / firm registration | D6: Texas PE / firm registration | E6: Texas PE / firm registration | F6: Hazard mitigation analysis (HMA) capability | G6: Scope coverage (design review, FAT, site QA) | H6: Texas PE / firm registration | I6: BESS IE portfolio (MW / MWh) | J6: FEOC compliance | K6: FEOC compliance / country of origin | L6: FEOC compliance / country of origin | M6: FEOC compliance / country of origin | N6: 345 kV self-perform capability | O6: Cybersecurity (SOC 2, NERC CIP)
A7: 3 | B7: Key personnel & availability | C7: Key personnel & availability | D7: Key personnel & availability | E7: Studies capability (ETAP, PSCAD, PSS/E) | F7: AHJ / fire marshal coordination in Texas | G7: Key personnel & availability | H7: Design tools (PLS-CADD, ETAP, AutoCAD) | I7: Independence / conflicts | J7: Cell chemistry & cell / module origin | K7: Ratings & standards (IEEE C57, DOE efficiency) | L7: Rating (362 kV class, interrupting kA) | M7: Rating (kV class, kA, IEEE C37) | N7: Bonding capacity | O7: Hosting & data origin (FEOC)
A8: 4 | B8: Fee basis / rate sheet | C8: Fee basis / rate sheet | D8: Fee basis / rate sheet | E8: Key personnel & availability | F8: Key personnel & availability | G8: Independence / conflicts | H8: Key personnel & availability | I8: Key personnel & availability | J8: Certifications (UL 9540, UL 9540A, NFPA 855) | K8: Production capacity / slot availability | L8: Insulating gas (SF6 / SF6-free) | M8: Arc-resistant design | N8: Safety record (EMR, TRIR) | O8: Integration (SCADA, APIs)
A9: 5 | B9: Insurance (PL / GL limits) | C9: Insurance (PL / GL limits) | D9: Insurance (PL / GL limits) | E9: Fee basis / rate sheet | F9: Fee basis / rate sheet | G9: Fee basis / rate sheet | H9: Fee basis / rate sheet | I9: Fee basis | J9: Warranty & performance guarantee | K9: Factory testing & witness (FAT) | L9: Utility / ERCOT references | M9: Warranty | N9: Financial strength | O9: Pricing model
A10: 6 | B10: Schedule capacity & turnaround | C10: Schedule capacity & start date | D10: Schedule capacity & start date | E10: Insurance (PL / GL limits) | F10: Insurance (PL / GL limits) | G10: Insurance (PL / GL limits) | H10: Insurance (PL limit) | I10: Report turnaround | J10: Domestic content (ITC adder) | K10: Warranty | L10: Warranty | M10: Texas field service support | N10: Texas labor availability | O10: Support / SLA
A11: 7 | B11: Texas office / field staff | C11: Geotech / survey capability | D11: Design software & standards (ASCE 7, ACI) | E11: Schedule capacity & start date | F11: Schedule capacity & turnaround | G11: Texas / ERCOT presence | H11: Schedule capacity & start date | I11: Insurance (PL / GL limits) | J11: Bankability / financial strength | K11: Domestic content | L11: Texas field service support | N11: Risk appetite (LDs, wrap, insurance) | O11: References
A12: 8
A13: 9
A14: 10
A16: Blank slots = spare. A header typed directly on an RFI tab overrides the default for that RFI only.

Sheet Projects
A1: Projects
A2: One row per Agentic project. RFI tabs pick their project from the Project Name column. Placeholder rows: rename them.
A4: Project ID | B4: Project Name | C4: County / Location | D4: ERCOT Load Zone | E4: POI Voltage (kV) | F4: Size (MW / MWh) | G4: Project Manager | H4: Status | I4: Notes
A5: PRJ-001 | B5: Seven Angels BESS | I5: Placeholder added at setup 2026-10-05
A6: PRJ-002 | B6: Project B (placeholder - rename) | I6: Placeholder added at setup 2026-10-05
A7: PRJ-003 | B7: Project C (placeholder - rename) | I7: Placeholder added at setup 2026-10-05

Sheet Lists
A1: Lists
A2: Dropdown values used across the workbook. Add owners in the yellow cells; change other lists only with a Change Log entry.
A4: RFI Vendor Status | B4: RFI Activity Status | C4: Qualification Status | D4: Key Item Rating | E4: Action Owners (add names) | F4: Vendor Types
A5: Not Sent | B5: Planning | C5: Discovery | D5: Meets | E5: Jason Knedlhans | F5: Environmental Engineering
A6: Sent | B6: Issued | C6: Prequalified | D6: Review / Risk | E6: Sam Brandin | F6: Civil Engineering
A7: Acknowledged | B7: Responses Due | C7: Qualified | D7: Fails | E7: Matt Shae | F7: Structural Engineering
A8: Clarifications Open | B8: Evaluation | C8: AVL | D8: Not Rated | E8: Project Manager | F8: Electrical Engineering
A9: Response Received | B9: Closed - Advance to RFP | C9: On Hold | E9: Project Engineer | F9: Fire Protection Engineering
A10: Under Review | B10: Closed - No Further Action | C10: Disqualified | E10: Vendor | F10: Owner's Engineer
A11: Complete | B11: Cancelled | F11: Engineer of Record
A12: Declined | F12: Independent Engineer
A13: No Response | F13: BESS Equipment
F14: MV Transformers
F15: HV Breakers
F16: MV Breakers / Switchgear
F17: EPC Contractor
F18: Software

Sheet Change Log
A1: Change Log
A2: Record every structural change (tabs, columns, lists, key item defaults, formulas) and each new RFI tab. Routine data entry is covered by SharePoint version history.
A4: Date | B4: Version | C4: Changed By | D4: Tab / Area | E4: Change | F4: Reason / Approved By
A5: 46300 | B5: 1.0 | C5: Claude (AI) for Jason Knedlhans | D5: All | E5: Initial release. Replaces the HTML RFI tracker (claude.ai artifact, retired). Tabs: Read Me, Dashboard, RFI Register, RFI-001 (example), RFI_TEMPLATE, Vendors (109 vendors from vendor landscape tracker), Key Items, Projects (placeholders), Lists, Change Log. | F5: Requested by Jason Knedlhans; pending review
