Workbook
Name lst_fin: Lists!$C$2:$C$5
Name lst_rfx: Lists!$B$2:$B$9
Name lst_scr: Lists!$D$2:$D$6
Name lst_status: Lists!$A$2:$A$7
Name lst_ver: Lists!$E$2:$E$3

Sheet Read Me
A1: Vendor Landscape Tracker
A2: Agentic — Procurement | v01 | 2026-10-05 | Owner: Jason Knedlhans | Classification: Internal
A4: PURPOSE
A5: What | B5: Landscape of candidate vendors for each Agentic procurement scope; feeds prequalification, RFI/RFP/RFQ invitations and the AVL (Objectives 1 and 4).
A6: Structure | B6: Dashboard (live counts) → 14 vendor tabs (one per scope) → Lists (dropdown values) → Sources (all URLs used to seed).
A8: HOW TO USE
A9: Add a vendor | B9: Type in the next empty row of the right tab. Use the next Vendor ID (e.g., ENV-009). Dashboard updates automatically.
A10: Yellow columns | B10: Enter from direct vendor contact: Primary Contact Name/Title/Email/Phone, Last Contact Date, Next Action, Next Action Due.
A11: Dropdowns | B11: Qualification Status, Last RFx Stage, Financial Strength, Supply Chain Risk, Data Verified?. Edit options on the Lists tab only.
A12: Verify before use | B12: Set 'Data Verified?' to 'Yes - Verified' once HQ, contact and ownership are confirmed with the vendor.
A13: Overdue | B13: Next Action Due turns red when past today.
A15: QUALIFICATION STATUS (per CONTEXT.md process)
A16: Discovery | B16: Identified in market scan; no contact yet. All seeded vendors start here.
A17: Prequalified | B17: Passed prequalification (as part of or before RFI).
A18: Qualified | B18: Passed qualification (as part of RFP).
A19: AVL | B19: On Approved Vendor List; eligible for RFQ.
A20: On Hold | B20: Paused (capacity, pending M&A, info outstanding).
A21: Disqualified | B21: Failed a gate or excluded; record reason in Notes.
A23: ADDITIONAL TRACKED ITEMS (selected 2026-10-05)
A24: Financial Strength / Bankability | B24: Ownership/parent, financial notes (M&A, listings, scale), and a rating (Strong / Adequate / Weak / Not Assessed). Why: counterparty, warranty and lender-acceptance risk on long-lead, high-value scopes.
A25: Supply Chain / Origin Risk | B25: Manufacturing/cell origin or staff/delivery origin, plus a risk flag. Why: FEOC rules, tariffs and lead-time exposure, esp. BESS and transformers.
A27: SEEDED DATA — LIMITS AND RISKS
A28: Status | B28: Seeded by AI web research on 2026-10-05. Every seeded row is 'Discovery' and 'No - AI seeded'. Not confirmed market data.
A29: Contacts | B29: Only main phone numbers/contact pages published on official pages were entered. No individual contacts were added; blanks mean not confirmed.
A30: Financial Strength | B30: All set to 'Not Assessed'. AI did not rate financial strength; ratings need statements, credit reports or lender acceptance.
A31: FEOC Review flag | B31: Set where sources mention Chinese-parent or China-origin cell exposure. It is a review flag, not a legal determination; confirm with counsel/tax advisor.
A32: Pending M&A (as of 2026-10-05) | B32: Bowman (Bernhard Capital, pending), Jensen Hughes (New Mountain Capital, expected Q4 2026), PCI Energy Solutions (Mitsubishi Electric, pending), Enverus (Blackstone; close not confirmed). Re-check before RFx.
A33: Common ownership | B33: WSP owns POWER Engineers and TRC; MasTec owns former IEA/Wanzek/White. Treat as related bidders when assessing competition.
A34: Thin markets | B34: HV Breakers: ~5 suppliers with current 345 kV offerings (HD Hyundai listed as watchlist). Expect long lead times; engage early.
A35: Duplicates | B35: Some firms sit on several tabs by design (one row per scope). Keep contact data consistent across tabs.
A36: Software scope | B36: Assumed: ERCOT QSE/bidding, BESS EMS/optimization, asset performance, market data. Adjust if procurement/ERP software was intended.
A38: Legend
A39: Enter from vendor | B39: Yellow fill = user-entered fields
A40: Vendor | B40: Column group band on vendor tabs
A41: HQ Location | B41: Column group band on vendor tabs
A42: Contact Information | B42: Column group band on vendor tabs
A43: Qualification | B43: Column group band on vendor tabs
A44: Financial Strength / Bankability | B44: Column group band on vendor tabs
A45: Supply Chain / Origin Risk | B45: Column group band on vendor tabs
A46: Tracking | B46: Column group band on vendor tabs

Sheet Dashboard
A1: Vendor Landscape — Dashboard
A2: All figures are live formulas over the vendor tabs.
A4: Vendor Tab | B4: Total | C4: Discovery | D4: Prequalified | E4: Qualified | F4: AVL | G4: On Hold | H4: Disqualified | I4: FEOC Review | J4: High SC Risk | K4: Fin. Not Assessed | L4: Overdue Actions | M4: Unverified
A5: Env Eng | B5: =COUNTA('Env Eng'!$B$5:$B$300) -> 8 | C5: =COUNTIF('Env Eng'!$P$5:$P$300,"Discovery") -> 8 | D5: =COUNTIF('Env Eng'!$P$5:$P$300,"Prequalified") -> 0 | E5: =COUNTIF('Env Eng'!$P$5:$P$300,"Qualified") -> 0 | F5: =COUNTIF('Env Eng'!$P$5:$P$300,"AVL") -> 0 | G5: =COUNTIF('Env Eng'!$P$5:$P$300,"On Hold") -> 0 | H5: =COUNTIF('Env Eng'!$P$5:$P$300,"Disqualified") -> 0 | I5: =COUNTIF('Env Eng'!$W$5:$W$300,"FEOC Review") -> 0 | J5: =COUNTIF('Env Eng'!$W$5:$W$300,"High") -> 0 | K5: =COUNTIF('Env Eng'!$T$5:$T$300,"Not Assessed") -> 8 | L5: =COUNTIFS('Env Eng'!$Z$5:$Z$300,"<"&TODAY(),'Env Eng'!$Z$5:$Z$300,"<>") -> 0 | M5: =COUNTIF('Env Eng'!$AB$5:$AB$300,"No - AI seeded") -> 8
A6: Civil Eng | B6: =COUNTA('Civil Eng'!$B$5:$B$300) -> 7 | C6: =COUNTIF('Civil Eng'!$P$5:$P$300,"Discovery") -> 7 | D6: =COUNTIF('Civil Eng'!$P$5:$P$300,"Prequalified") -> 0 | E6: =COUNTIF('Civil Eng'!$P$5:$P$300,"Qualified") -> 0 | F6: =COUNTIF('Civil Eng'!$P$5:$P$300,"AVL") -> 0 | G6: =COUNTIF('Civil Eng'!$P$5:$P$300,"On Hold") -> 0 | H6: =COUNTIF('Civil Eng'!$P$5:$P$300,"Disqualified") -> 0 | I6: =COUNTIF('Civil Eng'!$W$5:$W$300,"FEOC Review") -> 0 | J6: =COUNTIF('Civil Eng'!$W$5:$W$300,"High") -> 0 | K6: =COUNTIF('Civil Eng'!$T$5:$T$300,"Not Assessed") -> 7 | L6: =COUNTIFS('Civil Eng'!$Z$5:$Z$300,"<"&TODAY(),'Civil Eng'!$Z$5:$Z$300,"<>") -> 0 | M6: =COUNTIF('Civil Eng'!$AB$5:$AB$300,"No - AI seeded") -> 7
A7: Structural Eng | B7: =COUNTA('Structural Eng'!$B$5:$B$300) -> 6 | C7: =COUNTIF('Structural Eng'!$P$5:$P$300,"Discovery") -> 6 | D7: =COUNTIF('Structural Eng'!$P$5:$P$300,"Prequalified") -> 0 | E7: =COUNTIF('Structural Eng'!$P$5:$P$300,"Qualified") -> 0 | F7: =COUNTIF('Structural Eng'!$P$5:$P$300,"AVL") -> 0 | G7: =COUNTIF('Structural Eng'!$P$5:$P$300,"On Hold") -> 0 | H7: =COUNTIF('Structural Eng'!$P$5:$P$300,"Disqualified") -> 0 | I7: =COUNTIF('Structural Eng'!$W$5:$W$300,"FEOC Review") -> 0 | J7: =COUNTIF('Structural Eng'!$W$5:$W$300,"High") -> 0 | K7: =COUNTIF('Structural Eng'!$T$5:$T$300,"Not Assessed") -> 6 | L7: =COUNTIFS('Structural Eng'!$Z$5:$Z$300,"<"&TODAY(),'Structural Eng'!$Z$5:$Z$300,"<>") -> 0 | M7: =COUNTIF('Structural Eng'!$AB$5:$AB$300,"No - AI seeded") -> 6
A8: Electrical Eng | B8: =COUNTA('Electrical Eng'!$B$5:$B$300) -> 8 | C8: =COUNTIF('Electrical Eng'!$P$5:$P$300,"Discovery") -> 8 | D8: =COUNTIF('Electrical Eng'!$P$5:$P$300,"Prequalified") -> 0 | E8: =COUNTIF('Electrical Eng'!$P$5:$P$300,"Qualified") -> 0 | F8: =COUNTIF('Electrical Eng'!$P$5:$P$300,"AVL") -> 0 | G8: =COUNTIF('Electrical Eng'!$P$5:$P$300,"On Hold") -> 0 | H8: =COUNTIF('Electrical Eng'!$P$5:$P$300,"Disqualified") -> 0 | I8: =COUNTIF('Electrical Eng'!$W$5:$W$300,"FEOC Review") -> 0 | J8: =COUNTIF('Electrical Eng'!$W$5:$W$300,"High") -> 0 | K8: =COUNTIF('Electrical Eng'!$T$5:$T$300,"Not Assessed") -> 8 | L8: =COUNTIFS('Electrical Eng'!$Z$5:$Z$300,"<"&TODAY(),'Electrical Eng'!$Z$5:$Z$300,"<>") -> 0 | M8: =COUNTIF('Electrical Eng'!$AB$5:$AB$300,"No - AI seeded") -> 8
A9: Fire Eng | B9: =COUNTA('Fire Eng'!$B$5:$B$300) -> 7 | C9: =COUNTIF('Fire Eng'!$P$5:$P$300,"Discovery") -> 7 | D9: =COUNTIF('Fire Eng'!$P$5:$P$300,"Prequalified") -> 0 | E9: =COUNTIF('Fire Eng'!$P$5:$P$300,"Qualified") -> 0 | F9: =COUNTIF('Fire Eng'!$P$5:$P$300,"AVL") -> 0 | G9: =COUNTIF('Fire Eng'!$P$5:$P$300,"On Hold") -> 0 | H9: =COUNTIF('Fire Eng'!$P$5:$P$300,"Disqualified") -> 0 | I9: =COUNTIF('Fire Eng'!$W$5:$W$300,"FEOC Review") -> 0 | J9: =COUNTIF('Fire Eng'!$W$5:$W$300,"High") -> 0 | K9: =COUNTIF('Fire Eng'!$T$5:$T$300,"Not Assessed") -> 7 | L9: =COUNTIFS('Fire Eng'!$Z$5:$Z$300,"<"&TODAY(),'Fire Eng'!$Z$5:$Z$300,"<>") -> 0 | M9: =COUNTIF('Fire Eng'!$AB$5:$AB$300,"No - AI seeded") -> 7
A10: Owners Eng | B10: =COUNTA('Owners Eng'!$B$5:$B$300) -> 7 | C10: =COUNTIF('Owners Eng'!$P$5:$P$300,"Discovery") -> 7 | D10: =COUNTIF('Owners Eng'!$P$5:$P$300,"Prequalified") -> 0 | E10: =COUNTIF('Owners Eng'!$P$5:$P$300,"Qualified") -> 0 | F10: =COUNTIF('Owners Eng'!$P$5:$P$300,"AVL") -> 0 | G10: =COUNTIF('Owners Eng'!$P$5:$P$300,"On Hold") -> 0 | H10: =COUNTIF('Owners Eng'!$P$5:$P$300,"Disqualified") -> 0 | I10: =COUNTIF('Owners Eng'!$W$5:$W$300,"FEOC Review") -> 0 | J10: =COUNTIF('Owners Eng'!$W$5:$W$300,"High") -> 0 | K10: =COUNTIF('Owners Eng'!$T$5:$T$300,"Not Assessed") -> 7 | L10: =COUNTIFS('Owners Eng'!$Z$5:$Z$300,"<"&TODAY(),'Owners Eng'!$Z$5:$Z$300,"<>") -> 0 | M10: =COUNTIF('Owners Eng'!$AB$5:$AB$300,"No - AI seeded") -> 7
A11: Eng of Record | B11: =COUNTA('Eng of Record'!$B$5:$B$300) -> 7 | C11: =COUNTIF('Eng of Record'!$P$5:$P$300,"Discovery") -> 7 | D11: =COUNTIF('Eng of Record'!$P$5:$P$300,"Prequalified") -> 0 | E11: =COUNTIF('Eng of Record'!$P$5:$P$300,"Qualified") -> 0 | F11: =COUNTIF('Eng of Record'!$P$5:$P$300,"AVL") -> 0 | G11: =COUNTIF('Eng of Record'!$P$5:$P$300,"On Hold") -> 0 | H11: =COUNTIF('Eng of Record'!$P$5:$P$300,"Disqualified") -> 0 | I11: =COUNTIF('Eng of Record'!$W$5:$W$300,"FEOC Review") -> 0 | J11: =COUNTIF('Eng of Record'!$W$5:$W$300,"High") -> 0 | K11: =COUNTIF('Eng of Record'!$T$5:$T$300,"Not Assessed") -> 7 | L11: =COUNTIFS('Eng of Record'!$Z$5:$Z$300,"<"&TODAY(),'Eng of Record'!$Z$5:$Z$300,"<>") -> 0 | M11: =COUNTIF('Eng of Record'!$AB$5:$AB$300,"No - AI seeded") -> 7
A12: Independent Eng | B12: =COUNTA('Independent Eng'!$B$5:$B$300) -> 6 | C12: =COUNTIF('Independent Eng'!$P$5:$P$300,"Discovery") -> 6 | D12: =COUNTIF('Independent Eng'!$P$5:$P$300,"Prequalified") -> 0 | E12: =COUNTIF('Independent Eng'!$P$5:$P$300,"Qualified") -> 0 | F12: =COUNTIF('Independent Eng'!$P$5:$P$300,"AVL") -> 0 | G12: =COUNTIF('Independent Eng'!$P$5:$P$300,"On Hold") -> 0 | H12: =COUNTIF('Independent Eng'!$P$5:$P$300,"Disqualified") -> 0 | I12: =COUNTIF('Independent Eng'!$W$5:$W$300,"FEOC Review") -> 0 | J12: =COUNTIF('Independent Eng'!$W$5:$W$300,"High") -> 0 | K12: =COUNTIF('Independent Eng'!$T$5:$T$300,"Not Assessed") -> 6 | L12: =COUNTIFS('Independent Eng'!$Z$5:$Z$300,"<"&TODAY(),'Independent Eng'!$Z$5:$Z$300,"<>") -> 0 | M12: =COUNTIF('Independent Eng'!$AB$5:$AB$300,"No - AI seeded") -> 6
A13: BESS Equipment | B13: =COUNTA('BESS Equipment'!$B$5:$B$300) -> 10 | C13: =COUNTIF('BESS Equipment'!$P$5:$P$300,"Discovery") -> 10 | D13: =COUNTIF('BESS Equipment'!$P$5:$P$300,"Prequalified") -> 0 | E13: =COUNTIF('BESS Equipment'!$P$5:$P$300,"Qualified") -> 0 | F13: =COUNTIF('BESS Equipment'!$P$5:$P$300,"AVL") -> 0 | G13: =COUNTIF('BESS Equipment'!$P$5:$P$300,"On Hold") -> 0 | H13: =COUNTIF('BESS Equipment'!$P$5:$P$300,"Disqualified") -> 0 | I13: =COUNTIF('BESS Equipment'!$W$5:$W$300,"FEOC Review") -> 9 | J13: =COUNTIF('BESS Equipment'!$W$5:$W$300,"High") -> 0 | K13: =COUNTIF('BESS Equipment'!$T$5:$T$300,"Not Assessed") -> 10 | L13: =COUNTIFS('BESS Equipment'!$Z$5:$Z$300,"<"&TODAY(),'BESS Equipment'!$Z$5:$Z$300,"<>") -> 0 | M13: =COUNTIF('BESS Equipment'!$AB$5:$AB$300,"No - AI seeded") -> 10
A14: MV Transformers | B14: =COUNTA('MV Transformers'!$B$5:$B$300) -> 10 | C14: =COUNTIF('MV Transformers'!$P$5:$P$300,"Discovery") -> 10 | D14: =COUNTIF('MV Transformers'!$P$5:$P$300,"Prequalified") -> 0 | E14: =COUNTIF('MV Transformers'!$P$5:$P$300,"Qualified") -> 0 | F14: =COUNTIF('MV Transformers'!$P$5:$P$300,"AVL") -> 0 | G14: =COUNTIF('MV Transformers'!$P$5:$P$300,"On Hold") -> 0 | H14: =COUNTIF('MV Transformers'!$P$5:$P$300,"Disqualified") -> 0 | I14: =COUNTIF('MV Transformers'!$W$5:$W$300,"FEOC Review") -> 0 | J14: =COUNTIF('MV Transformers'!$W$5:$W$300,"High") -> 0 | K14: =COUNTIF('MV Transformers'!$T$5:$T$300,"Not Assessed") -> 10 | L14: =COUNTIFS('MV Transformers'!$Z$5:$Z$300,"<"&TODAY(),'MV Transformers'!$Z$5:$Z$300,"<>") -> 0 | M14: =COUNTIF('MV Transformers'!$AB$5:$AB$300,"No - AI seeded") -> 10
A15: HV Breakers | B15: =COUNTA('HV Breakers'!$B$5:$B$300) -> 6 | C15: =COUNTIF('HV Breakers'!$P$5:$P$300,"Discovery") -> 6 | D15: =COUNTIF('HV Breakers'!$P$5:$P$300,"Prequalified") -> 0 | E15: =COUNTIF('HV Breakers'!$P$5:$P$300,"Qualified") -> 0 | F15: =COUNTIF('HV Breakers'!$P$5:$P$300,"AVL") -> 0 | G15: =COUNTIF('HV Breakers'!$P$5:$P$300,"On Hold") -> 0 | H15: =COUNTIF('HV Breakers'!$P$5:$P$300,"Disqualified") -> 0 | I15: =COUNTIF('HV Breakers'!$W$5:$W$300,"FEOC Review") -> 0 | J15: =COUNTIF('HV Breakers'!$W$5:$W$300,"High") -> 0 | K15: =COUNTIF('HV Breakers'!$T$5:$T$300,"Not Assessed") -> 6 | L15: =COUNTIFS('HV Breakers'!$Z$5:$Z$300,"<"&TODAY(),'HV Breakers'!$Z$5:$Z$300,"<>") -> 0 | M15: =COUNTIF('HV Breakers'!$AB$5:$AB$300,"No - AI seeded") -> 6
A16: MV Breakers | B16: =COUNTA('MV Breakers'!$B$5:$B$300) -> 7 | C16: =COUNTIF('MV Breakers'!$P$5:$P$300,"Discovery") -> 7 | D16: =COUNTIF('MV Breakers'!$P$5:$P$300,"Prequalified") -> 0 | E16: =COUNTIF('MV Breakers'!$P$5:$P$300,"Qualified") -> 0 | F16: =COUNTIF('MV Breakers'!$P$5:$P$300,"AVL") -> 0 | G16: =COUNTIF('MV Breakers'!$P$5:$P$300,"On Hold") -> 0 | H16: =COUNTIF('MV Breakers'!$P$5:$P$300,"Disqualified") -> 0 | I16: =COUNTIF('MV Breakers'!$W$5:$W$300,"FEOC Review") -> 0 | J16: =COUNTIF('MV Breakers'!$W$5:$W$300,"High") -> 0 | K16: =COUNTIF('MV Breakers'!$T$5:$T$300,"Not Assessed") -> 7 | L16: =COUNTIFS('MV Breakers'!$Z$5:$Z$300,"<"&TODAY(),'MV Breakers'!$Z$5:$Z$300,"<>") -> 0 | M16: =COUNTIF('MV Breakers'!$AB$5:$AB$300,"No - AI seeded") -> 7
A17: EPC | B17: =COUNTA(EPC!$B$5:$B$300) -> 8 | C17: =COUNTIF(EPC!$P$5:$P$300,"Discovery") -> 8 | D17: =COUNTIF(EPC!$P$5:$P$300,"Prequalified") -> 0 | E17: =COUNTIF(EPC!$P$5:$P$300,"Qualified") -> 0 | F17: =COUNTIF(EPC!$P$5:$P$300,"AVL") -> 0 | G17: =COUNTIF(EPC!$P$5:$P$300,"On Hold") -> 0 | H17: =COUNTIF(EPC!$P$5:$P$300,"Disqualified") -> 0 | I17: =COUNTIF(EPC!$W$5:$W$300,"FEOC Review") -> 0 | J17: =COUNTIF(EPC!$W$5:$W$300,"High") -> 0 | K17: =COUNTIF(EPC!$T$5:$T$300,"Not Assessed") -> 8 | L17: =COUNTIFS(EPC!$Z$5:$Z$300,"<"&TODAY(),EPC!$Z$5:$Z$300,"<>") -> 0 | M17: =COUNTIF(EPC!$AB$5:$AB$300,"No - AI seeded") -> 8
A18: Software | B18: =COUNTA(Software!$B$5:$B$300) -> 12 | C18: =COUNTIF(Software!$P$5:$P$300,"Discovery") -> 12 | D18: =COUNTIF(Software!$P$5:$P$300,"Prequalified") -> 0 | E18: =COUNTIF(Software!$P$5:$P$300,"Qualified") -> 0 | F18: =COUNTIF(Software!$P$5:$P$300,"AVL") -> 0 | G18: =COUNTIF(Software!$P$5:$P$300,"On Hold") -> 0 | H18: =COUNTIF(Software!$P$5:$P$300,"Disqualified") -> 0 | I18: =COUNTIF(Software!$W$5:$W$300,"FEOC Review") -> 0 | J18: =COUNTIF(Software!$W$5:$W$300,"High") -> 0 | K18: =COUNTIF(Software!$T$5:$T$300,"Not Assessed") -> 12 | L18: =COUNTIFS(Software!$Z$5:$Z$300,"<"&TODAY(),Software!$Z$5:$Z$300,"<>") -> 0 | M18: =COUNTIF(Software!$AB$5:$AB$300,"No - AI seeded") -> 12
A19: Total (vendor-tab entries) | B19: =SUM(B5:B18) -> 109 | C19: =SUM(C5:C18) -> 109 | D19: =SUM(D5:D18) -> 0 | E19: =SUM(E5:E18) -> 0 | F19: =SUM(F5:F18) -> 0 | G19: =SUM(G5:G18) -> 0 | H19: =SUM(H5:H18) -> 0 | I19: =SUM(I5:I18) -> 9 | ... M19: =SUM(M5:M18) -> 109
A20: Note: some firms appear on several tabs (e.g., Burns & McDonnell, Sargent & Lundy, DNV), so totals count tab entries, not unique companies.

Sheet Env Eng
A1: Environmental engineering consultants — Vendor Landscape
A2: Seeded 2026-10-05 from public sources (Discovery stage, unverified). Yellow columns = enter from vendor contact. Confirm all data before use; see Read Me.
A3: Vendor | D3: HQ Location | I3: Contact Information | P3: Qualification | S3: Financial Strength / Bankability | V3: Supply Chain / Origin Risk | X3: Tracking
A4: Vendor ID | B4: Vendor Name | C4: Environmental Services | D4: HQ City | E4: HQ State / Prov | F4: HQ Country | G4: US HQ (if foreign) | H4: Texas Presence | I4: Website | J4: Main Phone | K4: Contact Page | L4: Primary Contact Name | M4: Contact Title | N4: Contact Email | O4: Contact Phone | P4: Qualification Status | Q4: Status Date | R4: Last RFx Stage | S4: Ownership / Parent | T4: Financial Strength | U4: Financial / Bankability Notes | V4: Staff / Delivery Origin | W4: Supply Chain Risk | X4: Last Contact Date | Y4: Next Action | Z4: Next Action Due | AA4: Notes | AB4: Data Verified? | AC4: Primary Source
A5: ENV-001 | B5: ERM (Environmental Resources Management) | C5: Environmental, health, safety, risk and social consulting; permitting/impact assessment and sustainability services for energy projects | D5: London | F5: United Kingdom | I5: https://www.erm.com/ | K5: https://www.erm.com/contact-us/ | P5: Discovery | Q5: 46300 | R5: None | S5: PE-backed: KKR majority stake (acquired May 2021, ~US$2.7B valuation); ERM partners hold minority | T5: Not Assessed | U5: ~8,000 employees, 140+ offices in 40+ countries; revenue US$1.32B (2023); June 2024 agreed to acquire energy-transition advisory Energetics | V5: Global firm; US offices exist but Texas office locations not confirmed (locations page blocked) | W5: Not Assessed | AB5: No - AI seeded | AC5: https://en.wikipedia.org/wiki/ERM_(consultancy)
A6: ENV-002 | B6: Tetra Tech, Inc. | C6: Environmental consulting and engineering (water, environment, energy); permitting, site assessment, natural/cultural resources | D6: Pasadena | E6: CA | F6: USA | I6: https://www.tetratech.com/ | J6: +1 (626) 351-4664 | K6: https://www.tetratech.com/contact/ | P6: Discovery | Q6: 46300 | R6: None | S6: Public (NASDAQ: TTEK) | T6: Not Assessed | U6: ~28,000 employees (Oct 2024); 550 locations globally; acquired LS Technologies (Feb 2024) and Convergence Controls & Engineering (May 2024) | V6: US-based; site states offices in every US state (Texas cities not listed on fetched pages) | W6: Not Assessed | AB6: No - AI seeded | AC6: https://www.tetratech.com/contact/
A7: ENV-003 | B7: Stantec Inc. | C7: Environmental consulting and engineering; environmental permitting and studies for energy/infrastructure projects | D7: Edmonton | E7: AB | F7: Canada | H7: Austin; Dallas; Houston; San Antonio | I7: https://www.stantec.com/en | P7: Discovery | Q7: 46300 | R7: None | S7: Public (TSX/NYSE: STN) | T7: Not Assessed | U7: ~30,000 employees (2024); acquired Page (architecture, Aug 2025) | V7: Texas offices confirmed via stantec.com office pages (Houston 1100 Louisiana St; Barkers Landing; Dallas Main St; Austin Aldrich St/6th St; San Antonio) | W7: Not Assessed | AB7: No - AI seeded | AC7: https://en.wikipedia.org/wiki/Stantec
A8: ENV-004 | B8: WSP Global Inc. (WSP USA) | C8: Environmental, engineering and permitting consulting; power & energy platform (incl. POWER Engineers and TRC) | D8: Montreal | E8: QC | F8: Canada | H8: Austin; Corpus Christi; Dallas; El Paso; Fort Worth; Houston; San Antonio; Spring; Tyler; Victoria | I8: https://www.wsp.com/en-us | K8: https://www.wsp.com/en-us/contact-us | P8: Discovery | Q8: 46300 | R8: None | S8: Public (TSX: WSP) | T8: Not Assessed | U8: ~83,000 employees (Feb 2026); revenue C$16.17B (2024); acquired POWER Engineers (closed Oct 1 2024, US$1.78B), Ricardo (Jun 2025), TRC (closed Feb 24 2026, ~$3.3B); abandoned Arcadis bid Sep 2026 | V8: US operations led from New York (One Penn Plaza) per office listing | W8: Not Assessed | AB8: No - AI seeded | AC8: https://en.wikipedia.org/wiki/WSP_Global
A9: ENV-005 | B9: Terracon Consultants, Inc. | C9: Environmental site assessment (Phase I/II ESA), geotechnical, materials testing and facilities consulting | D9: Olathe | E9: KS | F9: USA | H9: Austin; Houston; San Antonio; Frisco; DFW Metro | I9: https://www.terracon.com/ | J9: (800) 593-7777 | K9: https://www.terracon.com/contact/ | P9: Discovery | Q9: 46300 | R9: None | S9: Private, 100% employee-owned | T9: Not Assessed | U9: 6,000+ employees, 200+ locations; ENR Top 500 Design Firms #18 (2024); founded 1965 | V9: US-based staff; national office network | W9: Not Assessed | AB9: No - AI seeded | AC9: https://www.terracon.com/contact/
A10: ENV-006 | B10: SWCA Environmental Consultants | C10: Environmental planning/permitting, natural & cultural resources, renewable energy environmental services | D10: Phoenix | E10: AZ | F10: USA | H10: Arlington; Austin; Houston; San Antonio | I10: https://www.swca.com/ | J10: 602-274-3831 | K10: https://www.swca.com/contact/ | P10: Discovery | Q10: 46300 | R10: None | S10: Private, 100% employee-owned (ESOP since 2000) | T10: Not Assessed | U10: 1,700+ employees, 46 US offices; ENR Top 500 Design Firms #93 (2026); founded 1980 in Flagstaff | V10: US-based staff; Phoenix office is corporate HQ and focuses on renewable energy, environmental planning, cultural resources | W10: Not Assessed | AB10: No - AI seeded | AC10: https://www.swca.com/contact
A11: ENV-007 | B11: Westwood Professional Services | C11: Renewable/BESS development support incl. environmental permitting, survey, and design of standalone and hybrid battery storage | D11: Plano | E11: TX | F11: USA | H11: Plano (HQ); Austin; Celina; Dallas; Farmers Branch; Fort Worth; Frisco; Houston; San Antonio; Victoria | I11: https://westwoodps.com/ | J11: 214-473-4640 (HQ); 1-888-937-5150 (toll-free) | K11: https://westwoodps.com/contact-us | P11: Discovery | Q11: 46300 | R11: None | S11: PE-backed: Blackstone (Energy Transition Partners) majority since Aug 2024; management/employees retain minority (prior owner Endurance Partners) | T11: Not Assessed | U11: 1,600+ employees (2024); HQ relocated from Minneapolis to Plano, TX late 2023; founded 1971 | V11: US-based staff; strong Texas presence | W11: Not Assessed | AB11: No - AI seeded | AC11: https://westwoodps.com/about-us/offices
A12: ENV-008 | B12: HDR, Inc. | C12: Engineering, environmental and architecture consulting incl. environmental planning for infrastructure/energy | D12: Omaha | E12: NE | F12: USA | H12: Austin; Dallas; Houston; San Antonio; El Paso; Spring Branch | I12: https://www.hdrinc.com/ | J12: (402) 399-1000 | K12: https://www.hdrinc.com/contact-us | P12: Discovery | Q12: 46300 | R12: None | S12: Private, employee-owned | T12: Not Assessed | U12: 12,000+ employees; revenue $2.8B (2022); ENR #6 design firm (2023) | V12: US-based staff | W12: Not Assessed | AB12: No - AI seeded | AC12: https://www.hdrinc.com/contact-us

Sheet Civil Eng
A1: Civil engineering consultants — Vendor Landscape
A2: Seeded 2026-10-05 from public sources (Discovery stage, unverified). Yellow columns = enter from vendor contact. Confirm all data before use; see Read Me.
A3: Vendor | D3: HQ Location | I3: Contact Information | P3: Qualification | S3: Financial Strength / Bankability | V3: Supply Chain / Origin Risk | X3: Tracking
A4: Vendor ID | B4: Vendor Name | C4: Civil Services | D4: HQ City | E4: HQ State / Prov | F4: HQ Country | G4: US HQ (if foreign) | H4: Texas Presence | I4: Website | J4: Main Phone | K4: Contact Page | L4: Primary Contact Name | M4: Contact Title | N4: Contact Email | O4: Contact Phone | P4: Qualification Status | Q4: Status Date | R4: Last RFx Stage | S4: Ownership / Parent | T4: Financial Strength | U4: Financial / Bankability Notes | V4: Staff / Delivery Origin | W4: Supply Chain Risk | X4: Last Contact Date | Y4: Next Action | Z4: Next Action Due | AA4: Notes | AB4: Data Verified? | AC4: Primary Source
A5: CIV-001 | B5: Kimley-Horn and Associates, Inc. | C5: Site civil, grading/drainage, roads and planning/design; energy and infrastructure site development | D5: Raleigh | E5: NC | F5: USA | H5: Austin; Bryan/College Station; Celina; Childress; Dallas; Denton; Fort Worth; Frisco; Georgetown; Houston; Irving; Lubbock; McKinney; Pearland; Richardson; San Antonio; San Marcos; Sherman; Terrell; The Woodlands; Tyler; Weatherford | I5: https://www.kimley-horn.com/ | K5: https://www.kimley-horn.com/contact/ | P5: Discovery | Q5: 46300 | R5: None | S5: Private | T5: Not Assessed | U5: 11,000+ employees (2026); revenue $2.8B (2025); ENR Top 500 Design Firms #8 (2025) | V5: US-based staff; 170+ US locations | W5: Not Assessed | AB5: No - AI seeded | AC5: https://en.wikipedia.org/wiki/Kimley-Horn
A6: CIV-002 | B6: Westwood Professional Services | C6: Civil/site design, survey, and permitting for utility-scale solar, wind and BESS; power delivery | D6: Plano | E6: TX | F6: USA | H6: Plano (HQ); Austin; Celina; Dallas; Farmers Branch; Fort Worth; Frisco; Houston; San Antonio; Victoria | I6: https://westwoodps.com/ | J6: 214-473-4640 (HQ); 1-888-937-5150 (toll-free) | K6: https://westwoodps.com/contact-us | P6: Discovery | Q6: 46300 | R6: None | S6: PE-backed: Blackstone majority since Aug 2024 | T6: Not Assessed | U6: 1,600+ employees (2024); HQ moved to Plano, TX late 2023 | V6: US-based staff | W6: Not Assessed | AB6: No - AI seeded | AC6: https://westwoodps.com/about-us/offices
A7: CIV-003 | B7: Halff Associates, Inc. | C7: Infrastructure consulting: site civil, drainage/water resources, survey, transportation | D7: Richardson | E7: TX | F7: USA | H7: Richardson (HQ); Austin; Brownsville; Corpus Christi; Dallas; Fort Worth; Frisco; Houston; Lubbock; McAllen; Midland; San Antonio; The Woodlands; Tyler | I7: https://www.halff.com/ | K7: https://www.halff.com/contact/ | P7: Discovery | Q7: 46300 | R7: None | S7: Private, employee-owned | T7: Not Assessed | U7: 30+ offices in AR, FL, LA, OK, TX; Nov 2024 announced HQ move to 2380 Performance Dr, Richardson (80,000 sf); founded ~1950 | V7: US-based staff; Texas-headquartered | W7: Not Assessed | AB7: No - AI seeded | AC7: https://www.halff.com/contact/
A8: CIV-004 | B8: Pape-Dawson Engineers | C8: Civil engineering, survey, permitting; substation/switchyard civil design (170+ substations) and wind/solar civil | D8: San Antonio | E8: TX | F8: USA | H8: San Antonio (HQ); Amarillo; Austin; Corpus Christi; Dallas; Fort Worth; Houston; Longview; Lufkin; McKinney; Nacogdoches; New Braunfels; The Woodlands; Tyler | I8: https://www.pape-dawson.com/ | J8: 210-375-9000 | K8: https://www.pape-dawson.com/contact | P8: Discovery | Q8: 46300 | R8: None | S8: Private; Dawson family/management majority with growth capital from Palm Beach Capital (Apr 2023) | T8: Not Assessed | U8: Serial acquirer (e.g., BHC, KSA Engineers, Poulos & Bennett, GradyMinor); offices in TX, FL, GA, TN, KS, OK, LA, AL, AZ, KY | V8: US-based staff; Texas-headquartered | W8: Not Assessed | AB8: No - AI seeded | AC8: https://www.pape-dawson.com/contact
A9: CIV-005 | B9: Bowman Consulting Group Ltd. | C9: Infrastructure design, civil engineering, survey, environmental; energy design incl. battery storage | D9: Reston | E9: VA | F9: USA | H9: Austin; Arlington; Dallas (Plano); Houston; Marshall; Midland; San Antonio; San Marcos; Waco | I9: https://bowman.com/ | J9: (703) 464-1000 | K9: https://bowman.com/contact | P9: Discovery | Q9: 46300 | R9: None | S9: Public (NASDAQ: BWMN) - pending take-private by Bernhard Capital Partners | T9: Not Assessed | U9: 2,500+ employees; Aug 10 2026 agreed to be acquired by Bernhard Capital Partners at $43.00/sh (~$1.0B EV), expected close Q4 2026/Q1 2027; 42 acquisitions since 2021 IPO | V9: US-based staff; offices in 34+ states | W9: Not Assessed | AB9: No - AI seeded | AC9: https://investors.bowman.com/
A10: CIV-006 | B10: Terracon Consultants, Inc. | C10: Geotechnical engineering, materials testing and construction QA for site/foundation design | D10: Olathe | E10: KS | F10: USA | H10: Austin; Houston; San Antonio; Frisco; DFW Metro | I10: https://www.terracon.com/ | J10: (800) 593-7777 | K10: https://www.terracon.com/contact/ | P10: Discovery | Q10: 46300 | R10: None | S10: Private, 100% employee-owned | T10: Not Assessed | U10: 6,000+ employees, 200+ locations; ENR #18 (2024) | V10: US-based staff | W10: Not Assessed | AB10: No - AI seeded | AC10: https://www.terracon.com/contact/
A11: CIV-007 | B11: Burns & McDonnell | C11: Engineering/EPC incl. site civil for power generation, substations and transmission | D11: Kansas City | E11: MO | F11: USA | H11: Amarillo; Austin; Dallas-Fort Worth; Houston; Pearland; San Antonio | I11: https://www.burnsmcd.com/ | K11: https://info.burnsmcd.com/contact-us | P11: Discovery | Q11: 46300 | R11: None | S11: Private, 100% employee-owned (ESOP) | T11: Not Assessed | U11: 13,500+ employees (2023); revenue US$6.9B (2023); ENR Top 500 #7; 75+ offices | V11: US-based staff; Houston office 1700 West Loop South | W11: Not Assessed | AB11: No - AI seeded | AC11: https://en.wikipedia.org/wiki/Burns_%26_McDonnell

Sheet Structural Eng
A1: Structural engineering consultants — Vendor Landscape
A2: Seeded 2026-10-05 from public sources (Discovery stage, unverified). Yellow columns = enter from vendor contact. Confirm all data before use; see Read Me.
A3: Vendor | D3: HQ Location | I3: Contact Information | P3: Qualification | S3: Financial Strength / Bankability | V3: Supply Chain / Origin Risk | X3: Tracking
A4: Vendor ID | B4: Vendor Name | C4: Structural Services | D4: HQ City | E4: HQ State / Prov | F4: HQ Country | G4: US HQ (if foreign) | H4: Texas Presence | I4: Website | J4: Main Phone | K4: Contact Page | L4: Primary Contact Name | M4: Contact Title | N4: Contact Email | O4: Contact Phone | P4: Qualification Status | Q4: Status Date | R4: Last RFx Stage | S4: Ownership / Parent | T4: Financial Strength | U4: Financial / Bankability Notes | V4: Staff / Delivery Origin | W4: Supply Chain Risk | X4: Last Contact Date | Y4: Next Action | Z4: Next Action Due | AA4: Notes | AB4: Data Verified? | AC4: Primary Source
A5: STR-001 | B5: Walter P Moore | C5: Structural and civil engineering, foundations, forensic engineering | D5: Houston | E5: TX | F5: USA | H5: Houston (HQ); Austin; Dallas; El Paso; Fort Worth; The Woodlands | I5: https://www.walterpmoore.com/ | J5: 800-364-7300 (general); 713-630-7300 (Houston HQ) | K5: https://www.walterpmoore.com/contact | P5: Discovery | Q5: 46300 | R5: None | S5: Private | T5: Not Assessed | U5: 1,250+ staff, 36 offices in 6 countries; founded 1931 | V5: US-based staff; Texas-headquartered; India office exists | W5: Not Assessed | AB5: No - AI seeded | AC5: https://www.walterpmoore.com/about
A6: STR-002 | B6: Sargent & Lundy | C6: Power engineering incl. structural design for generation, BESS, substations and transmission structures | D6: Chicago | E6: IL | F6: USA | H6: Houston | I6: https://www.sargentlundy.com/ | J6: (312) 269-2000 | K6: https://www.sargentlundy.com/contact-us | P6: Discovery | Q6: 46300 | R6: None | S6: Private, engineer-owned | T6: Not Assessed | U6: ~2,000+ employees; 30-40+ offices; founded 1891 | V6: US-based staff; international offices incl. India, UAE, Saudi Arabia, South Korea | W6: Not Assessed | AB6: No - AI seeded | AC6: https://www.sargentlundy.com/contact-us
A7: STR-003 | B7: Burns & McDonnell | C7: Structural/civil design for substations, equipment foundations and power plants (engineering/EPC) | D7: Kansas City | E7: MO | F7: USA | H7: Amarillo; Austin; Dallas-Fort Worth; Houston; Pearland; San Antonio | I7: https://www.burnsmcd.com/ | K7: https://info.burnsmcd.com/contact-us | P7: Discovery | Q7: 46300 | R7: None | S7: Private, 100% employee-owned (ESOP) | T7: Not Assessed | U7: 13,500+ employees (2023); revenue US$6.9B (2023); ENR #7 | V7: US-based staff | W7: Not Assessed | AB7: No - AI seeded | AC7: https://en.wikipedia.org/wiki/Burns_%26_McDonnell
A8: STR-004 | B8: Black & Veatch | C8: Engineering/EPC for power generation, power delivery and substations incl. structural design | D8: Overland Park | E8: KS | F8: USA | H8: Houston | I8: https://www.bv.com/ | J8: +1 913-458-2000 | K8: https://www.bv.com/contact-us | P8: Discovery | Q8: 46300 | R8: None | S8: Private, employee-owned | T8: Not Assessed | U8: ~13,000 employees (2024); revenue $4.735B (2023); 100+ offices; acquired Bird Electric Enterprises (2023) | V8: US-based staff with global offices | W8: Not Assessed | AB8: No - AI seeded | AC8: https://www.bv.com/contact-us
A9: STR-005 | B9: POWER Engineers (a WSP company) | C9: Power delivery engineering incl. substation and transmission structural/civil design; renewables & storage | D9: Hailey | E9: ID | F9: USA | H9: Houston; Tyler | I9: https://www.powereng.com/ | P9: Discovery | Q9: 46300 | R9: None | S9: Subsidiary of WSP Global (TSX: WSP); acquisition closed Oct 1 2024 (US$1.78B); previously employee-owned | T9: Not Assessed | U9: ~4,000 employees, 50 North American offices at acquisition; founded 1976 | V9: US-based staff; powereng.com not fetchable (robots), Texas offices from powereng.com press release titles | W9: Not Assessed | AB9: No - AI seeded | AC9: https://www.wsp.com/en-us/news/2024/wsp-completes-acquisition-of-power-engineers
A10: STR-006 | B10: Electrical Consultants, Inc. (ECI) | C10: Power delivery only: civil, structural, electrical, survey for substations, transmission (to 765 kV), renewables and battery storage | D10: Billings | E10: MT | F10: USA | I10: https://eciusa.com/ | P10: Discovery | Q10: 46300 | R10: None | T10: Not Assessed | U10: 900+ professionals, 33+ offices (per FL Public Power assn listing); acquired Relay Application Innovation (2019); subsidiary EPC Services Company (design-build) | V10: US-based staff; company website not fetchable (SSL error) - phone/contact not verified on official page | W10: Not Assessed | AB10: No - AI seeded | AC10: https://www.flpublicpower.com/associate-membership/electrical-consultants-inc

Sheet Electrical Eng
A1: Electrical engineering consultants — Vendor Landscape
A2: Seeded 2026-10-05 from public sources (Discovery stage, unverified). Yellow columns = enter from vendor contact. Confirm all data before use; see Read Me.
A3: Vendor | D3: HQ Location | I3: Contact Information | P3: Qualification | S3: Financial Strength / Bankability | V3: Supply Chain / Origin Risk | X3: Tracking
A4: Vendor ID | B4: Vendor Name | C4: Electrical Services | D4: HQ City | E4: HQ State / Prov | F4: HQ Country | G4: US HQ (if foreign) | H4: Texas Presence | I4: Website | J4: Main Phone | K4: Contact Page | L4: Primary Contact Name | M4: Contact Title | N4: Contact Email | O4: Contact Phone | P4: Qualification Status | Q4: Status Date | R4: Last RFx Stage | S4: Ownership / Parent | T4: Financial Strength | U4: Financial / Bankability Notes | V4: Staff / Delivery Origin | W4: Supply Chain Risk | X4: Last Contact Date | Y4: Next Action | Z4: Next Action Due | AA4: Notes | AB4: Data Verified? | AC4: Primary Source
A5: ELE-001 | B5: POWER Engineers (a WSP company) | C5: Substation, transmission and interconnection engineering; renewables & storage power delivery | D5: Hailey | E5: ID | F5: USA | H5: Houston; Tyler | I5: https://www.powereng.com/ | P5: Discovery | Q5: 46300 | R5: None | S5: Subsidiary of WSP Global (TSX: WSP) since Oct 1 2024 | T5: Not Assessed | U5: ~4,000 employees, 50 offices at acquisition (US$1.78B); WSP also closed TRC acquisition Feb 2026 | V5: US-based staff | W5: Not Assessed | AB5: No - AI seeded | AC5: https://www.wsp.com/en-us/news/2024/wsp-completes-acquisition-of-power-engineers
A6: ELE-002 | B6: Burns & McDonnell | C6: Substation/transmission design and EPC, interconnection and power generation electrical engineering | D6: Kansas City | E6: MO | F6: USA | H6: Amarillo; Austin; Dallas-Fort Worth; Houston; Pearland; San Antonio | I6: https://www.burnsmcd.com/ | K6: https://info.burnsmcd.com/contact-us | P6: Discovery | Q6: 46300 | R6: None | S6: Private, 100% employee-owned (ESOP) | T6: Not Assessed | U6: 13,500+ employees (2023); revenue US$6.9B (2023); ENR #7; selected by CPS Energy for turnkey grid modernization program | V6: US-based staff | W6: Not Assessed | AB6: No - AI seeded | AC6: https://en.wikipedia.org/wiki/Burns_%26_McDonnell
A7: ELE-003 | B7: Sargent & Lundy | C7: Grid/substation/transmission engineering, renewables and BESS electrical design, owner's engineer/due diligence | D7: Chicago | E7: IL | F7: USA | H7: Houston | I7: https://www.sargentlundy.com/ | J7: (312) 269-2000 | K7: https://www.sargentlundy.com/contact-us | P7: Discovery | Q7: 46300 | R7: None | S7: Private, engineer-owned | T7: Not Assessed | U7: ~2,000+ employees; founded 1891 | V7: US-based staff; international offices incl. India | W7: Not Assessed | AB7: No - AI seeded | AC7: https://www.sargentlundy.com/contact-us
A8: ELE-004 | B8: Black & Veatch | C8: Power delivery (substation/transmission) engineering and EPC; generation and storage | D8: Overland Park | E8: KS | F8: USA | H8: Houston | I8: https://www.bv.com/ | J8: +1 913-458-2000 | K8: https://www.bv.com/contact-us | P8: Discovery | Q8: 46300 | R8: None | S8: Private, employee-owned | T8: Not Assessed | U8: ~13,000 employees (2024); revenue $4.735B (2023) | V8: US-based staff with global offices | W8: Not Assessed | AB8: No - AI seeded | AC8: https://www.bv.com/contact-us
A9: ELE-005 | B9: Electric Power Engineers, LLC (EPE) | C9: Grid analysis/interconnection studies, utility engineering, regulatory/compliance; renewables & storage | D9: Austin | E9: TX | F9: USA | H9: Austin (HQ) | I9: https://epeconsulting.com/ | J9: 512-382-6700 | K9: https://epeconsulting.com/contact | P9: Discovery | Q9: 46300 | R9: None | S9: PE-backed: Berkshire Partners strategic growth investment (Jan 7 2025); Lime Rock New Energy exited; CEO/COO remain significant investors | T9: Not Assessed | U9: Founded 1968; 100+ developer/generation/utility clients | V9: US HQ Austin; other offices in Champaign IL, Waterloo ON, Beirut (Lebanon), Panama City | W9: Not Assessed | AB9: No - AI seeded | AC9: https://epeconsulting.com/contact
A10: ELE-006 | B10: TRC Companies, Inc. (a member of WSP) | C10: Power & utilities engineering incl. substation, transmission and interconnection; environmental | D10: Windsor | E10: CT | F10: USA | H10: Houston | I10: https://www.trccompanies.com/ | J10: +1 (860) 298-9692 | K10: https://www.trccompanies.com/contact-us/ | P10: Discovery | Q10: 46300 | R10: None | S10: Subsidiary of WSP Global (TSX: WSP); acquisition closed Feb 24 2026 | T10: Not Assessed | U10: ~8,000 professionals; ENR Top 500 #17; deal ~$3.3B per Wikipedia | V10: US-based staff | W10: Not Assessed | AB10: No - AI seeded | AC10: https://www.trccompanies.com/contact-us/
A11: ELE-007 | B11: Leidos (Power Delivery / Energy) | C11: Substation design (4-765 kV), T&D lines, SCADA, system planning, NERC compliance for Texas utilities | D11: Reston | E11: VA | F11: USA | H11: Houston; Fort Worth (per Leidos careers postings); site cites design centers across Texas | I11: https://www.leidos.com/ | K11: https://www.leidos.com/contact-us | P11: Discovery | Q11: 46300 | R11: None | S11: Public (NYSE: LDOS) | T11: Not Assessed | U11: ~47,000 employees (2026); revenue $17.2B (2025); Jan 2026 agreed to acquire Entrust Solutions Group (utility engineering) for ~$2.4B; ENR #4 T&D design (2022) | V11: US-based staff | W11: Not Assessed | AB11: No - AI seeded | AC11: https://www.leidos.com/markets/energy/texas
A12: ELE-008 | B12: Electrical Consultants, Inc. (ECI) | C12: Power delivery engineering: substations, transmission to 765 kV, protection & control, renewables/BESS | D12: Billings | E12: MT | F12: USA | I12: https://eciusa.com/ | P12: Discovery | Q12: 46300 | R12: None | T12: Not Assessed | U12: 900+ professionals, 33+ offices (FL Public Power assn listing); acquired Relay Application Innovation (2019) | V12: US-based staff; official site not reachable for verification | W12: Not Assessed | AB12: No - AI seeded | AC12: https://www.flpublicpower.com/associate-membership/electrical-consultants-inc

Sheet Fire Eng
A1: Fire protection engineering consultants — Vendor Landscape
A2: Seeded 2026-10-05 from public sources (Discovery stage, unverified). Yellow columns = enter from vendor contact. Confirm all data before use; see Read Me.
A3: Vendor | D3: HQ Location | I3: Contact Information | P3: Qualification | S3: Financial Strength / Bankability | V3: Supply Chain / Origin Risk | X3: Tracking
A4: Vendor ID | B4: Vendor Name | C4: Fire / BESS Hazard Services | D4: HQ City | E4: HQ State / Prov | F4: HQ Country | G4: US HQ (if foreign) | H4: Texas Presence | I4: Website | J4: Main Phone | K4: Contact Page | L4: Primary Contact Name | M4: Contact Title | N4: Contact Email | O4: Contact Phone | P4: Qualification Status | Q4: Status Date | R4: Last RFx Stage | S4: Ownership / Parent | T4: Financial Strength | U4: Financial / Bankability Notes | V4: Staff / Delivery Origin | W4: Supply Chain Risk | X4: Last Contact Date | Y4: Next Action | Z4: Next Action Due | AA4: Notes | AB4: Data Verified? | AC4: Primary Source
A5: FIRE-001 | B5: Jensen Hughes | C5: Lithium-ion/BESS risk consulting: hazard mitigation, NFPA 855/UL 9540A expertise, explosion protection (CFD, deflagration venting), large-scale fire testing | D5: Columbia | E5: MD | F5: USA | I5: https://www.jensenhughes.com/ | K5: https://www.jensenhughes.com/contact-us | P5: Discovery | Q5: 46300 | R5: None | S5: PE-backed: Gryphon Investors; Aug 5 2026 definitive agreement for New Mountain Capital to acquire (close expected Q4 2026) | T5: Not Assessed | U5: ~2,000 employees, 110 offices; founded 1939 | V5: Global firm; Texas office not confirmed | W5: Not Assessed | AB5: No - AI seeded | AC5: https://www.jensenhughes.com/contact-us
A6: FIRE-002 | B6: ESRG (Energy Safety Response Group) | C6: Energy-storage-only safety: testing, permitting/project review, emergency response plans & first-responder training, incident response | I6: https://www.energyresponsegroup.com/ | J6: 1-833-SAFE-ESS | K6: https://www.energyresponsegroup.com/contact | P6: Discovery | Q6: 46300 | R6: None | T6: Not Assessed | V6: Team of fire-service veterans; HQ not stated on site | W6: Not Assessed | AB6: No - AI seeded | AC6: https://energyresponsegroup.com/
A7: FIRE-003 | B7: Fire & Risk Alliance | C7: BESS code consulting (NFPA 855/IFC), HMA, UL 9540A assessment, deflagration (NFPA 68/69) and heat-flux modeling, FMEA, ERP and responder training | D7: Rockville | E7: MD | F7: USA | I7: https://fireriskalliance.com/ | J7: (301) 658-3060 | K7: https://fireriskalliance.com/contact-us/ | P7: Discovery | Q7: 46300 | R7: None | T7: Not Assessed | V7: Single listed office (Rockville, MD); 24/7 availability | W7: Not Assessed | AB7: No - AI seeded | AC7: https://fireriskalliance.com/
A8: FIRE-004 | B8: Telgian Engineering & Consulting | C8: Fire protection engineering and code consulting; has published ESS fire-hazard guidance (BESS-specific services not detailed on site) | D8: Phoenix | E8: AZ | F8: USA | H8: Richardson (Dallas office) | I8: https://www.telgian.com/ | J8: 480.753.5444 | K8: https://www.telgian.com/contact/ | P8: Discovery | Q8: 46300 | R8: None | S8: Private (Telgian Holdings, Inc.) | T8: Not Assessed | V8: US-based staff; offices in Atlanta, Chicago, Dallas, Denver, Irvine, Phoenix, Seattle, Wilmington DE, plus Toronto and Mexico City | W8: Not Assessed | AB8: No - AI seeded | AC8: https://www.telgian.com/contact/
A9: FIRE-005 | B9: DNV | C9: Battery safety, risk analysis (QRA) and permitting support; energy storage technical due diligence and engineering review | D9: Høvik (Oslo) | F9: Norway | H9: Houston (North American HQ) | I9: https://www.dnv.com/ | K9: https://www.dnv.us/contact/ | P9: Discovery | Q9: 46300 | R9: None | S9: Owned by the independent Det Norske Veritas Foundation | T9: Not Assessed | U9: ~15,000 employees (2024); revenue NOK 31.6B (2023); 1,500+ US employees | V9: Global firm; North American HQ Houston, TX | W9: Not Assessed | AB9: No - AI seeded | AC9: https://en.wikipedia.org/wiki/DNV
A10: FIRE-006 | B10: UL Solutions Inc. | C10: UL 9540A testing, NFPA 855 documentation readiness review, fire/explosion hazard assessment, AHJ-focused technical support | D10: Northbrook | E10: IL | F10: USA | H10: Houston; Plano; Rollingwood (Austin area) | I10: https://www.ul.com/ | J10: +1.877.854.3577 (customer service) | K10: https://www.ul.com/contact-us | P10: Discovery | Q10: 46300 | R10: None | S10: Public (NYSE: ULS), IPO April 16 2024 | T10: Not Assessed | U10: IPO ~US$1.08B (Apr 2024); serves 80,000+ companies | V10: US-based labs incl. Plano, TX | W10: Not Assessed | AB10: No - AI seeded | AC10: https://www.ul.com/services/ess-safety-assessment-and-nfpa-compliance
A11: FIRE-007 | B11: Exponent, Inc. | C11: BESS safety & risk consulting: fire protection engineering, emergency response planning, root-cause failure analysis, testing | D11: Menlo Park | E11: CA | F11: USA | H11: Houston | I11: https://www.exponent.com/ | J11: (650) 326-9400 | P11: Discovery | Q11: 46300 | R11: None | S11: Public (NASDAQ: EXPO) | T11: Not Assessed | U11: 20 US offices + 5 overseas; founded 1967 as Failure Analysis Associates | V11: US-based staff; Menlo Park HQ has on-site labs | W11: Not Assessed | AB11: No - AI seeded | AC11: https://www.exponent.com/offices/menlo-park

Sheet Owners Eng
A1: Owner's engineer — Vendor Landscape
A2: Seeded 2026-10-05 from public sources (Discovery stage, unverified). Yellow columns = enter from vendor contact. Confirm all data before use; see Read Me.
A3: Vendor | D3: HQ Location | I3: Contact Information | P3: Qualification | S3: Financial Strength / Bankability | V3: Supply Chain / Origin Risk | X3: Tracking
A4: Vendor ID | B4: Vendor Name | C4: OE Services | D4: HQ City | E4: HQ State / Prov | F4: HQ Country | G4: US HQ (if foreign) | H4: Texas Presence | I4: Website | J4: Main Phone | K4: Contact Page | L4: Primary Contact Name | M4: Contact Title | N4: Contact Email | O4: Contact Phone | P4: Qualification Status | Q4: Status Date | R4: Last RFx Stage | S4: Ownership / Parent | T4: Financial Strength | U4: Financial / Bankability Notes | V4: Staff / Delivery Origin | W4: Supply Chain Risk | X4: Last Contact Date | Y4: Next Action | Z4: Next Action Due | AA4: Notes | AB4: Data Verified? | AC4: Primary Source
A5: OE-001 | B5: DNV | C5: Owner's engineering for energy storage: feasibility, dispatch modeling, RFP/tender support, design and procurement review, grid connection, warranty definition, FAT/SAT, construction PM, HSE | D5: Høvik | F5: Norway | H5: Houston (North America HQ); Austin; Dallas (per DNV job postings) | I5: https://www.dnv.com | J5: +1 281 396 1000 (DNV North America HQ, Houston) | K5: https://www.dnv.us/contact/ | P5: Discovery | Q5: 46300 | R5: None | S5: Private; owned by the independent foundation Stiftelsen Det Norske Veritas | T5: Not Assessed | U5: 2025 operating revenue NOK 35,291 million (+0.9% y/y); operates in 100+ countries | V5: US energy-storage OE/IE staff posted in Houston, Austin, Dallas, plus Oakland, San Diego, Seattle, Portland, Medford MA, Chalfont PA, New York | W5: Not Assessed | AB5: No - AI seeded | AC5: https://www.dnv.com/services/owner-s-engineering-for-energy-storage-63162
A6: OE-002 | B6: Enertis Applus+ | C6: Renewables and BESS technical advisory: design evaluation, site assessment, engineering, QA/QC, testing and optimization for developers, owners and financiers | D6: Madrid | F6: Spain | I6: https://enertisapplus.com | J6: +1 415 671 4000 (US offices, San Francisco / Raleigh) | K6: https://enertisapplus.com/contact/ | P6: Discovery | Q6: 46300 | R6: None | S6: Subsidiary of Applus+ (Applus Services S.A.), taken private June 2024 by Amber EquityCo (TDR Capital and I Squared Capital) | T6: Not Assessed | U6: Parent Applus+: 26,000+ employees in 70+ countries; TDR/I Squared takeover completed 14 Jun 2024 | V6: US offices in San Francisco, CA and Raleigh, NC; Madrid HQ; 15 offices globally | W6: Not Assessed | AB6: No - AI seeded | AC6: https://enertisapplus.com/
A7: OE-003 | B7: Black & Veatch | C7: BESS owner's engineer: EPC design review, construction monitoring, commissioning supervision, early operations oversight; firm reports 74 GWh supported as OE | D7: Overland Park | E7: KS | F7: USA | H7: Houston (Energy Corridor; second-largest B&V office); Dallas; Deer Park | I7: https://www.bv.com | J7: +1 913-458-2000 | K7: https://www.bv.com/contact-us | P7: Discovery | Q7: 46300 | R7: None | S7: Private; 100% employee-owned | T7: Not Assessed | U7: Revenue ~$4.7B (2023); ~13,000 employees (2024); ENR 2024 #13 design firm, #4 power design; acquired Bird Electric (Texas electrical contractor, ~600 staff) 2023 | V7: Houston office houses 300+ staff and is the regional hub for power and energy (May 2026) | W7: Not Assessed | AB7: No - AI seeded | AC7: https://new.bv.com/news/black-and-veatch-appointed-as-owners-engineer-for-eccles-battery-storage-project-in-scotland
A8: OE-004 | B8: Sargent & Lundy | C8: Owner's engineer for utility-scale solar + BESS: EPC RFP/specs, bid evaluation, contract negotiation support, review of LV/MV, collection, substation and transmission designs | D8: Chicago | E8: IL | F8: USA | H8: Fort Worth; Houston; Midland | I8: https://www.sargentlundy.com | J8: 312-269-2000 | K8: https://www.sargentlundy.com/contact-us | P8: Discovery | Q8: 46300 | R8: None | S8: Private; owned and managed by its employees (engineers) | T8: Not Assessed | U8: Founded 1891; 30+ offices; acquisitions include Summit Engineering Services and ARES Corp. Energy Services Division (2019) | W8: Not Assessed | AB8: No - AI seeded | AC8: https://www.sargentlundy.com/contact-us
A9: OE-005 | B9: Clean Energy Associates (Intertek CEA) | C9: Owner's engineer and technical due diligence; storage system QA, factory/production monitoring, supply-chain traceability for BESS and PV | E9: CO | F9: USA | I9: https://www.cea3.com | P9: Discovery | Q9: 46300 | R9: None | S9: Subsidiary of Intertek Group plc (LSE: ITRK); acquired 2022 | T9: Not Assessed | U9: Acquisition completed mid-2022 (price undisclosed); CEA had 150+ employees and GBP 21.7M revenue in 2021 | V9: Staff across North America, Europe and Asia; significant operations in China (factory QA) | W9: Not Assessed | AB9: No - AI seeded | AC9: https://www.cea3.com/
A10: OE-006 | B10: Kimley-Horn | C10: BESS consulting incl. owner's engineering, feasibility, siting/permitting, interconnection studies, and civil/structural/electrical design | D10: Raleigh | E10: NC | F10: USA | H10: Austin | I10: https://www.kimley-horn.com | K10: https://www.kimley-horn.com/contact/submit-a-service-inquiry/ | P10: Discovery | Q10: 46300 | R10: None | S10: Private; employee-owned | T10: Not Assessed | U10: Revenue US$2.8B (2025); 11,000+ employees; ENR Top 500 Design Firms #8 (2025) | W10: Not Assessed | AB10: No - AI seeded | AC10: https://www.kimley-horn.com/services/energy-consulting/battery-energy-storage-systems-consulting/
A11: OE-007 | B11: Natural Power | C11: Renewables-only consultant: owner's advisory, technology evaluation, field inspections and technical due diligence for standalone/co-located storage | D11: Castle Douglas | E11: Scotland | F11: UK | I11: https://www.naturalpower.com | J11: +1 (518) 308 0200 (Saratoga Springs, NY office) | K11: https://www.naturalpower.com/us/contact | P11: Discovery | Q11: 46300 | R11: None | S11: Private; independent (founded 1995) | T11: Not Assessed | U11: 400+ staff globally; 30+ NA IE projects (6+ GW) in 2025 | V11: US offices: Saratoga Springs NY, Seattle WA, Golden CO | W11: Not Assessed | AB11: No - AI seeded | AC11: https://www.naturalpower.com/us/sector/energy-storage

Sheet Eng of Record
A1: Engineer of record — Vendor Landscape
A2: Seeded 2026-10-05 from public sources (Discovery stage, unverified). Yellow columns = enter from vendor contact. Confirm all data before use; see Read Me.
A3: Vendor | D3: HQ Location | I3: Contact Information | P3: Qualification | S3: Financial Strength / Bankability | V3: Supply Chain / Origin Risk | X3: Tracking
A4: Vendor ID | B4: Vendor Name | C4: EOR Services | D4: HQ City | E4: HQ State / Prov | F4: HQ Country | G4: US HQ (if foreign) | H4: Texas Presence | I4: Website | J4: Main Phone | K4: Contact Page | L4: Primary Contact Name | M4: Contact Title | N4: Contact Email | O4: Contact Phone | P4: Qualification Status | Q4: Status Date | R4: Last RFx Stage | S4: Ownership / Parent | T4: Financial Strength | U4: Financial / Bankability Notes | V4: Staff / Delivery Origin | W4: Supply Chain Risk | X4: Last Contact Date | Y4: Next Action | Z4: Next Action Due | AA4: Notes | AB4: Data Verified? | AC4: Primary Source
A5: EOR-001 | B5: Burns & McDonnell | C5: In-house design engineering and EPC for BESS, substations and transmission; delivered Texas BESS EPC (e.g., RWE Texas Waves II, LGES/SER West Texas) | D5: Kansas City | E5: MO | F5: USA | H5: Amarillo; Austin; Dallas-Fort Worth; Houston; Pearland; San Antonio | I5: https://www.burnsmcd.com | J5: (816) 333-9400 | K5: https://info.burnsmcd.com/contact-us | P5: Discovery | Q5: 46300 | R5: None | S5: Private; 100% employee-owned | T5: Not Assessed | U5: 75+ offices worldwide; founded 1898 | W5: Not Assessed | AB5: No - AI seeded | AC5: https://www.burnsmcd.com/
A6: EOR-002 | B6: Sargent & Lundy | C6: Power engineering firm: electrical design for collection, substation and transmission; renewables and storage engineering | D6: Chicago | E6: IL | F6: USA | H6: Fort Worth; Houston; Midland | I6: https://www.sargentlundy.com | J6: 312-269-2000 | K6: https://www.sargentlundy.com/contact-us | P6: Discovery | Q6: 46300 | R6: None | S6: Private; owned and managed by its employees (engineers) | T6: Not Assessed | U6: Founded 1891; 30+ offices | W6: Not Assessed | AB6: No - AI seeded | AC6: https://www.sargentlundy.com/contact-us
A7: EOR-003 | B7: POWER Engineers (Member of WSP) | C7: Power delivery engineering: substation, transmission, renewables and storage design | D7: Hailey | E7: ID | F7: USA | I7: https://www.powereng.com | P7: Discovery | Q7: 46300 | R7: None | S7: Subsidiary of WSP Global Inc. (TSX: WSP) | T7: Not Assessed | U7: Acquired by WSP for US$1.78B, completed 1 Oct 2024; ~4,000 employees, ~50 US locations | V7: WSP substation job postings show Fort Worth and Spring, TX roles (unconfirmed as POWER offices) | W7: Not Assessed | AB7: No - AI seeded | AC7: https://www.wsp.com/en-gl/investors/press-releases/details/WSP-Completes-Acquisition--of-POWER-Engineers/2956467/2024
A8: EOR-004 | B8: Westwood Professional Services | C8: Design, permitting and optimization of standalone/hybrid BESS; substation and transmission line engineering; surveying | D8: Plano | E8: TX | F8: USA | H8: Plano (HQ); Austin; Celina; Dallas; Farmers Branch; Fort Worth; Frisco; Houston; San Antonio; Victoria | I8: https://www.westwoodps.com | J8: 1-888-937-5150 | K8: https://westwoodps.com/contact-us | P8: Discovery | Q8: 46300 | R8: None | S8: PE-backed; Blackstone Energy Transition Partners majority investment (Aug 2024), previously Endurance Partners | T8: Not Assessed | U8: 1,600+ employees (2024); acquired O'Dell Engineering (California) | V8: Texas-headquartered | W8: Not Assessed | AB8: No - AI seeded | AC8: https://www.westwoodps.com/
A9: EOR-005 | B9: Black & Veatch | C9: Engineering and EPC for BESS and HV substations; firm reports 8.9 GWh delivered as BESS EPC | D9: Overland Park | E9: KS | F9: USA | H9: Houston; Dallas; Deer Park | I9: https://www.bv.com | J9: +1 913-458-2000 | K9: https://www.bv.com/contact-us | P9: Discovery | Q9: 46300 | R9: None | S9: Private; 100% employee-owned | T9: Not Assessed | U9: Revenue ~$4.7B (2023); ~13,000 employees; ENR 2024 #4 power design | W9: Not Assessed | AB9: No - AI seeded | AC9: https://new.bv.com/news/black-and-veatch-appointed-as-owners-engineer-for-eccles-battery-storage-project-in-scotland
A10: EOR-006 | B10: Kimley-Horn | C10: Detailed civil, structural and electrical BESS design incl. plant, HV substation and transmission/interconnection design | D10: Raleigh | E10: NC | F10: USA | H10: Austin | I10: https://www.kimley-horn.com | K10: https://www.kimley-horn.com/contact/submit-a-service-inquiry/ | P10: Discovery | Q10: 46300 | R10: None | S10: Private; employee-owned | T10: Not Assessed | U10: Revenue US$2.8B (2025); 11,000+ employees; ENR Top 500 Design Firms #8 (2025) | W10: Not Assessed | AB10: No - AI seeded | AC10: https://www.kimley-horn.com/services/energy-consulting/battery-energy-storage-systems-consulting/
A11: EOR-007 | B11: Bowman Consulting Group | C11: Energy design and engineering incl. BESS, electric power and transmission; civil/survey | D11: Reston | E11: VA | F11: USA | H11: Austin; Arlington; Plano (Dallas); Houston (2); Marshall; Midland; San Antonio; San Marcos; Waco | I11: https://bowman.com | K11: https://bowman.com/contact/ | P11: Discovery | Q11: 46300 | R11: None | S11: Public (Nasdaq: BWMN) | T11: Not Assessed | U11: FY2025 gross contract revenue ~$490M; 2,300+ employees; ENR Top 500 #72; 7 acquisitions in 2025 (~$75.4M) incl. RPT Alliance (Houston, Dec 2025) | W11: Not Assessed | AB11: No - AI seeded | AC11: https://bowman.com/services/battery-energy-storage-systems

Sheet Independent Eng
A1: Independent engineer — Vendor Landscape
A2: Seeded 2026-10-05 from public sources (Discovery stage, unverified). Yellow columns = enter from vendor contact. Confirm all data before use; see Read Me.
A3: Vendor | D3: HQ Location | I3: Contact Information | P3: Qualification | S3: Financial Strength / Bankability | V3: Supply Chain / Origin Risk | X3: Tracking
A4: Vendor ID | B4: Vendor Name | C4: IE Services | D4: HQ City | E4: HQ State / Prov | F4: HQ Country | G4: US HQ (if foreign) | H4: Texas Presence | I4: Website | J4: Main Phone | K4: Contact Page | L4: Primary Contact Name | M4: Contact Title | N4: Contact Email | O4: Contact Phone | P4: Qualification Status | Q4: Status Date | R4: Last RFx Stage | S4: Ownership / Parent | T4: Financial Strength | U4: Financial / Bankability Notes | V4: Staff / Delivery Origin | W4: Supply Chain Risk | X4: Last Contact Date | Y4: Next Action | Z4: Next Action Due | AA4: Notes | AB4: Data Verified? | AC4: Primary Source
A5: IE-001 | B5: DNV | C5: Independent engineering and technical due diligence for BESS: vendor/design/safety review, performance validation, guarantee verification, bankability for investors/financiers | D5: Høvik | F5: Norway | H5: Houston (North America HQ); Austin; Dallas (per DNV job postings) | I5: https://www.dnv.com | J5: +1 281 396 1000 (DNV North America HQ, Houston) | K5: https://www.dnv.us/contact/ | P5: Discovery | Q5: 46300 | R5: None | S5: Private; owned by the independent foundation Stiftelsen Det Norske Veritas | T5: Not Assessed | U5: 2025 operating revenue NOK 35,291 million | V5: Energy Storage IE PM roles posted in Austin and Houston among other US cities | W5: Not Assessed | AB5: No - AI seeded | AC5: https://www.dnv.com/services/independent-engineering-and-technical-due-diligence-63108/
A6: IE-002 | B6: Enertis Applus+ | C6: Lender's IE for BESS: project-finance technical due diligence, design/grid/warranty review, MC/SC/FC milestone certification (e.g., 550 MW / 1,433 MWh Texas portfolio for Excelsior/Lydian) | D6: Madrid | F6: Spain | I6: https://enertisapplus.com | J6: +1 415 671 4000 (US offices) | K6: https://enertisapplus.com/contact/ | P6: Discovery | Q6: 46300 | R6: None | S6: Subsidiary of Applus+ (private since June 2024; TDR Capital and I Squared Capital) | T6: Not Assessed | U6: Parent Applus+: 26,000+ employees, 70+ countries | V6: US offices in San Francisco, CA and Raleigh, NC | W6: Not Assessed | AB6: No - AI seeded | AC6: https://informedinfrastructure.com/index.php/post/enertis-applus-delivers-independent-engineering-expertise-to-texas-bess-projects-for-excelsior-energy-capital
A7: IE-003 | B7: Leidos | C7: Independent engineering for project development, acquisition, financing and investment diligence across energy storage and other technologies | D7: Reston | E7: VA | F7: USA | I7: https://www.leidos.com | J7: (571) 526-6000 | K7: https://www.leidos.com/contact | P7: Discovery | Q7: 46300 | R7: None | S7: Public (NYSE: LDOS) | T7: Not Assessed | U7: ~48,000 employees (Jan 2025); ~87% of FY2024 revenue from US government; energy IE is a small commercial practice | W7: Not Assessed | AB7: No - AI seeded | AC7: https://www.infocastinc.com/2026-solar-wind-finance-investment-sponsors/leidos
A8: IE-004 | B8: Sargent & Lundy | C8: BESS independent engineering due diligence for investors/tax equity: use-case modeling, module warranty terms, fire protection design | D8: Chicago | E8: IL | F8: USA | H8: Fort Worth; Houston; Midland | I8: https://www.sargentlundy.com | J8: 312-269-2000 | K8: https://www.sargentlundy.com/contact-us | P8: Discovery | Q8: 46300 | R8: None | S8: Private; owned and managed by its employees (engineers) | T8: Not Assessed | U8: Founded 1891; describes itself as one of the few tax-equity-accepted IEs for BESS | W8: Not Assessed | AB8: No - AI seeded | AC8: https://sargentlundy.com/?p=12226
A9: IE-005 | B9: Natural Power | C9: Independent engineering and technical due diligence for lenders/investors on wind, solar and storage; new Head of IE North America (Dec 2025) | D9: Castle Douglas | E9: Scotland | F9: UK | I9: https://www.naturalpower.com | J9: +1 (518) 308 0200 (Saratoga Springs, NY office) | K9: https://www.naturalpower.com/us/contact | P9: Discovery | Q9: 46300 | R9: None | S9: Private; independent (founded 1995) | T9: Not Assessed | U9: 400+ staff; 184+ GW NA transactions supported since 2022; 30+ NA IE projects (6+ GW) in 2025 | V9: US offices: Saratoga Springs NY, Seattle WA, Golden CO | W9: Not Assessed | AB9: No - AI seeded | AC9: https://www.naturalpower.com/us/news/news-post/natural-power-appoints-head-of-independent-engineering-in-north-america
A10: IE-006 | B10: UL Solutions | C10: Energy Storage Advisory: IE and technical advisory for project financing, tax equity, sales and acquisitions (contracts, financial models, designs); BESS testing/certification | D10: Northbrook | E10: IL | F10: USA | I10: https://www.ul.com | J10: (847) 272-8800 | P10: Discovery | Q10: 46300 | R10: None | S10: Public (NYSE: ULS); majority voting control held by ULSE Inc. (UL Standards & Engagement) | T10: Not Assessed | U10: ~14,600 full-time employees (FY2025); 110+ countries | W10: Not Assessed | AB10: No - AI seeded | AC10: https://www.builtinchicago.org/job/senior-project-engineer-energy-storage-advisory/9342322

Sheet BESS Equipment
A1: Energy storage equipment — Vendor Landscape
A2: Seeded 2026-10-05 from public sources (Discovery stage, unverified). Yellow columns = enter from vendor contact. Confirm all data before use; see Read Me.
A3: Vendor | D3: HQ Location | I3: Contact Information | P3: Qualification | S3: Financial Strength / Bankability | V3: Supply Chain / Origin Risk | X3: Tracking
A4: Vendor ID | B4: Vendor Name | C4: Product Line | D4: HQ City | E4: HQ State / Prov | F4: HQ Country | G4: US HQ (if foreign) | H4: Texas Presence | I4: Website | J4: Main Phone | K4: Contact Page | L4: Primary Contact Name | M4: Contact Title | N4: Contact Email | O4: Contact Phone | P4: Qualification Status | Q4: Status Date | R4: Last RFx Stage | S4: Ownership / Parent | T4: Financial Strength | U4: Financial / Bankability Notes | V4: Manufacturing / Cell Origin | W4: Supply Chain Risk | X4: Last Contact Date | Y4: Next Action | Z4: Next Action Due | AA4: Notes | AB4: Data Verified? | AC4: Primary Source
A5: BESS-001 | B5: Tesla (Tesla Energy) | C5: Megapack 2 / Megapack 2 XL / Megapack 3 (~5 MWh) / Megablock (4x Megapack 3 + transformer + switchgear, ~20 MWh) | D5: Austin | E5: TX | F5: USA | H5: Austin (corporate HQ); Brookshire, TX Megafactory (Megapack 3 production began Aug 2026 per SMM report) | I5: https://www.tesla.com/megapack | K5: https://www.tesla.com/megapack | P5: Discovery | Q5: 46300 | R5: None | S5: Public (NASDAQ: TSLA) | T5: Not Assessed | U5: Brookshire, TX Megafactory targets 50 GWh/yr; ~$200M investment and 1,500-job commitment by 2028 (Basenor, Apr/Jul 2026). BNEF tier status not confirmed in this pass. | V5: Megapack 3 built in Brookshire, TX (production start reported Aug 6, 2026). Per SMM (Aug 2026), LFP cell suppliers span US, Southeast Asia and China, with CATL identified as Tesla's largest storage cell supplier; a reported $4.3B LG Energy Solution deal supplies LFP cells from Lansing, MI (secondary source). Cell origin varies by order — FEOC/material-assistance review of cell supply required; tariff exposure on any China-origin cells. | W5: FEOC Review | AB5: No - AI seeded | AC5: https://www.tesla.com/megapack
A6: BESS-002 | B6: Fluence Energy | C6: Grid-scale BESS (Gridstack/Smartstack platforms), US domestic-content offering | D6: Arlington | E6: VA | F6: USA | I6: https://fluenceenergy.com | P6: Discovery | Q6: 46300 | R6: None | S6: Public (NASDAQ: FLNC); AES and Siemens are founding shareholders | T6: Not Assessed | U6: FY2025 revenue $2.3B; FY2026 guidance $3.2-3.6B; record backlog $5.3B (results released Nov 24, 2025). | V6: US module assembly in Tooele County, UT; LFP cells from a supplier in Smyrna, TN; partner manufacturing ramping in AZ and TX (May 28, 2025). Markets a US domestic-content strategy. Confirm cell/enclosure origin per order for FEOC compliance. | W6: FEOC Review | AB6: No - AI seeded | AC6: https://www.nasdaq.com/press-release/fluence-energy-inc-reports-2025-financial-results-and-initiates-2026-guidance-2025-11
A7: BESS-003 | B7: Sungrow | C7: PowerTitan 3.0 AC block (6.9 MWh per 20-ft container); PowerStack (C&I) | D7: Hefei | E7: Anhui | F7: China | G7: Costa Mesa, CA (3200 Park Center Dr Suite 850) | I7: https://www.sungrowpower.com/us/en | J7: +1 833 747 6937 | K7: https://www.sungrowpower.com/us/en/about-us/contact-us | P7: Discovery | Q7: 46300 | R7: None | S7: Public (Shenzhen: 300274) | T7: Not Assessed | U7: PowerTitan 3.0 launched for North America at RE+ 2025 (Sep 9, 2025). BNEF tier status not confirmed in this pass. | V7: Chinese parent company — FEOC review required under OBBBA (enacted Jul 4, 2025). No US manufacturing identified in sources reviewed; China-origin equipment subject to Section 301/reciprocal tariffs. | W7: FEOC Review | AB7: No - AI seeded | AC7: https://www.powermag.com/sungrow-introduces-new-solar-energy-storage-products-for-north-american-market/
A8: BESS-004 | B8: LG Energy Solution Vertech | C8: Containerized LFP grid-scale BESS + AEROS controls/analytics; integration and lifecycle services | D8: Seoul | F8: South Korea | G8: Westborough, MA | P8: Discovery | Q8: 46300 | R8: None | S8: Subsidiary of LG Energy Solution (KRX: 373220) | T8: Not Assessed | U8: Dec 19, 2024: multi-year 7.5 GWh agreement with Excelsior Energy Capital (first delivery Apr 2026), following an 8 GWh Terra-Gen agreement. | V8: LFP ESS cells produced at LG Energy Solution's Lansing, MI plant (production began 2025; >35 GWh/yr at full scale). Products marketed as meeting US domestic-content requirements. Korean parent (not a covered-nation FEOC on its face) — still confirm material-assistance cost ratio per OBBBA. | W8: FEOC Review | AB8: No - AI seeded | AC8: https://lgcorp.com/media/release/28489
A9: BESS-005 | B9: Samsung SDI | C9: Samsung Battery Box (SBB) 2.0 — prismatic LFP DC block (cell/DC supplier; requires PCS/EMS integrator) | D9: Yongin | E9: Gyeonggi | F9: South Korea | I9: https://www.samsungsdi.com | P9: Discovery | Q9: 46300 | R9: None | S9: Public (KRX: 006400) | T9: Not Assessed | U9: Dec 2025: ~$1.36B, 3-year LFP ESS supply contract with an unnamed North American energy company, deliveries from 2027. | V9: Converting lines at StarPlus Energy (Samsung SDI–Stellantis JV) plant in Kokomo, IN to prismatic LFP ESS cells (announced Dec 10, 2025); company describes itself as the only non-Chinese prismatic LFP ESS cell maker producing in the US. Korean parent. | W9: Not Assessed | AB9: No - AI seeded | AC9: https://www.solarpowerworldonline.com/2025/12/samsung-sdi-to-begin-lfp-battery-manufacturing-in-indiana/
A10: BESS-006 | B10: Wärtsilä Energy Storage | C10: Quantum3 AC-block BESS (introduced Sep 2024); GEMS software | D10: Helsinki | F10: Finland | G10: Houston, TX (Wärtsilä North America, Inc., 11710 N. Gessner Rd., Suite A); Energy Storage offices Emeryville, CA and Herndon, VA | H10: Houston, TX | I10: https://www.wartsila.com/usa | J10: +1 281 233 6200 | K10: https://www.wartsila.com/usa/about/contact-us | P10: Discovery | Q10: 46300 | R10: None | S10: Public (Nasdaq Helsinki: WRT1V) | T10: Not Assessed | U10: Mar 31, 2025: concluded 18-month strategic review and retained the energy storage business; separate Energy Storage reporting segment from Apr 1, 2025 (target ≥10% organic growth, 3-5% operating margin). | V10: Cell supplier/origin not stated in sources reviewed — confirm cell origin for FEOC/tariff review. | W10: FEOC Review | AB10: No - AI seeded | AC10: https://energy-storage.news/wartsila-closes-strategic-review-of-energy-storage-segment-remains-committed-to-sector
A11: BESS-007 | B11: FlexGen Power Systems | C11: BESS integration with HybridOS EMS; legacy Powin fleet support (Powin assets/IP acquired) | D11: Durham | E11: NC | F11: USA | I11: https://www.flexgen.com | J11: 855-327-5674 | K11: https://www.flexgen.com/contact-us | P11: Discovery | Q11: 46300 | R11: None | S11: Private | T11: Not Assessed | U11: Acquired key Powin assets and IP via court-approved sale (court approval announced Aug 6, 2025; completion announced Aug 15, 2025); now supports >25 GWh across >200 sites. | V11: No manufacturing locations stated in sources reviewed; confirm battery/cell OEM and origin per project for FEOC review. Legacy Powin warranty/support assumptions should be diligenced. | W11: FEOC Review | AB11: No - AI seeded | AC11: https://www.flexgen.com/resources/blog/flexgen-completes-acquisition-powin-assets-expanding-global-leadership-grid-scale
A12: BESS-008 | B12: Hithium | C12: LFP BESS modules/systems (∞Power 6.25 MWh platform) | D12: Xiamen | E12: Fujian | F12: China | H12: Mesquite, TX (12955 FM 2932) — module/system plant | I12: https://hithium.com | P12: Discovery | Q12: 46300 | R12: None | S12: Private (founded 2019) | T12: Not Assessed | U12: ~$200M Mesquite plant opened May 28/Jun 5, 2025; 10 GWh/yr modules and systems; mass production slated for late 2025. | V12: Chinese parent company — FEOC review required under OBBBA. US assembly in Mesquite, TX; cell origin not stated in sources (assume imported until confirmed) — tariff relevance. | W12: FEOC Review | AB12: No - AI seeded | AC12: https://dallasinnovates.com/hithium-opens-200m-battery-energy-storage-manufacturing-facility-in-north-texas/
A13: BESS-009 | B13: Canadian Solar e-STORAGE | C13: Utility-scale BESS (SolBank platform) and EPC/LTSA services | D13: Kitchener | E13: ON | F13: Canada | H13: Mesquite, TX module plant (solar, not storage) | I13: https://www.csisolar.com/e-storage/ | P13: Discovery | Q13: 46300 | R13: None | S13: Part of Canadian Solar Inc. (NASDAQ: CSIQ); US manufacturing consolidated into CS PowerTech (75.1% CSIQ / 24.9% CSI Solar) | T13: Not Assessed | U13: Company states Tier 1 storage rating and 23 GWh shipped. Q2 2026: revenue $1.2B (-29% YoY), net loss $76.9M, e-STORAGE backlog $3.5B (IIR, Aug 28, 2026). Dec 2025 restructuring moved US manufacturing out from under China-listed CSI Solar. | V13: Shelbyville, KY BESS plant: Phase I 3 GWh complete, Phase II planned later 2026 to double capacity. CSI Solar (Suzhou, China-listed) retains 24.9% of US JV — FEOC review required; restructuring was positioned to address FEOC rules. | W13: FEOC Review | AB13: No - AI seeded | AC13: https://www.ess-news.com/2025/12/01/canadian-solar-consolidates-us-manufacturing-under-parent-including-solar-and-storage/
A14: BESS-010 | B14: Prevalon Energy (now Nextpower) | C14: HD5 AC / HD5 DC BESS platforms, insightOS, service/LTSA | D14: Fremont | E14: CA | F14: USA | I14: https://prevalonenergy.com | K14: https://prevalonenergy.com/contact-us/ | P14: Discovery | Q14: 46300 | R14: None | S14: Subsidiary of Nextpower (NASDAQ: NXT; formerly Nextracker) since Jul 20, 2026; previously Mitsubishi Power Americas / EES JV | T14: Not Assessed | U14: Nextpower completed acquisition for up to $365M cash and stock (Jul 20, 2026); Prevalon has >6 GWh deployed; CEO Tom Cornell continues leading the division. | V14: Cell supplier and manufacturing locations not stated in sources reviewed — confirm origin for FEOC/tariff review. HQ shown is Nextpower parent (Prevalon described as US-headquartered). | W14: FEOC Review | AB14: No - AI seeded | AC14: https://www.businesswire.com/news/home/20260720085364/en/

Sheet MV Transformers
A1: Medium-voltage transformers — Vendor Landscape
A2: Seeded 2026-10-05 from public sources (Discovery stage, unverified). Yellow columns = enter from vendor contact. Confirm all data before use; see Read Me.
A3: Vendor | D3: HQ Location | I3: Contact Information | P3: Qualification | S3: Financial Strength / Bankability | V3: Supply Chain / Origin Risk | X3: Tracking
A4: Vendor ID | B4: Vendor Name | C4: Product Line | D4: HQ City | E4: HQ State / Prov | F4: HQ Country | G4: US HQ (if foreign) | H4: Texas Presence | I4: Website | J4: Main Phone | K4: Contact Page | L4: Primary Contact Name | M4: Contact Title | N4: Contact Email | O4: Contact Phone | P4: Qualification Status | Q4: Status Date | R4: Last RFx Stage | S4: Ownership / Parent | T4: Financial Strength | U4: Financial / Bankability Notes | V4: Manufacturing Origin | W4: Supply Chain Risk | X4: Last Contact Date | Y4: Next Action | Z4: Next Action Due | AA4: Notes | AB4: Data Verified? | AC4: Primary Source
A5: MVT-001 | B5: Hitachi Energy | C5: Pad-mount and distribution transformers (single-phase pad-mount from Reynosa); large distribution transformers (South Boston, VA) | D5: Zurich | F5: Switzerland | G5: Raleigh, NC | I5: https://www.hitachienergy.com/us/en | P5: Discovery | Q5: 46300 | R5: None | S5: Subsidiary of Hitachi, Ltd. (TSE: 6501) | T5: Not Assessed | U5: Sep 2024: $155M North American expansion (incl. $70M Reynosa MX pad-mount plant, $25M+ South Boston VA). Sep 5, 2025: $1B US manufacturing commitment incl. ~$457-475M South Boston VA large power transformer plant (ops ~2028). | V5: US plants in South Boston, VA; pad-mount distribution transformers from Reynosa, Mexico (USMCA). Confirm three-phase 34.5 kV BESS/solar pad-mount availability and plant of origin per quote. | W5: Not Assessed | AB5: No - AI seeded | AC5: https://www.publicpower.org/periodical/article/hitachi-energy-new-distribution-transformer-factory-serve-north-american-market
A6: MVT-002 | B6: Eaton | C6: Three-phase pad-mount transformers; single-phase/pole/pad-mount | D6: Dublin | F6: Ireland | G6: Cleveland (Beachwood), OH | H6: Nacogdoches, TX (single-phase, pole-mount and pad-mount transformer plant) | I6: https://www.eaton.com/us/en-us.html | P6: Discovery | Q6: 46300 | R6: None | S6: Public (NYSE: ETN) | T6: Not Assessed | U6: Feb 12, 2025: $340M Jonesville, SC three-phase transformer plant (production 2027, 700 jobs); >$1B invested in North American electrical manufacturing since 2023. | V6: US transformer plants: Waukesha, WI (three-phase), Nacogdoches, TX, Jonesville, SC (from 2027). US-manufactured options available. | W6: Not Assessed | AB6: No - AI seeded | AC6: https://www.businesswire.com/news/home/20250212663224/en
A7: MVT-003 | B7: Prolec GE (GE Vernova) | C7: Three-phase pad-mount (Shreveport) and medium power / substation transformers (Goldsboro) | D7: Monterrey | E7: Nuevo León | F7: Mexico | I7: https://www.prolec.energy | P7: Discovery | Q7: 46300 | R7: None | S7: Wholly owned by GE Vernova (NYSE: GEV) since Feb 5, 2026 (bought Xignux's 50% for $5.275B); operating under GE Vernova brand in Electrification segment | T7: Not Assessed | U7: ~10,000 employees, 7 manufacturing sites incl. 5 in US. May 14, 2025: $140M Goldsboro, NC expansion (doubling capacity by 2030); >$300M recent North American investment. | V7: US plants: Shreveport, LA (three-phase pad-mount, 1,500+ units/yr) and Goldsboro, NC (medium power); additional plants in Mexico (USMCA). | W7: Not Assessed | AB7: No - AI seeded | AC7: https://www.tdworld.com/utility-business/news/55355616/ge-vernova-completes-acquisition-of-prolec-ge
A8: MVT-004 | B8: WEG | C8: Distribution and power transformers (WEG Transformers USA); confirm three-phase 34.5 kV pad-mount offering | D8: Jaraguá do Sul | E8: Santa Catarina | F8: Brazil | I8: https://www.weg.net/institutional/US/en/ | P8: Discovery | Q8: 46300 | R8: None | S8: Public (B3: WEGE3) | T8: Not Assessed | U8: Sep 2025: $77M, 130,000 sq ft expansion of Washington, MO transformer plant (50 jobs). | V8: US transformer manufacturing in Washington, MO. US HQ and BESS/solar pad-mount product details not confirmed in this pass. | W8: Not Assessed | AB8: No - AI seeded | AC8: https://www.areadevelopment.com/newsItems/9-27-2025/weg-washington-missouri.shtml
A9: MVT-005 | B9: Virginia Transformer Corp | C9: E2X pad-mount; liquid substation/GSU (500 kVA–1,400 MVA); BESS listed as served industry | D9: Roanoke | E9: VA | F9: USA | I9: https://www.vatransformer.com | J9: (540) 345-9892 | K9: https://www.vatransformer.com | P9: Discovery | Q9: 46300 | R9: None | S9: Private, US-owned | T9: Not Assessed | U9: Bloomberg (Jan 9, 2025) reported it was considering a sale (~$6B). Nov 20, 2025: Rincon, GA expansion starting Jan 2026 (+400 jobs, ~70% capacity increase); still privately held per that release. | V9: Six facilities across US and Mexico (incl. Rincon, GA power transformers 30–500 MVA up to 525 kV). Watch for ownership change. | W9: Not Assessed | AB9: No - AI seeded | AC9: https://www.vatransformer.com/
A10: MVT-006 | B10: ERMCO | C10: Three-phase and single-phase pad-mount distribution transformers (incl. ECO-PAD) | D10: Dyersburg | E10: TN | F10: USA | I10: https://www.ermco-eci.com | K10: https://www.ermco-eci.com/ | P10: Discovery | Q10: 46300 | R10: None | S10: Subsidiary of Arkansas Electric Cooperatives, Inc. (cooperative-owned) | T10: Not Assessed | U10: Describes itself as the largest US maker of oil-filled distribution transformers. Jan 2026: new ~566,000 sq ft three-phase plant west of Phoenix, AZ (production 2027, ~541 jobs). | V10: Facilities in Dyersburg, Greeneville and Bristol, TN, and Reynosa, Mexico; Arizona plant from 2027. Primarily distribution-class; confirm kVA range for BESS MV step-up. | W10: Not Assessed | AB10: No - AI seeded | AC10: https://www.ermco-eci.com/
A11: MVT-007 | B11: Howard Industries | C11: Distribution transformers incl. large three-phase pad-mount 750–10,000 kVA (utilities, data centers, BESS) | D11: Ellisville | E11: MS | F11: USA | I11: https://www.howard.com | J11: (601) 425-3151 | P11: Discovery | Q11: 46300 | R11: None | S11: Private | T11: Not Assessed | U11: Jun 26, 2025: >$230M Mississippi expansion (450 jobs). May 8, 2026: ~$100M, 825,000 sq ft Mexico plant for three-phase 750–10,000 kVA units, operational Q3 2026. | V11: Mississippi plants (Laurel/Ellisville area, Quitman); new Mexico plant (USMCA) explicitly targeting BESS. | W11: Not Assessed | AB11: No - AI seeded | AC11: https://www.howard.com/INFO/news/2025/06/26/howard-industries-invests-over-230-million-to-expand-operations-across-mississippi.cfm
A12: MVT-008 | B12: Maddox Transformer | C12: New and remanufactured three-phase pad-mount and substation transformers; in-stock inventory | D12: Battle Ground | E12: WA | F12: USA | H12: Houston, TX | I12: https://www.maddox.com | J12: 1-800-270-2011 | K12: https://www.maddox.com/contact | P12: Discovery | Q12: 46300 | R12: None | S12: Private (founded 2015); ownership structure not disclosed | T12: Not Assessed | U12: No financial data published in sources reviewed. | V12: Locations in WA, SC (5 sites), OH and Houston, TX. Manufacturing origin of new units not stated — confirm country of origin per unit for tariff review. | W12: Not Assessed | AB12: No - AI seeded | AC12: https://www.maddox.com/
A13: MVT-009 | B13: JST Power Equipment | C13: Liquid-filled pad-mount 1- and 3-phase (25–6,000 kVA, up to 35 kV); MV switchgear and packaged substations | D13: Lake Mary | E13: FL | F13: USA | I13: https://www.jstpower.com | K13: https://jstpower.com/contact/ | P13: Discovery | Q13: 46300 | R13: None | S13: Not disclosed in sources reviewed — confirm parent/ultimate ownership | T13: Not Assessed | U13: May 19, 2026: opened Wytheville, VA pad-mount plant (~150 units 2026, scaling to 1,000 in 2027). | V13: Plants in Wuhan, China (2021), Nogales, Mexico (2019), Malaysia (2025) and Wytheville, VA. China-origin units carry tariff exposure; specify plant of origin in RFQ. | W13: Not Assessed | AB13: No - AI seeded | AC13: https://www.businesswire.com/news/home/20260519751615/en/JST-Power-Equipment-Opens-Virginia-Transformer-Manufacturing-Facility-to-Support-Power-for-Utilities-and-Data-Center-Demand
A14: MVT-010 | B14: Sunbelt Solomon | C14: New and refurbished pad-mount and substation transformers; rentals and field services | D14: Temple | E14: TX | F14: USA | H14: Temple, TX (HQ and facility) | I14: https://www.sunbeltsolomon.com | J14: 888-691-4712 | K14: https://www.sunbeltsolomon.com/ | P14: Discovery | Q14: 46300 | R14: None | S14: Private; Trilantic North America portfolio company | T14: Not Assessed | U14: Formed by 2019 merger of Sunbelt Transformer and Solomon Corp; added Trinity Power Rentals (2022) and Power Solutions Group (2024). 40+ locations; 64,000+ units in inventory. | V14: Facilities in Temple, TX; Solomon, KS; Sharon, PA; Elba and Bay Minette, AL; plus Canada and Chile. Origin of new units not stated — confirm per unit. | W14: Not Assessed | AB14: No - AI seeded | AC14: https://www.sunbeltsolomon.com/

Sheet HV Breakers
A1: High-voltage breakers (345 kV class) — Vendor Landscape
A2: Seeded 2026-10-05 from public sources (Discovery stage, unverified). Yellow columns = enter from vendor contact. Confirm all data before use; see Read Me.
A3: Vendor | D3: HQ Location | I3: Contact Information | P3: Qualification | S3: Financial Strength / Bankability | V3: Supply Chain / Origin Risk | X3: Tracking
A4: Vendor ID | B4: Vendor Name | C4: Product Line | D4: HQ City | E4: HQ State / Prov | F4: HQ Country | G4: US HQ (if foreign) | H4: Texas Presence | I4: Website | J4: Main Phone | K4: Contact Page | L4: Primary Contact Name | M4: Contact Title | N4: Contact Email | O4: Contact Phone | P4: Qualification Status | Q4: Status Date | R4: Last RFx Stage | S4: Ownership / Parent | T4: Financial Strength | U4: Financial / Bankability Notes | V4: Manufacturing Origin | W4: Supply Chain Risk | X4: Last Contact Date | Y4: Next Action | Z4: Next Action Due | AA4: Notes | AB4: Data Verified? | AC4: Primary Source
A5: HVB-001 | B5: Hitachi Energy | C5: Dead tank circuit breakers up to 420 kV (incl. 362 kV); EconiQ SF6-free; PASS hybrid switchgear | D5: Zurich | F5: Switzerland | G5: Raleigh, NC | I5: https://www.hitachienergy.com/us/en | P5: Discovery | Q5: 46300 | R5: None | S5: Subsidiary of Hitachi, Ltd. (TSE: 6501) | T5: Not Assessed | U5: Apr 2025: >$70M Pennsylvania investments (Mount Pleasant, Hunker, Greensburg); full capacity expected 2026. Part of $1B US commitment (Sep 5, 2025) incl. Pittsburgh-area breaker/switchgear expansion. | V5: Dead tank breakers manufactured in Mount Pleasant, PA (US-made). | W5: Not Assessed | AB5: No - AI seeded | AC5: https://www.hitachienergy.com/products-and-solutions/high-voltage-switchgear-and-breakers/air-insulated-switchgear/dead-tank-circuit-breaker-362-420-kv
A6: HVB-002 | B6: Siemens Energy | C6: Dead tank breakers 72.5–550 kV (US SPS 362 kV); Blue SF6-free portfolio | D6: Munich | F6: Germany | I6: https://siemens-energy.com/us/en/home.html | K6: https://siemens-energy.com/us/en/home/products-services/product/dead-tank.html | P6: Discovery | Q6: 46300 | R6: None | S6: Public (Frankfurt: ENR) | T6: Not Assessed | U6: Feb 3, 2026: ~$1B US investment incl. new high-voltage switchgear plant near Richland, MS (300 jobs) and Charlotte, NC transformer expansion. | V6: Richland, MS HV switchgear/breaker manufacturing (expanding). German parent. | W6: Not Assessed | AB6: No - AI seeded | AC6: https://siemens-energy.com/us/en/home/products-services/product/dead-tank.html
A7: HVB-003 | B7: GE Vernova | C7: Dead tank breakers up to 550 kV (DT1-362 for 362 kV); g3 SF6-free models (72.5/145 kV) | D7: Cambridge | E7: MA | F7: USA | I7: https://www.gevernova.com/grid-solutions/equipment/circuit-breakers/dead-tank-circuit-breakers | P7: Discovery | Q7: 46300 | R7: None | S7: Public (NYSE: GEV) | T7: Not Assessed | U7: Aug 20, 2026: $138M expansion of Charleroi, PA plant (HV breakers, switchgear, instrument transformers; ~275 jobs through 2028). Acquired 100% of Prolec GE Feb 5, 2026. | V7: HV circuit breakers manufactured in Charleroi, PA (US). | W7: Not Assessed | AB7: No - AI seeded | AC7: https://www.gevernova.com/grid-solutions/equipment/circuit-breakers/dead-tank-circuit-breakers
A8: HVB-004 | B8: Mitsubishi Electric Power Products (MEPPI) | C8: Dead tank gas circuit breakers 72.5–800 kV (362 kV up to 63 kA) | D8: Tokyo | F8: Japan | G8: Warrendale, PA | I8: https://www.meppi.com | K8: https://www.meppi.com/contact-us | P8: Discovery | Q8: 46300 | R8: None | S8: Subsidiary of Mitsubishi Electric Corp. (TSE: 6503) | T8: Not Assessed | U8: $86M investment incl. new 160,000 sq ft Warrendale, PA factory for vacuum and gas circuit breakers (>200 jobs; reported 2025). | V8: Breakers 'fully assembled and tested in the USA' per MEPPI. | W8: Not Assessed | AB8: No - AI seeded | AC8: https://meppi.com/products/hv-gas-insulated-circuit-breakers
A9: HVB-005 | B9: Hyosung HICO | C9: Gas circuit breakers 72.5–800 kV | D9: Seoul | F9: South Korea | G9: Memphis, TN | I9: https://www.hyosungheavyindustries.com/en/business/power-products/P010104 | P9: Discovery | Q9: 46300 | R9: None | S9: Subsidiary of Hyosung Heavy Industries (KRX-listed) | T9: Not Assessed | U9: Jun 2026: formed JV 'Hyosung HICO Breaker' with Quanta Services; targets 25% US GCB share by 2030. Nov 12, 2025: $157M Memphis transformer expansion. | V9: GCB semi-finished products from Changwon, Korea; final assembly at Quanta's Canonsburg, PA facility from Oct 2026. Korean-origin content — tariff relevance. | W9: Not Assessed | AB9: No - AI seeded | AC9: https://www.koreatimes.co.kr/business/companies/20260918/hyosung-heavy-industries-forms-us-joint-venture-to-make-high-voltage-circuit-breakers
A10: HVB-006 | B10: HD Hyundai Electric (watchlist) | C10: SF6-free switchgear/breakers; 362 kV dead tank breaker planned for 2028 launch | F10: South Korea | P10: Discovery | Q10: 46300 | R10: None | S10: Public (KRX-listed) | T10: Not Assessed | U10: May 7, 2026: ~$119M contract for 765 kV transformers/reactors for an SPP transmission project. | V10: 362 kV dead tank breaker not available until 2028 per source — future-option only. Korean origin; tariff relevance. | W10: Not Assessed | AB10: No - AI seeded | AC10: https://transformer-technology.com/hd-hyundai-electric-expands-us-grid-presence-with-119-million-contract/

Sheet MV Breakers
A1: Medium-voltage breakers / switchgear — Vendor Landscape
A2: Seeded 2026-10-05 from public sources (Discovery stage, unverified). Yellow columns = enter from vendor contact. Confirm all data before use; see Read Me.
A3: Vendor | D3: HQ Location | I3: Contact Information | P3: Qualification | S3: Financial Strength / Bankability | V3: Supply Chain / Origin Risk | X3: Tracking
A4: Vendor ID | B4: Vendor Name | C4: Product Line | D4: HQ City | E4: HQ State / Prov | F4: HQ Country | G4: US HQ (if foreign) | H4: Texas Presence | I4: Website | J4: Main Phone | K4: Contact Page | L4: Primary Contact Name | M4: Contact Title | N4: Contact Email | O4: Contact Phone | P4: Qualification Status | Q4: Status Date | R4: Last RFx Stage | S4: Ownership / Parent | T4: Financial Strength | U4: Financial / Bankability Notes | V4: Manufacturing Origin | W4: Supply Chain Risk | X4: Last Contact Date | Y4: Next Action | Z4: Next Action Due | AA4: Notes | AB4: Data Verified? | AC4: Primary Source
A5: MVB-001 | B5: Eaton | C5: VacClad-HD 38 kV metal-clad switchgear with VCPW-HD vacuum breakers (1,200–3,000 A, up to 40 kA) | D5: Dublin | F5: Ireland | G5: Cleveland (Beachwood), OH | I5: https://www.eaton.com/us/en-us.html | P5: Discovery | Q5: 46300 | R5: None | S5: Public (NYSE: ETN) | T5: Not Assessed | U5: >$1B invested in North American electrical manufacturing since 2023 (Feb 2025). | V5: US manufacturing footprint; confirm plant of origin for 38 kV gear per quote. | W5: Not Assessed | AB5: No - AI seeded | AC5: https://eaton.com/us/en-us/catalog/medium-voltage-power-distribution-control-systems/vacclad-w-38-kv-metal-clad-medium-voltage-switchgear.html
A6: MVB-002 | B6: Schneider Electric | C6: MV switchgear: air-insulated, gas-insulated and shielded solid insulation | D6: Rueil-Malmaison | F6: France | G6: Andover, MA (Boston One campus) | I6: https://www.se.com/us/en/ | P6: Discovery | Q6: 46300 | R6: None | S6: Public (Euronext Paris: SU) | T6: Not Assessed | U6: Nov 11, 2025: opened Mt. Juliet, TN MV switchgear plant (500,000+ sq ft; second 540,000+ sq ft building under construction). | V6: US MV switchgear production in Mt. Juliet, TN; other TN sites Smyrna and Franklin. | W6: Not Assessed | AB6: No - AI seeded | AC6: https://www.se.com/us/en/about-us/newsroom/news/press-releases/Schneider-Electric-Opens-New-Energy-Manufacturing-Facility-in-Middle-Tennessee-68d6a8ba1686eb8d4d047558
A7: MVB-003 | B7: ABB | C7: MV breakers/switchgear and grid components (Electrification); confirm 38 kV outdoor breaker line | D7: Zurich | F7: Switzerland | G7: Cary, NC | I7: https://electrification.us.abb.com | P7: Discovery | Q7: 46300 | R7: None | S7: Public (SIX: ABBN) | T7: Not Assessed | U7: Sep 16, 2025: $110M US manufacturing investment (Richmond VA, Pinetops NC, Senatobia MS, Arecibo PR) incl. LV and MV grid components; ~17,000 US employees. | V7: ~40 US facilities; confirm plant of origin for 34.5 kV equipment per quote. | W7: Not Assessed | AB7: No - AI seeded | AC7: https://new.abb.com/news/detail/129047/abb-to-invest-us110-million-in-us-manufacturing
A8: MVB-004 | B8: Siemens (Smart Infrastructure) | C8: SDV7 / SDV7-AR outdoor distribution vacuum breakers (15.5–38 kV, up to 40 kA, 200 kV BIL) | D8: Munich | F8: Germany | H8: Fort Worth, TX plant (low-voltage switchboards/switchgear; opened Mar 2025) | I8: https://www.siemens.com/us/en.html | J8: +1 (800) 347-6659 | P8: Discovery | Q8: 46300 | R8: None | S8: Public (Frankfurt: SIE) | T8: Not Assessed | U8: Mar 2025: $190M Fort Worth, TX plant (LV equipment; 800 jobs by 2026) as part of $285M two-plant investment. | V8: SDV7 manufactured by Siemens Industry, Inc., Wendell, NC (per product flyer). German parent. | W8: Not Assessed | AB8: No - AI seeded | AC8: https://assets.new.siemens.com/siemens/assets/api/uuid:49344958-3e1b-4282-ac76-e1c7fa185d32/ansi-mv-ovcb-sdv7-flyer-en.pdf
A9: MVB-005 | B9: Powell Industries | C9: ANSI metal-clad (PowlVac, Power/Vac) and metal-enclosed switchgear; E-houses / PCR packaged solutions | D9: Houston | E9: TX | F9: USA | H9: Houston, TX (HQ) | I9: https://www.powellind.com | K9: https://www.powellind.com/contact | P9: Discovery | Q9: 46300 | R9: None | S9: Public (NASDAQ: POWL) | T9: Not Assessed | U9: FY2025 (Sep 30) revenue $1.1B (+9%); backlog $1.4B; acquired Remsdaq Ltd. (UK SCADA RTUs) (Nov 18, 2025 release). | V9: Operations in US, Canada and UK; Texas-based manufacturer. Confirm 38 kV rating availability per product line. | W9: Not Assessed | AB9: No - AI seeded | AC9: https://powellindustriesinc.gcs-web.com/news-releases/news-release-details/powell-industries-announces-fourth-quarter-and-full-year-0
A10: MVB-006 | B10: S&C Electric Company | C10: MV switching and protection (pad-mounted / metal-enclosed switchgear, distribution switching); confirm 34.5 kV collector-system products | D10: Chicago | E10: IL | F10: USA | I10: https://www.sandc.com | P10: Discovery | Q10: 46300 | R10: None | S10: Private | T10: Not Assessed | U10: Mar 2023: 275,000 sq ft Palatine, IL manufacturing expansion; ~3,500 employees globally. | V10: US manufacturing in Chicago area (Rogers Park HQ campus; Palatine, IL). | W10: Not Assessed | AB10: No - AI seeded | AC10: https://www.sandc.com/en/company/
A11: MVB-007 | B11: G&W Electric | C11: Switchgear, reclosers, overhead switches, current-limiting protection, cable accessories; confirm 38 kV ratings | D11: Bolingbrook | E11: IL | F11: USA | I11: https://www.gwelectric.com | P11: Discovery | Q11: 46300 | R11: None | S11: Private (Mueller family; Chairman/owner John H. Mueller) | T11: Not Assessed | U11: Acquired Veneta Isolatori SpA (Italy). No revenue data published in sources reviewed. | V11: HQ and manufacturing in Bolingbrook, IL; facility in Italy. Confirm origin per product. | W11: Not Assessed | AB11: No - AI seeded | AC11: https://www.gwelectric.com/about/

Sheet EPC
A1: EPC contractor services — Vendor Landscape
A2: Seeded 2026-10-05 from public sources (Discovery stage, unverified). Yellow columns = enter from vendor contact. Confirm all data before use; see Read Me.
A3: Vendor | D3: HQ Location | I3: Contact Information | P3: Qualification | S3: Financial Strength / Bankability | V3: Supply Chain / Origin Risk | X3: Tracking
A4: Vendor ID | B4: Vendor Name | C4: EPC Scope | D4: HQ City | E4: HQ State / Prov | F4: HQ Country | G4: US HQ (if foreign) | H4: Texas Presence | I4: Website | J4: Main Phone | K4: Contact Page | L4: Primary Contact Name | M4: Contact Title | N4: Contact Email | O4: Contact Phone | P4: Qualification Status | Q4: Status Date | R4: Last RFx Stage | S4: Ownership / Parent | T4: Financial Strength | U4: Financial / Bankability Notes | V4: Labor / Delivery Origin | W4: Supply Chain Risk | X4: Last Contact Date | Y4: Next Action | Z4: Next Action Due | AA4: Notes | AB4: Data Verified? | AC4: Primary Source
A5: EPC-001 | B5: Mortenson | C5: Full EPC for utility-scale BESS incl. project substation and gen-tie (e.g., Revolution 150 MW / 300 MWh, Crane TX, ERCOT) | D5: Minneapolis | E5: MN | F5: USA | H5: San Antonio | I5: https://www.mortenson.com | J5: 763.522.2100 | K5: https://www.mortenson.com/contact | P5: Discovery | Q5: 46300 | R5: None | S5: Private (M. A. Mortenson Company) | T5: Not Assessed | U5: #1 utility-scale storage installer in Solar Power World 2026 list (5,776 MWh installed in 2025) | W5: Not Assessed | AB5: No - AI seeded | AC5: https://www.mortenson.com/projects/revolution-energy-storage
A6: EPC-002 | B6: McCarthy Building Companies | C6: Renewable Energy & Storage group: utility-scale BESS and solar EPC | D6: St. Louis | E6: MO | F6: USA | H6: Austin; Dallas (Richardson); Houston; Channelview | I6: https://www.mccarthy.com | J6: 314-968-3300 | K6: https://www.mccarthy.com/contact-us | P6: Discovery | Q6: 46300 | R6: None | S6: Private; 100% employee-owned | T6: Not Assessed | U6: #2 utility-scale storage installer in Solar Power World 2026 list (4,188 MWh installed in 2025); founded 1864 | W6: Not Assessed | AB6: No - AI seeded | AC6: https://www.mccarthy.com/locations/st-louis
A7: EPC-003 | B7: Blattner (Quanta Services) | C7: Utility-scale wind, solar and energy storage construction/EPC incl. HV substation and collection | D7: Avon | E7: MN | F7: USA | I7: https://www.blattnercompany.com | J7: 320-356-7351 | K7: https://www.blattnercompany.com/contact | P7: Discovery | Q7: 46300 | R7: None | S7: Subsidiary of Quanta Services, Inc. (NYSE: PWR); acquisition completed Oct 14, 2021 | T7: Not Assessed | U7: Says it has installed 20%+ of US utility-scale wind, solar and storage capacity; parent Quanta ranked #3 storage installer in Solar Power World 2026 (2,520 MWh) | W7: Not Assessed | AB7: No - AI seeded | AC7: https://www.quantaservices.com/companies/blattner
A8: EPC-004 | B8: Burns & McDonnell | C8: Self-perform EPC for BESS, substations and transmission; Texas BESS EPC references | D8: Kansas City | E8: MO | F8: USA | H8: Amarillo; Austin; Dallas-Fort Worth; Houston; Pearland; San Antonio | I8: https://www.burnsmcd.com | J8: (816) 333-9400 | K8: https://info.burnsmcd.com/contact-us | P8: Discovery | Q8: 46300 | R8: None | S8: Private; 100% employee-owned | T8: Not Assessed | U8: 75+ offices worldwide | W8: Not Assessed | AB8: No - AI seeded | AC8: https://www.burnsmcd.com/news/epc-contract-for-west-texas-storage-projects
A9: EPC-005 | B9: Primoris Services (Primoris Renewable Energy) | C9: Utility-scale solar and BESS EPC; T&D/substation via Primoris T&D and Power Line Services | D9: Dallas | E9: TX | F9: USA | H9: Dallas (corporate HQ); Fort Worth; Houston; The Woodlands; Converse; Balch Springs; Heath | I9: https://www.prim.com | J9: (214) 740-5600 | K9: https://www.prim.com/contact | P9: Discovery | Q9: 46300 | R9: None | S9: Public (NYSE: PRIM) | T9: Not Assessed | U9: FY2025 revenue $7.6B (+19%); Energy segment $5.0B; renewables revenue >$3B; backlog $11.9B; Primoris Renewable Energy HQ Aurora, CO (720-374-3900) | W9: Not Assessed | AB9: No - AI seeded | AC9: https://www.prim.com/contact
A10: EPC-006 | B10: Rosendin | C10: Electrical contractor/EPC for utility-scale wind, solar, BESS and HV substation | D10: San Jose | E10: CA | F10: USA | H10: Austin; Coppell; Pflugerville; San Antonio | I10: https://www.rosendin.com | J10: (408) 286-2800 | K10: https://www.rosendin.com/contact/ | P10: Discovery | Q10: 46300 | R10: None | S10: Private; 100% employee-owned (ESOP) | T10: Not Assessed | U10: Founded 1919; 12,000+ employees; ~US$5.6B annual revenue (company history page) | W10: Not Assessed | AB10: No - AI seeded | AC10: https://www.rosendin.com/contact/
A11: EPC-007 | B11: SOLV Energy | C11: Utility-scale solar and BESS EPC, substation/HV, and O&M | D11: San Diego | E11: CA | F11: USA | I11: https://solvenergy.com | J11: 858.251.4888 | K11: https://solvenergy.com/contact/ | P11: Discovery | Q11: 46300 | R11: None | S11: Public (Nasdaq: MWH) since Feb 2026 IPO; sponsor American Securities | T11: Not Assessed | U11: IPO priced Feb 11, 2026 at $25 (~$513M raised); #4 utility-scale storage installer in Solar Power World 2026 (1,648 MWh) | W11: Not Assessed | AB11: No - AI seeded | AC11: https://solvenergy.com/contact/
A12: EPC-008 | B12: MasTec Renewables (incl. former IEA, Wanzek, White Construction) | C12: Utility-scale solar, wind and battery storage EPC; parent also provides transmission and substation (Power Delivery segment) | D12: Coral Gables | E12: FL | F12: USA | I12: https://www.mastec.com | P12: Discovery | Q12: 46300 | R12: None | S12: Subsidiary/unit of MasTec, Inc. (NYSE: MTZ); MasTec acquired IEA Oct 7, 2022; IEA, Wanzek and White rebranded as MasTec Renewables | T12: Not Assessed | U12: MasTec FY2025 revenue ~$14.2B; Clean Energy & Infrastructure segment ~$4.7B; ~36,000 employees; iea.net now redirects to mastec.com | V12: Operates in both union and open-shop markets | W12: Not Assessed | AB12: No - AI seeded | AC12: https://mastec.com/expertise/clean-energy-and-infrastructure/renewables.html

Sheet Software
A1: Software (QSE, EMS, APM, market data) — Vendor Landscape
A2: Seeded 2026-10-05 from public sources (Discovery stage, unverified). Yellow columns = enter from vendor contact. Confirm all data before use; see Read Me.
A3: Vendor | D3: HQ Location | I3: Contact Information | P3: Qualification | S3: Financial Strength / Bankability | V3: Supply Chain / Origin Risk | X3: Tracking
A4: Vendor ID | B4: Vendor Name | C4: Sub-scope / Product | D4: HQ City | E4: HQ State / Prov | F4: HQ Country | G4: US HQ (if foreign) | H4: Texas Presence | I4: Website | J4: Main Phone | K4: Contact Page | L4: Primary Contact Name | M4: Contact Title | N4: Contact Email | O4: Contact Phone | P4: Qualification Status | Q4: Status Date | R4: Last RFx Stage | S4: Ownership / Parent | T4: Financial Strength | U4: Financial / Bankability Notes | V4: Hosting / Development Origin | W4: Supply Chain Risk | X4: Last Contact Date | Y4: Next Action | Z4: Next Action Due | AA4: Notes | AB4: Data Verified? | AC4: Primary Source
A5: SW-001 | B5: Tesla, Inc. (Tesla Energy) | C5: (a)/(b) Trading & BESS optimization - Autobidder (real-time trading and dispatch control platform) | D5: Austin | E5: TX | F5: USA | H5: HQ: 1 Tesla Road, Austin, TX 78725 (Gigafactory Texas) | I5: https://www.tesla.com/support/energy/tesla-software/autobidder | K5: https://www.tesla.com/contact | P5: Discovery | Q5: 46300 | R5: None | S5: Public (NASDAQ: TSLA) | T5: Not Assessed | U5: Autobidder described by Tesla as a real-time trading and control platform for market bidding and dispatch; Tesla page cites Hornsdale Power Reserve (S. Australia); official Autobidder page does not explicitly mention ERCOT. Support email on official page: autobiddersupport@tesla.com. (Tesla energy toll-free 877-798-3752 is residential Powerwall/Solar support, not listed as general line.) | V5: Official page: runs on Tesla's cloud infrastructure and interfaces with market operators via secure web APIs. No SOC 2/NERC CIP statement found. | W5: Not Assessed | AB5: No - AI seeded | AC5: https://www.tesla.com/support/energy/tesla-software/autobidder
A6: SW-002 | B6: Fluence Energy (Fluence Mosaic / Nispera) | C6: (a)/(b) Fluence Mosaic intelligent bidding software (launched in ERCOT Feb 2023); (c) Fluence Nispera APM | D6: Arlington | E6: VA | F6: USA | H6: Houston (listed among Fluence office locations on contact page; street address not confirmed) | I6: https://fluenceenergy.com | K6: https://fluenceenergy.com/contact/ | P6: Discovery | Q6: 46300 | R6: None | S6: Public (NASDAQ: FLNC) | T6: Not Assessed | U6: Mosaic launched in ERCOT Feb 22, 2023 with 350+ MW of storage scheduled that year; acquired Nispera (Zurich; ~8 GW / 450 wind & solar projects under APM) announced Apr 11, 2022. | V6: Nispera originally developed in Zurich, Switzerland. No SOC 2/NERC CIP statement found on pages reviewed. | W6: Not Assessed | AB6: No - AI seeded | AC6: https://fluenceenergy.com/contact/
A7: SW-003 | B7: Ascend Analytics | C7: (a)/(d) SmartBidder (nodal price forecasting & bid optimization); Market Intelligence, PowerSIMM, PowerVAL | D7: Boulder | E7: CO | F7: USA | I7: https://www.ascendanalytics.com | J7: 1-303-415-1400 | K7: https://www.ascendanalytics.com/about-us/lets-connect | P7: Discovery | Q7: 46300 | R7: None | S7: Private, PE-backed (Rubicon Technology Partners lead; Galvanize Climate Solutions; Silversmith Capital Partners) | T7: Not Assessed | U7: Strategic growth investment led by Rubicon Technology Partners with Galvanize and Silversmith announced Mar 21, 2024 (amount undisclosed); co-founded 2002. | W7: Not Assessed | AB7: No - AI seeded | AC7: https://www.ascendanalytics.com/
A8: SW-004 | B8: PCI Energy Solutions (Power Costs, Inc.) | C8: (a) ERCOT QSE / bid-to-bill - GenManager (forecast, ISO scheduling, settlements) and GenTrader (portfolio/storage optimization) | D8: Norman | E8: OK | F8: USA | I8: https://www.pcienergysolutions.com | J8: +1 405.447.6933 | K8: https://www.pcienergysolutions.com/contact-us/ | P8: Discovery | Q8: 46300 | R8: None | S8: Private (held by individual U.S. shareholders); definitive agreement to be acquired by Mitsubishi Electric (TSE: 6503) | T8: Not Assessed | U8: Mitsubishi Electric agreed Aug 20, 2026 to acquire 100% of PCI for ~US$1.4B, expected to close within 2026 subject to regulatory approvals; PCI says 50%+ of North American power optimized on its platform. | V8: Website cites a cloud-native platform; no explicit SOC 2/NERC CIP statement found. Offices also in Mexico City and Lima. | W8: Not Assessed | AB8: No - AI seeded | AC8: https://www.pcienergysolutions.com/contact-us/
A9: SW-005 | B9: Yes Energy | C9: (d) Market data & analytics (PowerSignals, QuickSignals, Live Power, Demand Forecasts, EnCompass); (a) bid-to-bill (PowerCore, Submission Services) | D9: Boulder | E9: CO | F9: USA | I9: https://www.yesenergy.com | J9: +1 303-993-2773 | K9: https://www.yesenergy.com/locations | P9: Discovery | Q9: 46300 | R9: None | S9: Private, PE-backed (Accel-KKR portfolio company since 2022) | T9: Not Assessed | U9: Accel-KKR invested 2022; acquisitions incl. Power Settlements (bid-to-bill) and TESLA Inc. forecasting (2024), The C Three Group and Live Power; processes ~1.2B daily updates from 1,400+ sources. | W9: Not Assessed | AB9: No - AI seeded | AC9: https://www.yesenergy.com/
A10: SW-006 | B10: Enverus | C10: (d) Market data & analytics / forecasting - Enverus Power & Renewables (Mosaic, Panorama, MarketView, Trading & Risk) | D10: Austin | E10: TX | F10: USA | H10: HQ: 2901 Via Fortuna #100, Austin, TX 78746 | I10: https://www.enverus.com | J10: 1-800-282-4245 | K10: https://www.enverus.com/contact-us/ | P10: Discovery | Q10: 46300 | R10: None | S10: Private, PE-backed (Blackstone agreed to acquire from Hellman & Friedman and Genstar Capital; announced Aug 5, 2025, expected close by end of 2025 - closing not confirmed in sources reviewed) | T10: Not Assessed | U10: Blackstone acquisition announced Aug 5, 2025 (value not disclosed in release; press reports ~$6.5B); ~8,000 customers in 50 countries. | W10: Not Assessed | AB10: No - AI seeded | AC10: https://www.enverus.com/contact-us/
A11: SW-007 | B11: Power Factors | C11: (c) Asset performance management / SCADA / EMS - Unity platform (Drive APM, local monitoring & controls) | D11: San Francisco | E11: CA | F11: USA | I11: https://www.powerfactors.com | J11: 1-866-398-3010 | K11: https://www.powerfactors.com/contact | P11: Discovery | Q11: 46300 | R11: None | S11: Private, PE-backed (Vista Equity Partners majority since 2021; Mubadala strategic minority investor 2026) | T11: Not Assessed | U11: 310+ GW under management, 600+ enterprise customers in 70+ countries (per About page); Mubadala joined as minority investor in 2026. | V11: About page states founded in San Francisco (2013) with operations in North America and Europe; HQ city based on founding location - current HQ address not published on pages reviewed. No SOC 2/NERC CIP statement found. | W11: Not Assessed | AB11: No - AI seeded | AC11: https://www.powerfactors.com/about
A12: SW-008 | B12: Habitat Energy | C12: (a)/(b) BESS optimization & trading service incl. Level 4 QSE services in ERCOT (EVOLVE) | D12: Oxford | E12: England | F12: United Kingdom | H12: 300 W. 6th St, Suite 1960, Austin, TX 78701 | I12: https://www.habitat.energy | K12: https://www.habitat.energy/contact | P12: Discovery | Q12: 46300 | R12: None | S12: Private; portfolio company of Quinbrook Infrastructure Partners | T12: Not Assessed | U12: May 2024: contracted to optimize UBS Asset Management's 730 MW ERCOT BESS portfolio, taking ERCOT contracted capacity to ~1 GW and global portfolio to 2+ GW; 90+ employees. | W12: Not Assessed | AB12: No - AI seeded | AC12: https://www.habitat.energy/contact
A13: SW-009 | B13: Tyba | C13: (b)/(d) BESS simulation, automated dispatch/bidding and AI price forecasting platform | D13: San Francisco | E13: CA | F13: USA | I13: https://www.tyba.ai | K13: https://www.tyba.ai/contact/ | P13: Discovery | Q13: 46300 | R13: None | S13: Private, VC-backed (Series A led by Energize Capital) | T13: Not Assessed | U13: Raised $13.9M Series A led by Energize Capital (Feb 7, 2025); operates 1+ GWh of storage across Texas and California. | W13: Not Assessed | AB13: No - AI seeded | AC13: https://www.tyba.ai/
A14: SW-010 | B14: Modo Energy | C14: (d) Market data, BESS revenue benchmarks & forecasts (ERCOT coverage) | D14: London | E14: England | F14: United Kingdom | I14: https://modoenergy.com | P14: Discovery | Q14: 46300 | R14: None | S14: Private, VC-backed (Molten Ventures, ETF Partners, MMC Ventures, Fred. Olsen) | T14: Not Assessed | U14: Raised ~$33M (GBP 25M) Series B led by Molten Ventures (reported Dec 2025), following $15M Series A led by MMC (Nov 2023). | V14: Website lists teams in New York (Americas), London and Madrid, and Sydney; HQ as UK per ESS News. Benchmarks described as FCA-regulated. | W14: Not Assessed | AB14: No - AI seeded | AC14: https://modoenergy.com/
A15: SW-011 | B15: Stem, Inc. | C15: (b)/(c) PowerTrack Suite - PowerTrack EMS, PowerTrack Optimizer (formerly Athena), PowerTrack APM/monitoring (AlsoEnergy) | D15: Houston | E15: TX | F15: USA | H15: HQ: 1400 Post Oak Blvd, Suite 560, Houston, TX 77056 | I15: https://www.stem.com | J15: 877-374-7836 | K15: https://www.stem.com/contact/ | P15: Discovery | Q15: 46300 | R15: None | S15: Public (NYSE: STEM) | T15: Not Assessed | U15: Sept 2025 strategic realignment: unified brand with AlsoEnergy, launched PowerTrack EMS and rebranded Athena as PowerTrack Optimizer; 600+ employees. | V15: Offices also in Broomfield & Longmont CO, Berlin, Gurgaon, Tokyo. | W15: Not Assessed | AB15: No - AI seeded | AC15: https://www.stem.com/contact/
A16: SW-012 | B16: Tenaska Power Services Co. (TPS) | C16: (a) QSE service provider - power marketing, 24/7 energy management, storage/renewable portfolio optimization, settlements | D16: Irving | E16: TX | F16: USA | H16: TPS HQ: The Point at Las Colinas, 300 E. John Carpenter Freeway, Suite 1100, Irving, TX 75062 | I16: https://www.tenaska.com/our-business/power-marketing/ | J16: 817-462-1521 | K16: https://www.tenaska.com/contact-us/ | P16: Discovery | Q16: 46300 | R16: None | S16: Subsidiary of Tenaska (privately held; HQ Omaha, NE) | T16: Not Assessed | U16: 18,500+ MW wholesale/retail load management, 650+ enabling agreements, 29 years of energy management services; serves energy storage customers. | V16: Official page does not use the term 'QSE' explicitly; QSE role not confirmed from an official source (only historical ERCOT/SEC references seen in search results) - verify current ERCOT QSE registration. | W16: Not Assessed | AB16: No - AI seeded | AC16: https://www.tenaska.com/our-business/power-marketing/

Sheet Lists
A1: Qualification Status | B1: Last RFx Stage | C1: Financial Strength | D1: Supply Chain Risk | E1: Data Verified?
A2: Discovery | B2: None | C2: Strong | D2: Low | E2: No - AI seeded
A3: Prequalified | B3: RFI Sent | C3: Adequate | D3: Medium | E3: Yes - Verified
A4: Qualified | B4: RFI Received | C4: Weak | D4: High
A5: AVL | B5: RFP Sent | C5: Not Assessed | D5: FEOC Review
A6: On Hold | B6: RFP Received | D6: Not Assessed
A7: Disqualified | B7: RFQ Sent
B8: RFQ Received
B9: Awarded

Sheet Sources
A1: Vendor ID | B1: Vendor | C1: Tab | D1: Source URL (accessed 2026-10-05)
A2: ENV-001 | B2: ERM (Environmental Resources Management) | C2: Env Eng | D2: https://en.wikipedia.org/wiki/ERM_(consultancy)
A3: ENV-001 | B3: ERM (Environmental Resources Management) | C3: Env Eng | D3: https://www.erm.com/locations/
A4: ENV-001 | B4: ERM (Environmental Resources Management) | C4: Env Eng | D4: https://www.erm.com/contact-us/
A5: ENV-002 | B5: Tetra Tech, Inc. | C5: Env Eng | D5: https://www.tetratech.com/contact/
A6: ENV-002 | B6: Tetra Tech, Inc. | C6: Env Eng | D6: https://en.wikipedia.org/wiki/Tetra_Tech
A7: ENV-002 | B7: Tetra Tech, Inc. | C7: Env Eng | D7: https://tetratech.com/en/united-states
A8: ENV-003 | B8: Stantec Inc. | C8: Env Eng | D8: https://en.wikipedia.org/wiki/Stantec
A9: ENV-003 | B9: Stantec Inc. | C9: Env Eng | D9: https://www.stantec.com/en/offices/united-states-locations/texas-offices
A10: ENV-003 | B10: Stantec Inc. | C10: Env Eng | D10: https://www.stantec.com/en/offices/united-states-locations/texas-offices/houston-tx
A11: ENV-003 | B11: Stantec Inc. | C11: Env Eng | D11: https://www.stantec.com/en/offices/united-states-locations/texas-offices/san-antonio-texas-office
A12: ENV-004 | B12: WSP Global Inc. (WSP USA) | C12: Env Eng | D12: https://en.wikipedia.org/wiki/WSP_Global
... A323: SW-012 | B323: Tenaska Power Services Co. (TPS) | C323: Software | D323: https://www.tenaska.com/
